Workbook

Sheet Final Summary
A1: Main Benchmark
A2: Total Issues: 225 | B2: Total F2P: 75
A4: By Models
A5: Model: gpt-4.1-mini
A7: No. | B7: Pipeline | C7: F2P App (w/ in-Patch) | D7: F2P App (w/o in-patch) | E7: F2P App | F7: F2P Framework (w/ in-Patch) | G7: F2P Framework (w/o in-patch) | H7: F2P Framework | I7: Total F2P (w/ in-patch) | J7: Total F2P (w/o in-patch) | K7: Total F2P | L7: Avg. Duration | M7: Avg. Cost | N7: Avg. Token Consumption | O7: Env. build | P7: Avg. Input Token | Q7: Avg. Output Token
A8: 1 | B8: AgentBug-Smith | C8: =3+0+0+0 -> 3 | D8: =6+3+4+0 -> 13 | E8: =C8+D8 -> 16 | F8: =6+1+14+0 -> 21 | G8: =4+0+2+2 -> 8 | H8: =F8+G8 -> 29 | I8: =C8+F8 -> 24 | J8: =D8+G8 -> 21 | K8: =I8+J8 -> 45 | L8: 58m 10s | M8: =((P8/1000000)*0.4)+((Q8/1000000)*1.6) -> 0.5595124 | N8: =P8+Q8 -> 1287247 | O8: 84 | P8: 1250069 | Q8: 37178
A9: 2 | B9: SWE-Factory | C9: =3+0+0+0 -> 3 | D9: 0 | E9: =C9+D9 -> 3 | F9: =8+0+10+0 -> 18 | G9: 0 | H9: =F9+G9 -> 18 | I9: =C9+F9 -> 21 | J9: =D9+G9 -> 0 | K9: =I9+J9 -> 21 | L9: 5m 45s | M9: =((P9/1000000)*0.4)+((Q9/1000000)*1.6) -> 0.0906424 | N9: =P9+Q9 -> 167176 | O9: 36 | P9: 147366 | Q9: 19810
A10: 3 | B10: SWE-bench-Live | C10: =1+0+0+0 -> 1 | D10: 0 | E10: =C10+D10 -> 1 | F10: =3+1+1+0 -> 5 | G10: 0 | H10: =F10+G10 -> 5 | I10: =C10+F10 -> 6 | J10: =D10+G10 -> 0 | K10: =I10+J10 -> 6 | L10: 22m 19s | M10: =((P10/1000000)*0.4)+((Q10/1000000)*1.6) -> 0.4091236 | N10: =P10+Q10 -> 1007209 | O10: 33 | P10: 1002009 | Q10: 5200
A12: Model: Deepseek-v3.2
A14: No. | B14: Pipeline | C14: F2P App (w/ in-Patch) | D14: F2P App (w/o in-patch) | E14: F2P App | F14: F2P Framework (w/ in-Patch) | G14: F2P Framework (w/o in-patch) | H14: F2P Framework | I14: Total F2P (w/ in-patch) | J14: Total F2P (w/o in-patch) | K14: Total F2P | L14: Avg. Duration | M14: Avg. Cost | N14: Avg. Token Consumption | O14: Env. build | P14: Avg. Input Token | Q14: Avg. Output Token
A15: 1 | B15: AgentBug-Smith | C15: 5 | D15: 21 | E15: =C15+D15 -> 26 | F15: 29 | G15: 8 | H15: =F15+G15 -> 37 | I15: =F15+C15 -> 34 | J15: =G15+D15 -> 29 | K15: =I15+J15 -> 63 | L15: 76m 26s | M15: =((P15/1000000)*0.28)+((Q15/1000000)*0.4) -> 2.4390618 | N15: =P15+Q15 -> 8667177 | O15: 93 | P15: 8565075 | Q15: 102102
A16: 2 | B16: SWE-Factory | C16: 3 | D16: 0 | E16: =C16+D16 -> 3 | F16: 28 | G16: 0 | H16: =F16+G16 -> 28 | I16: =F16+C16 -> 31 | J16: =G16+D16 -> 0 | K16: =I16+J16 -> 31 | L16: 6m 27s | M16: =((P16/1000000)*0.28)+((Q16/1000000)*0.4) -> 0.30701028 | N16: =P16+Q16 -> 1039926 | O16: 44 | P16: 908001 | Q16: 131925
A17: 3 | B17: SWE-bench-Live | C17: 0 | D17: 0 | E17: =C17+D17 -> 0 | F17: 1 | G17: 0 | H17: =F17+G17 -> 1 | I17: =F17+C17 -> 1 | J17: =G17+D17 -> 0 | K17: =I17+J17 -> 1 | L17: 17m 22s | M17: =((P17/1000000)*0.28)+((Q17/1000000)*0.4) -> 1.0495557 | N17: =P17+Q17 -> 3738206 | O17: 14 | P17: 3714389 | Q17: 23817
A19: Model: Kimi-k2.5
A21: No. | B21: Pipeline | C21: F2P App (w/ in-Patch) | D21: F2P App (w/o in-patch) | E21: F2P App | F21: F2P Framework (w/ in-Patch) | G21: F2P Framework (w/o in-patch) | H21: F2P Framework | I21: Total F2P (w/ in-patch) | J21: Total F2P (w/o in-patch) | K21: Total F2P | L21: Avg. Duration | M21: Avg. Cost | N21: Avg. Token Consumption | O21: Env. build | P21: Avg. Input Token | Q21: Avg. Output Token
A22: 1 | B22: AgentBug-Smith | C22: 3 | D22: 22 | E22: =C22+D22 -> 25 | F22: 17 | G22: 4 | H22: =F22+G22 -> 21 | I22: =C22+F22 -> 20 | J22: =D22+G22 -> 26 | K22: =J22+I22 -> 46 | L22: 57m 15s | M22: =((P22/1000000)*0.6)+((Q22/1000000)*3) -> 0.9140562 | N22: =P22+Q22 -> 1285523 | O22: 53 | P22: 1226047 | Q22: 59476
A23: 2 | B23: SWE-Factory | C23: 2 | D23: 0 | E23: =C23+D23 -> 2 | F23: 17 | G23: 0 | H23: =F23+G23 -> 17 | I23: =C23+F23 -> 19 | J23: =D23+G23 -> 0 | K23: =J23+I23 -> 19 | L23: 4m 48s | M23: =((P23/1000000)*0.6)+((Q23/1000000)*3) -> 0.365214 | N23: =P23+Q23 -> 592602 | O23: 27 | P23: 588580 | Q23: 4022
A24: 3 | B24: SWE-bench-Live | C24: 2 | D24: 0 | E24: =C24+D24 -> 2 | F24: 4 | G24: 0 | H24: =F24+G24 -> 4 | I24: =C24+F24 -> 6 | J24: =D24+G24 -> 0 | K24: =J24+I24 -> 6 | L24: 25m 14s | M24: =((P24/1000000)*0.6)+((Q24/1000000)*3) -> 0.6554874 | N24: =P24+Q24 -> 1065259 | O24: 29 | P24: 1058454 | Q24: 6805
A28: Repository Distribution
A30: Agent Frameworks | B30: Agent Applications
A31: No. | B31: Repository | C31: Link | D31: Stars | E31: License | F31: Total Issues with In-Patch Test | G31: Total Issues without In-Patch Test | H31: Total Issues | I31: Total F2P
I32: GPT-4.1-Mini | J32: Deepseek-v3.2 | K32: Kimi-k2.5
A33: 1 | B33: dapr/dapr-agents | C33: https://github.com/dapr/dapr-agents/ | D33: 743 | E33: Apache-2.0 license | F33: 1 | G33: 2 | H33: 3 | I33: 1 | J33: 2 | K33: 2
A34: 2 | B34: VoltAgent/voltagent | C34: https://github.com/VoltAgent/voltagent/ | D34: 7.1k | E34: MIT license | F34: 0 | G34: 1 | H34: 1 | I34: 0 | J34: 0 | K34: 0
A35: 3 | B35: agentscope-ai/agentscope | C35: https://github.com/agentscope-ai/agentscope/ | D35: 22.5k | E35: Apache-2.0 license | F35: 10 | G35: 19 | H35: 29 | I35: 15 | J35: 15 | K35: 10
A36: 4 | B36: crewAIInc/crewAI | C36: https://github.com/crewAIInc/crewAI | D36: 47.6k | E36: MIT license | F36: 28 | G36: 21 | H36: 49 | I36: 12 | J36: 15 | K36: 4
A37: 5 | B37: strands-agents/harness-sdk | C37: https://github.com/strands-agents/sdk-python | D37: 5.5k | E37: Apache-2.0 license | F37: 1 | G37: 0 | H37: 1 | I37: 1 | J37: 0 | K37: 1
A38: 6 | B38: mastra-ai/mastra | C38: https://github.com/mastra-ai/mastra | D38: 22.5k | E38: Apache-2.0 license | F38: 0 | G38: 3 | H38: 3 | I38: 0 | J38: 0 | K38: 0
A39: 7 | B39: langchain-ai/langgraph | C39: https://github.com/langchain-ai/langgraph | D39: 28.4k | E39: MIT license | F39: 11 | G39: 2 | H39: 13 | I39: 0 | J39: 5 | K39: 4
A40: 8 | B40: langflow-ai/langflow | C40: https://github.com/langflow-ai/langflow | D40: 148k | E40: MIT license | F40: 9 | G40: 2 | H40: 11 | I40: 0 | J40: 0 | K40: 0
A41: 9 | B41: geekan/MetaGPT | C41: https://github.com/geekan/MetaGPT | D41: 67.9k | E41: MIT license | F41: 7 | G41: 5 | H41: 12 | I41: 0 | J41: 0 | K41: 0
A42: 10 | B42: tensorzero/tensorzero | C42: https://github.com/tensorzero/tensorzero | D42: 11.4k | E42: Apache-2.0 license | F42: 11 | G42: 0 | H42: 11 | I42: 0 | J42: 0 | K42: 0
A43: 11 | B43: Significant-Gravitas/AutoGPT | C43: https://github.com/Significant-Gravitas/AutoGPT | D43: 183k | E43: MIT License & PolyForm Shield License 1.0.0 | F43: 10 | G43: 3 | H43: 13 | I43: 0 | J43: 2 | K43: 0
A44: 12 | B44: MLSysOps/MLE-agent | C44: https://github.com/MLSysOps/MLE-agent/ | D44: 1.5k | E44: MIT license | F44: 0 | G44: 21 | H44: 21 | I44: 6 | J44: 9 | K44: 10
A45: 13 | B45: always-further/AgentUp | C45: https://github.com/always-further/AgentUp/ | D45: 126 | E45: Apache-2.0 license | F45: 0 | G45: 2 | H45: 2 | I45: 0 | J45: 0 | K45: 0
A46: 14 | B46: Canner/WrenAI | C46: https://github.com/Canner/WrenAI | D46: 14.9k | E46: AGPL-3.0 license | F46: 0 | G46: 1 | H46: 1 | I46: 0 | J46: 0 | K46: 0
A47: 15 | B47: reworkd/AgentGPT | C47: https://github.com/reworkd/AgentGPT | D47: 35.9k | E47: GPL-3.0 license | F47: 1 | G47: 4 | H47: 5 | I47: 0 | J47: 0 | K47: 0
A48: 16 | B48: Aider-AI/aider | C48: https://github.com/Aider-AI/aider | D48: 42.8k | E48: Apache-2.0 license | F48: 1 | G48: 6 | H48: 7 | I48: 5 | J48: 7 | K48: 5
A49: 17 | B49: ValueCell-ai/valuecell | C49: https://github.com/ValueCell-ai/valuecell | D49: 10.2k | E49: Apache-2.0 license | F49: 0 | G49: 5 | H49: 5 | I49: 0 | J49: 0 | K49: 0
A50: 18 | B50: AntonOsika/gpt-engineer | C50: https://github.com/AntonOsika/gpt-engineer | D50: 55.2k | E50: MIT license | F50: 9 | G50: 10 | H50: 19 | I50: 5 | J50: 7 | K50: 9
A51: 19 | B51: OpenInterpreter/open-interpreter | C51: https://github.com/OpenInterpreter/open-interpreter | D51: 11.4k | E51: Apache-2.0 license | F51: 0 | G51: 12 | H51: 12 | I51: 0 | J51: 1 | K51: 1
A52: 20 | B52: lobehub/lobehub | C52: https://github.com/lobehub/lobehub | D52: 77k | E52: Apache-2.0 license | F52: 7 | G52: 0 | H52: 7 | I52: 0 | J52: 0 | K52: 0
B53: TOTAL | F53: =SUM(F33:F52) -> 106 | G53: =SUM(G33:G52) -> 119 | H53: =SUM(H33:H52) -> 225 | I53: =SUM(I33:I52) -> 45 | J53: =SUM(J33:J52) -> 63 | K53: =SUM(K33:K52) -> 46
A57: Models Distribution
A59: No. | B59: Distribution | C59: F2P with In-Patch Test | D59: F2P without In-Patch Test | E59: Total F2P | F59: %
A60: 1 | B60: GPT only | C60: 0 | D60: 4 | E60: 4 | F60: =E60/225 -> 0.017777778
A61: 2 | B61: Deepseek only | C61: 6 | D61: 7 | E61: 13 | F61: =E61/225 -> 0.057777778
A62: 3 | B62: Kimi only | C62: 0 | D62: 3 | E62: 3 | F62: =E62/225 -> 0.013333333
A63: 4 | B63: GPT | Deepseek | C63: 9 | D63: 3 | E63: 12 | F63: =E63/225 -> 0.053333333
A64: 5 | B64: GPT | Kimi | C64: 0 | D64: 5 | E64: 5 | F64: =E64/225 -> 0.022222222
A65: 6 | B65: Deepseek | Kimi | C65: 5 | D65: 9 | E65: 14 | F65: =E65/225 -> 0.062222222
A66: 7 | B66: GPT | Deepseek | Kimi | C66: 14 | D66: 10 | E66: 24 | F66: =E66/225 -> 0.10666667
B67: TOTAL | E67: =SUM(E60:E66) -> 75 | F67: =E67/225 -> 0.33333333
A71: F2P - Repos Distribution (*Each issue is counted once, regardless of how many models achieve F2P)
A73: No. | B73: Repository | C73: Total F2P
A74: 1 | B74: AntonOsika/gpt-engineer | C74: 10
A75: 2 | B75: MLSysOps/MLE-agent | C75: 14
A76: 3 | B76: agentscope-ai/agentscope | C76: 16
A77: 4 | B77: dapr/dapr-agents | C77: 2
A78: 5 | B78: OpenInterpreter/open-interpreter | C78: 2
A79: 6 | B79: Aider-AI/aider | C79: 7
A80: 7 | B80: strands-agents/harness-sdk | C80: 1
A81: 8 | B81: crewAIInc/crewAI | C81: 16
A82: 9 | B82: Significant-Gravitas/AutoGPT | C82: 2
A83: 10 | B83: langchain-ai/langgraph | C83: 5
B84: TOTAL | C84: =SUM(C74:C83) -> 75
A88: Additional Data for Baselines
A90: No, | B90: Distribution | C90: Total F2P
C91: SWE-Factory | D91: % | E91: SWE-bench-Live | F91: %
A92: 1 | B92: GPT only | C92: 4 | D92: =C92/225 -> 0.017777778 | E92: 4 | F92: =E92/225 -> 0.017777778
A93: 2 | B93: Deepseek only | C93: 9 | D93: =C93/225 -> 0.04 | E93: 0 | F93: =E93/225 -> 0
A94: 3 | B94: Kimi only | C94: 0 | D94: =C94/225 -> 0 | E94: 3 | F94: =E94/225 -> 0.013333333
A95: 4 | B95: GPT | Deepseek | C95: 5 | D95: =C95/225 -> 0.022222222 | E95: 0 | F95: =E95/225 -> 0
A96: 5 | B96: GPT | Kimi | C96: 1 | D96: =C96/225 -> 0.0044444444 | E96: 2 | F96: =E96/225 -> 0.0088888889
A97: 6 | B97: Deepseek | Kimi | C97: 6 | D97: =C97/225 -> 0.026666667 | E97: 1 | F97: =E97/225 -> 0.0044444444
A98: 7 | B98: GPT | Deepseek | Kimi | C98: 11 | D98: =C98/225 -> 0.048888889 | E98: 0 | F98: =E98/225 -> 0
B99: TOTAL | C99: =SUM(C92:C98) -> 36 | D99: =C99/225 -> 0.16 | E99: =SUM(E92:E98) -> 10 | F99: =E99/225 -> 0.044444444
A107: Extended Benchmark
A109: Model: | B109: gpt-4.1-mini
A111: Total F2P with In-Patch Test: | B111: 114
A112: Total F2P without In-Patch Test: | B112: 11
A113: Total F2P: | B113: 125
A115: F2P - Repos Distribution
A117: No. | B117: Repository | C117: Total F2P
A118: 1 | B118: AntonOsika/gpt-engineer | C118: 1
A119: 2 | B119: MLSysOps/MLE-agent | C119: 1
A120: 3 | B120: agentscope-ai/agentscope | C120: 34
A121: 4 | B121: dapr/dapr-agents | C121: 1
A122: 5 | B122: Aider-AI/aider | C122: 1
A123: 6 | B123: strands-agents/harness-sdk | C123: 79
A124: 7 | B124: crewAIInc/crewAI | C124: 8
B125: TOTAL | C125: =SUM(C118:C124) -> 125
A133: Agent Harness Components
A135: Components Distribution
A137: No. | B137: Harness Components | C137: Description | D137: Main Benchmark | E137: Extended Benchmark | F137: SWE-Factory | G137: SWE-bench-Live
A138: 1 | B138: Tool Registry & Action Interface | C138: The registry, interface, and protocol (e.g., MCP, function schemas) for discovering tools, formatting calls, and parsing observations/tool results. | D138: 22 | E138: 41 | F138: 14 | G138: 5
A139: 2 | B139: Context & Memory Management | C139: Context window assembly, token budgeting, persistent storage (vector/relational/KV memory), retrieval (RAG), and state tracking. | D139: 27 | E139: 34 | F139: 11 | G139: 2
A140: 3 | B140: Lifecycle & Orchestration Loop | C140: The agent control flow: the observe-think-act inner loop, multi-agent coordination, sub-task planning/routing, retry strategies, and termination conditions. | D140: 17 | E140: 27 | F140: 10 | G140: 2
A141: 4 | B141: Observability & Environment | C141: Isolated runtime infrastructure, trajectory tracing, token/cost tracking, error logging, event telemetry, and debugging/replay infrastructure. | D141: 8 | E141: 15 | F141: 1 | G141: 1
A142: 5 | B142: Governance, Security & Verification | C142: Runtime policy enforcement (permissions, guardrails, human-in-the-loop gates) and trajectory evaluation/verification (grounding, deterministic checks, safety assertions). | D142: 1 | E142: 8 | F142: 0 | G142: 0
...

Sheet RQ2
A1: issue_number | B1: url | C1: Alfin | D1: Yiming | E1: Human Golden | J1: issue_number | K1: url | L1: Alfin | M1: Yiming | N1: Human Golden | Q1: Yes | R1: No
A2: 1020 | B2: https://github.com/EaminC/AgentBug-Smith/tree/main/results/all_combined_f2p/issue_1020_20260814T120504Z | C2: Y | D2: Y | E2: Y | J2: 1037 | K2: https://github.com/EaminC/AgentBug-Smith/blob/main/data/issues_80/issue_1037.json | L2: Y | M2: Y | N2: Y | P2: Alfin | Q2: =COUNTIF(L2:L133, "Y") -> 123 | R2: =COUNTIF(L2:L133, "N") -> 9
A3: 1067 | B3: https://github.com/EaminC/AgentBug-Smith/tree/main/results/all_combined_f2p/issue_1067_20260814T123127Z | C3: Y | D3: Y | E3: Y | J3: 109 | K3: https://github.com/EaminC/AgentBug-Smith/blob/main/data/issues_80/issue_109.json | L3: Y | M3: Y | N3: Y | P3: Yiming | Q3: =COUNTIF(M2:M133, "Y") -> 123 | R3: =COUNTIF(M2:M133, "N") -> 9
A4: 1112 | B4: https://github.com/EaminC/AgentBug-Smith/tree/main/results/all_combined_f2p/issue_1112_20260623T030619Z | C4: Y | D4: Y | E4: Y | J4: 1129 | K4: https://github.com/EaminC/AgentBug-Smith/blob/main/data/issues_80/issue_1129.json | L4: Y | M4: Y | N4: Y | P4: Human Golden | Q4: =COUNTIF(N2:N133, "Y") -> 123 | R4: =COUNTIF(N2:N133, "N") -> 9
A5: 1115 | B5: https://github.com/EaminC/AgentBug-Smith/tree/main/results/all_combined_f2p/issue_1115_20260707T180736Z | C5: Y | D5: Y | E5: Y | J5: 1136 | K5: https://github.com/EaminC/AgentBug-Smith/blob/main/data/issues_80/issue_1136.json | L5: Y | M5: Y | N5: Y
A6: 1131 | B6: https://github.com/EaminC/AgentBug-Smith/tree/main/results/all_combined_f2p/issue_1131_20260814T215507Z | C6: Y | D6: Y | E6: Y | J6: 1197 | K6: https://github.com/EaminC/AgentBug-Smith/blob/main/data/issues_80/issue_1197.json | L6: Y | M6: Y | N6: Y | P6: Total labelled issues | Q6: 132
A7: 1136 | B7: https://github.com/EaminC/AgentBug-Smith/tree/main/results/all_combined_f2p/issue_1136_20260511T024303Z | C7: Y | D7: Y | E7: Y | J7: 121 | K7: https://github.com/EaminC/AgentBug-Smith/blob/main/data/issues_80/issue_121.json | L7: Y | M7: Y | N7: Y
A8: 1158 | B8: https://github.com/EaminC/AgentBug-Smith/tree/main/results/all_combined_f2p/issue_1158_20260814T222448Z | C8: Y | D8: Y | E8: Y | J8: 1222 | K8: https://github.com/EaminC/AgentBug-Smith/blob/main/data/issues_80/issue_1222.json | L8: Y | M8: Y | N8: Y | P8: Observed agreement | Q8: =Q4/132 -> 0.93181818
A9: 1176 | B9: https://github.com/EaminC/AgentBug-Smith/tree/main/results/all_combined_f2p/issue_1176_20260815T110931Z | C9: Y | D9: Y | E9: Y | J9: 1277 | K9: https://github.com/EaminC/AgentBug-Smith/blob/main/data/issues_80/issue_1277.json | L9: Y | M9: Y | N9: Y
A10: 1197 | B10: https://github.com/EaminC/AgentBug-Smith/tree/main/results/all_combined_f2p/issue_1197_20260815T160749Z | C10: Y | D10: Y | E10: Y | J10: 1280 | K10: https://github.com/EaminC/AgentBug-Smith/blob/main/data/issues_80/issue_1280.json | L10: Y | M10: Y | N10: Y | Q10: Alfiin: Yes | R10: Alfin: No
A11: 1208 | B11: https://github.com/EaminC/AgentBug-Smith/tree/main/results/all_combined_f2p/issue_1208_20260816T000846Z | C11: Y | D11: Y | E11: Y | J11: 137 | K11: https://github.com/EaminC/AgentBug-Smith/blob/main/data/issues_80/issue_137.json | L11: Y | M11: Y | N11: Y | P11: Yiming: Yes | Q11: =COUNTIFS(L2:L133,"Y",M2:M133,"Y") -> 122 | R11: =COUNTIFS(L2:L133,"N",M2:M133,"Y") -> 1
A12: 121 | B12: https://github.com/EaminC/AgentBug-Smith/tree/main/results/all_combined_f2p/issue_121_20260614T144239Z | C12: Y | D12: Y | E12: Y | J12: 1437 | K12: https://github.com/EaminC/AgentBug-Smith/blob/main/data/issues_80/issue_1437.json | L12: Y | M12: Y | N12: Y | P12: Yiming: No | Q12: =COUNTIFS(M2:M133,"N",L2:L133,"Y") -> 1 | R12: =COUNTIFS(M2:M133,"N",L2:L133,"N") -> 8
A13: 1221 | B13: https://github.com/EaminC/AgentBug-Smith/tree/main/results/all_combined_f2p/issue_1221_20260816T090307Z | C13: Y | D13: Y | E13: Y | J13: 1439 | K13: https://github.com/EaminC/AgentBug-Smith/blob/main/data/issues_80/issue_1439.json | L13: Y | M13: Y | N13: Y
A14: 1222 | B14: https://github.com/EaminC/AgentBug-Smith/tree/main/results/all_combined_f2p/issue_1222_20260617T122512Z | C14: Y | D14: Y | E14: Y | J14: 1445 | K14: https://github.com/EaminC/AgentBug-Smith/blob/main/data/issues_80/issue_1445.json | L14: Y | M14: Y | N14: Y | P14: Observed agreement | Q14: =(Q11+R12)/Q6 -> 0.98484848
A15: 1260 | B15: https://github.com/EaminC/AgentBug-Smith/tree/main/results/all_combined_f2p/issue_1260_20260816T160950Z | C15: Y | D15: Y | E15: Y | J15: 1455 | K15: https://github.com/EaminC/AgentBug-Smith/blob/main/data/issues_80/issue_1455.json | L15: Y | M15: Y | N15: Y | P15: Alfin Yes proportion | Q15: =Q2/Q6 -> 0.93181818 | R15: Alfin No proportion | S15: =R2/Q6 -> 0.068181818
A16: 1272 | B16: https://github.com/EaminC/AgentBug-Smith/tree/main/results/all_combined_f2p/issue_1272_20260816T174203Z | C16: Y | D16: Y | E16: Y | J16: 149 | K16: https://github.com/EaminC/AgentBug-Smith/blob/main/data/issues_80/issue_149.json | L16: Y | M16: Y | N16: Y | P16: Yiming Yes proportion | Q16: =Q3/Q6 -> 0.93181818 | R16: Yiming No proportion | S16: =R3/Q6 -> 0.068181818
A17: 1277 | B17: https://github.com/EaminC/AgentBug-Smith/tree/main/results/all_combined_f2p/issue_1277_20260511T034601Z | C17: Y | D17: Y | E17: Y | J17: 1511 | K17: https://github.com/EaminC/AgentBug-Smith/blob/main/data/issues_80/issue_1511.json | L17: Y | M17: Y | N17: Y | P17: Expected agreement | Q17: =(Q15*Q16)+(S15*S16) -> 0.87293388
A18: 1280 | B18: https://github.com/EaminC/AgentBug-Smith/tree/main/results/all_combined_f2p/issue_1280_20260717T161006Z | C18: Y | D18: Y | E18: Y | J18: 1583 | K18: https://github.com/EaminC/AgentBug-Smith/blob/main/data/issues_80/issue_1583.json | L18: Y | M18: Y | N18: Y
A19: 1294 | B19: https://github.com/EaminC/AgentBug-Smith/tree/main/results/all_combined_f2p/issue_1294_20260816T182750Z | C19: Y | D19: Y | E19: Y | J19: 1675 | K19: https://github.com/EaminC/AgentBug-Smith/blob/main/data/issues_80/issue_1675.json | L19: Y | M19: Y | N19: Y | P19: Cohen's Kappa | Q19: =(Q14-Q17)/(1-Q17) -> 0.88075881
A20: 1297 | B20: https://github.com/EaminC/AgentBug-Smith/tree/main/results/all_combined_f2p/issue_1297_20260624T043153Z | C20: Y | D20: Y | E20: Y | J20: 169 | K20: https://github.com/EaminC/AgentBug-Smith/blob/main/data/issues_80/issue_169.json | L20: Y | M20: Y | N20: Y
A21: 1334 | B21: https://github.com/EaminC/AgentBug-Smith/tree/main/results/all_combined_f2p/issue_1334_20260816T182942Z | C21: Y | D21: Y | E21: Y | J21: 174 | K21: https://github.com/EaminC/AgentBug-Smith/blob/main/data/issues_80/issue_174.json | L21: Y | M21: Y | N21: Y
A22: 1351 | B22: https://github.com/EaminC/AgentBug-Smith/tree/main/results/all_combined_f2p/issue_1351_20260624T075019Z | C22: Y | D22: Y | E22: Y | J22: 177 | K22: https://github.com/EaminC/AgentBug-Smith/blob/main/data/issues_80/issue_177.json | L22: Y | M22: Y | N22: Y
A23: 141 | B23: https://github.com/EaminC/AgentBug-Smith/tree/main/results/all_combined_f2p/issue_141_20260729T075605Z | C23: Y | D23: Y | E23: Y | J23: 1851 | K23: https://github.com/EaminC/AgentBug-Smith/blob/main/data/issues_80/issue_1851.json | L23: Y | M23: Y | N23: Y
A24: 1432 | B24: https://github.com/EaminC/AgentBug-Smith/tree/main/results/all_combined_f2p/issue_1432_20260817T045516Z | C24: Y | D24: Y | E24: Y | J24: 1886 | K24: https://github.com/EaminC/AgentBug-Smith/blob/main/data/issues_80/issue_1886.json | L24: Y | M24: Y | N24: Y
A25: 1439 | B25: https://github.com/EaminC/AgentBug-Smith/tree/main/results/all_combined_f2p/issue_1439_20260802T002117Z | C25: Y | D25: Y | E25: Y | J25: 1887 | K25: https://github.com/EaminC/AgentBug-Smith/blob/main/data/issues_80/issue_1887.json | L25: N | M25: N | N25: N
A26: 1538 | B26: https://github.com/EaminC/AgentBug-Smith/tree/main/results/all_combined_f2p/issue_1538_20260817T110225Z | C26: Y | D26: Y | E26: Y | J26: 209 | K26: https://github.com/EaminC/AgentBug-Smith/blob/main/data/issues_80/issue_209.json | L26: Y | M26: Y | N26: Y
A27: 1545 | B27: https://github.com/EaminC/AgentBug-Smith/tree/main/results/all_combined_f2p/issue_1545_20260817T110601Z | C27: Y | D27: Y | E27: Y | J27: 2390 | K27: https://github.com/EaminC/AgentBug-Smith/blob/main/data/issues_80/issue_2390.json | L27: Y | M27: Y | N27: Y
A28: 1551 | B28: https://github.com/EaminC/AgentBug-Smith/tree/main/results/all_combined_f2p/issue_1551_20260817T114349Z | C28: Y | D28: Y | E28: Y | J28: 255 | K28: https://github.com/EaminC/AgentBug-Smith/blob/main/data/issues_80/issue_255.json | L28: Y | M28: Y | N28: Y
A29: 1651 | B29: https://github.com/EaminC/AgentBug-Smith/tree/main/results/all_combined_f2p/issue_1651_20260817T190549Z | C29: Y | D29: Y | E29: Y | J29: 256 | K29: https://github.com/EaminC/AgentBug-Smith/blob/main/data/issues_80/issue_256.json | L29: Y | M29: Y | N29: Y
A30: 166 | B30: https://github.com/EaminC/AgentBug-Smith/tree/main/results/all_combined_f2p/issue_166_20260703T205716Z | C30: Y | D30: Y | E30: Y | J30: 259 | K30: https://github.com/EaminC/AgentBug-Smith/blob/main/data/issues_80/issue_259.json | L30: Y | M30: Y | N30: Y
A31: 1675 | B31: https://github.com/EaminC/AgentBug-Smith/tree/main/results/all_combined_f2p/issue_1675_20260617T165705Z | C31: Y | D31: Y | E31: Y | J31: 273 | K31: https://github.com/EaminC/AgentBug-Smith/blob/main/data/issues_80/issue_273.json | L31: Y | M31: Y | N31: Y
... A59: 194 | B59: https://github.com/EaminC/AgentBug-Smith/tree/main/results/all_combined_f2p/issue_194_20260623T191609Z | C59: Y | D59: Y | E59: Y | J59: 6050 | K59: https://github.com/EaminC/AgentBug-Smith/blob/main/data/issues_80/issue_6050.json | L59: Y | M59: Y | N59: Y
A60: 196 | B60: https://github.com/EaminC/AgentBug-Smith/tree/main/results/all_combined_f2p/issue_196_20260629T055224Z | C60: N | D60: Y | E60: N | F60: The fix is in the example not the agent itself. Therefore, I don't think it is agent issue. | J60: 6072 | K60: https://github.com/EaminC/AgentBug-Smith/blob/main/data/issues_80/issue_6072.json | L60: Y | M60: Y | N60: Y
A61: 1965 | B61: https://github.com/EaminC/AgentBug-Smith/tree/main/results/all_combined_f2p/issue_1965_20260729T165449Z | C61: Y | D61: Y | E61: Y | J61: 6212 | K61: https://github.com/EaminC/AgentBug-Smith/blob/main/data/issues_80/issue_6212.json | L61: Y | M61: Y | N61: Y
A62: 2000 | B62: https://github.com/EaminC/AgentBug-Smith/tree/main/results/all_combined_f2p/issue_2000_20260808T192026Z | C62: Y | D62: Y | E62: Y | J62: 6302 | K62: https://github.com/EaminC/AgentBug-Smith/blob/main/data/issues_80/issue_6302.json | L62: Y | M62: Y | N62: Y
A63: 2007 | B63: https://github.com/EaminC/AgentBug-Smith/tree/main/results/all_combined_f2p/issue_2007_20260819T163823Z | C63: Y | D63: Y | E63: Y | J63: 6409 | K63: https://github.com/EaminC/AgentBug-Smith/blob/main/data/issues_80/issue_6409.json | L63: Y | M63: Y | N63: Y
A64: 2052 | B64: https://github.com/EaminC/AgentBug-Smith/tree/main/results/all_combined_f2p/issue_2052_20260729T231408Z | C64: Y | D64: Y | E64: Y | J64: 6465 | K64: https://github.com/EaminC/AgentBug-Smith/blob/main/data/issues_80/issue_6465.json | L64: Y | M64: Y | N64: Y
A65: 2055 | B65: https://github.com/EaminC/AgentBug-Smith/tree/main/results/all_combined_f2p/issue_2055_20260730T044249Z | C65: Y | D65: Y | E65: Y | J65: 6585 | K65: https://github.com/EaminC/AgentBug-Smith/blob/main/data/issues_80/issue_6585.json | L65: Y | M65: Y | N65: Y
A66: 2089 | B66: https://github.com/EaminC/AgentBug-Smith/tree/main/results/all_combined_f2p/issue_2089_20260823T001916Z | C66: Y | D66: Y | E66: Y | J66: 66 | K66: https://github.com/EaminC/AgentBug-Smith/blob/main/data/issues_80/issue_66.json | L66: Y | M66: Y | N66: Y
A67: 209 | B67: https://github.com/EaminC/AgentBug-Smith/tree/main/results/all_combined_f2p/issue_209_20260619T235044Z | C67: Y | D67: Y | E67: Y | J67: 682 | K67: https://github.com/EaminC/AgentBug-Smith/blob/main/data/issues_80/issue_682.json | L67: Y | M67: Y | N67: Y
A68: 2090 | B68: https://github.com/EaminC/AgentBug-Smith/tree/main/results/all_combined_f2p/issue_2090_20260820T062310Z | C68: Y | D68: Y | E68: Y | J68: 70 | K68: https://github.com/EaminC/AgentBug-Smith/blob/main/data/issues_80/issue_70.json | L68: N | M68: N | N68: N
A69: 2122 | B69: https://github.com/EaminC/AgentBug-Smith/tree/main/results/all_combined_f2p/issue_2122_20260820T091450Z | C69: Y | D69: Y | E69: Y | J69: 700 | K69: https://github.com/EaminC/AgentBug-Smith/blob/main/data/issues_80/issue_700.json | L69: Y | M69: Y | N69: Y
A70: 2130 | B70: https://github.com/EaminC/AgentBug-Smith/tree/main/results/all_combined_f2p/issue_2130_20260810T101709Z | C70: Y | D70: Y | E70: Y | J70: 71 | K70: https://github.com/EaminC/AgentBug-Smith/blob/main/data/issues_80/issue_71.json | L70: Y | M70: N | N70: N
A71: 2130 | B71: https://github.com/EaminC/AgentBug-Smith/tree/main/results/all_combined_f2p/issue_2130_20260823T112024Z | C71: Y | D71: Y | E71: Y | J71: 768 | K71: https://github.com/EaminC/AgentBug-Smith/blob/main/data/issues_80/issue_768.json | L71: Y | M71: Y | N71: Y
A72: 2166 | B72: https://github.com/EaminC/AgentBug-Smith/tree/main/results/all_combined_f2p/issue_2166_20260808T214256Z | C72: Y | D72: Y | E72: Y | J72: 793 | K72: https://github.com/EaminC/AgentBug-Smith/blob/main/data/issues_80/issue_793.json | L72: Y | M72: Y | N72: Y
... A93: 29 | B93: https://github.com/EaminC/AgentBug-Smith/tree/main/results/all_combined_f2p/issue_29_20260614T084508Z | C93: Y | D93: Y | E93: Y | J93: 1539 | K93: https://github.com/EaminC/AgentBug-Smith/blob/main/data/issues_70/issue_1539.json | L93: Y | M93: Y | N93: Y
A94: 2910 | B94: https://github.com/EaminC/AgentBug-Smith/tree/main/results/all_combined_f2p/issue_2910_20260826T221655Z | C94: Y | D94: N | E94: Y | F94: Does this not include as dependency issue in the agent components? | J94: 160 | K94: https://github.com/EaminC/AgentBug-Smith/blob/main/data/issues_70/issue_160.json | L94: Y | M94: Y | N94: Y
A95: 2968 | B95: https://github.com/EaminC/AgentBug-Smith/tree/main/results/all_combined_f2p/issue_2968_20260717T205549Z | C95: Y | D95: Y | E95: Y | J95: 166 | K95: https://github.com/EaminC/AgentBug-Smith/blob/main/data/issues_70/issue_166.json | L95: Y | M95: Y | N95: Y
A96: 298 | B96: https://github.com/EaminC/AgentBug-Smith/tree/main/results/all_combined_f2p/issue_298_20260622T123423Z | C96: Y | D96: Y | E96: Y | J96: 184 | K96: https://github.com/EaminC/AgentBug-Smith/blob/main/data/issues_70/issue_184.json | L96: N | M96: N | N96: N
A97: 3112 | B97: https://github.com/EaminC/AgentBug-Smith/tree/main/results/all_combined_f2p/issue_3112_20260804T212932Z | C97: Y | D97: Y | E97: Y | J97: 211 | K97: https://github.com/EaminC/AgentBug-Smith/blob/main/data/issues_70/issue_211.json | L97: Y | M97: Y | N97: Y
A98: 322 | B98: https://github.com/EaminC/AgentBug-Smith/tree/main/results/all_combined_f2p/issue_322_20260731T162619Z | C98: Y | D98: Y | E98: Y | J98: 220 | K98: https://github.com/EaminC/AgentBug-Smith/blob/main/data/issues_70/issue_220.json | L98: Y | M98: Y | N98: Y
A99: 3226 | B99: https://github.com/EaminC/AgentBug-Smith/tree/main/results/all_combined_f2p/issue_3226_20260822T080137Z | C99: Y | D99: Y | E99: Y | J99: 245 | K99: https://github.com/EaminC/AgentBug-Smith/blob/main/data/issues_70/issue_245.json | L99: Y | M99: Y | N99: Y
A100: 3266 | B100: https://github.com/EaminC/AgentBug-Smith/tree/main/results/all_combined_f2p/issue_3266_20260805T121048Z | C100: Y | D100: Y | E100: Y | J100: 253 | K100: https://github.com/EaminC/AgentBug-Smith/blob/main/data/issues_70/issue_253.json | L100: Y | M100: Y | N100: Y
A101: 33 | B101: https://github.com/EaminC/AgentBug-Smith/tree/main/results/all_combined_f2p/issue_33_MLE_20260614T100655Z | C101: Y | D101: Y | E101: Y | J101: 259 | K101: https://github.com/EaminC/AgentBug-Smith/blob/main/data/issues_70/issue_259.json | L101: Y | M101: Y | N101: Y
A102: 337 | B102: https://github.com/EaminC/AgentBug-Smith/tree/main/results/all_combined_f2p/issue_337_20260813T113844Z | C102: Y | D102: Y | E102: Y | J102: 2598 | K102: https://github.com/EaminC/AgentBug-Smith/blob/main/data/issues_70/issue_2598.json | L102: Y | M102: Y | N102: Y
A103: 3388 | B103: https://github.com/EaminC/AgentBug-Smith/tree/main/results/all_combined_f2p/issue_3388_20260822T080336Z | C103: Y | D103: Y | E103: Y | J103: 266 | K103: https://github.com/EaminC/AgentBug-Smith/blob/main/data/issues_70/issue_266.json | L103: Y | M103: Y | N103: Y
A104: 3391 | B104: https://github.com/EaminC/AgentBug-Smith/tree/main/results/all_combined_f2p/issue_3391_20260523T120852Z | C104: Y | D104: Y | E104: Y | J104: 270 | K104: https://github.com/EaminC/AgentBug-Smith/blob/main/data/issues_70/issue_270.json | L104: Y | M104: Y | N104: Y
A105: 3425 | B105: https://github.com/EaminC/AgentBug-Smith/tree/main/results/all_combined_f2p/issue_3425_20260824T015929Z | C105: Y | D105: Y | E105: Y | J105: 2864 | K105: https://github.com/EaminC/AgentBug-Smith/blob/main/data/issues_70/issue_2864.json | L105: Y | M105: Y | N105: Y
A106: 3493 | B106: https://github.com/EaminC/AgentBug-Smith/tree/main/results/all_combined_f2p/issue_3493_20260822T091738Z | C106: Y | D106: Y | E106: Y | J106: 298 | K106: https://github.com/EaminC/AgentBug-Smith/blob/main/data/issues_70/issue_298.json | L106: Y | M106: Y | N106: Y
... A120: 579 | B120: https://github.com/EaminC/AgentBug-Smith/tree/main/results/all_combined_f2p/issue_579_20260814T054708Z | C120: Y | D120: Y | E120: Y | J120: 4947 | K120: https://github.com/EaminC/AgentBug-Smith/blob/main/data/issues_70/issue_4947.json | L120: Y | M120: Y | N120: Y
A121: 590 | B121: https://github.com/EaminC/AgentBug-Smith/tree/main/results/all_combined_f2p/issue_590_20260814T081942Z | C121: N | D121: Y | E121: N | F121: Cloud SDK config issue, not agent component issue | J121: 5178 | K121: https://github.com/EaminC/AgentBug-Smith/blob/main/data/issues_70/issue_5178.json | L121: Y | M121: Y | N121: Y
A122: 596 | B122: https://github.com/EaminC/AgentBug-Smith/tree/main/results/all_combined_f2p/issue_596_20260706T040852Z | C122: Y | D122: Y | E122: Y | J122: 5338 | K122: https://github.com/EaminC/AgentBug-Smith/blob/main/data/issues_70/issue_5338.json | L122: Y | M122: Y | N122: Y
A123: 6050 | B123: https://github.com/EaminC/AgentBug-Smith/tree/main/results/all_combined_f2p/issue_6050_20260805T172922Z | C123: Y | D123: Y | E123: Y | J123: 5343 | K123: https://github.com/EaminC/AgentBug-Smith/blob/main/data/issues_70/issue_5343.json | L123: Y | M123: Y | N123: Y
A124: 6585 | B124: https://github.com/EaminC/AgentBug-Smith/tree/main/results/all_combined_f2p/issue_6585_20260805T202509Z | C124: Y | D124: Y | E124: Y | J124: 536 | K124: https://github.com/EaminC/AgentBug-Smith/blob/main/data/issues_70/issue_536.json | L124: Y | M124: Y | N124: Y
A125: 667 | B125: https://github.com/EaminC/AgentBug-Smith/tree/main/results/all_combined_f2p/issue_667_20260814T105805Z | C125: Y | D125: Y | E125: Y | J125: 5452 | K125: https://github.com/EaminC/AgentBug-Smith/blob/main/data/issues_70/issue_5452.json | L125: Y | M125: Y | N125: Y
A126: 70 | B126: https://github.com/EaminC/AgentBug-Smith/tree/main/results/all_combined_f2p/issue_70_20260512T041132Z | C126: N | D126: N | E126: N | J126: 5489 | K126: https://github.com/EaminC/AgentBug-Smith/blob/main/data/issues_70/issue_5489.json | L126: Y | M126: Y | N126: Y
A127: 71 | B127: https://github.com/EaminC/AgentBug-Smith/tree/main/results/all_combined_f2p/issue_71_20260510T083954Z | C127: Y | D127: N | E127: N | F127: This one I agree with you. I think it is not agent issue since there is no fix for the modelwrapper, the ground-truth patch only raise valueerror | J127: 5517 | K127: https://github.com/EaminC/AgentBug-Smith/blob/main/data/issues_70/issue_5517.json | L127: Y | M127: Y | N127: Y
A128: 83 | B128: https://github.com/EaminC/AgentBug-Smith/tree/main/results/all_combined_f2p/issue_83_20260618T195818Z | C128: Y | D128: Y | E128: Y | J128: 5616 | K128: https://github.com/EaminC/AgentBug-Smith/blob/main/data/issues_70/issue_5616.json | L128: Y | M128: Y | N128: Y
A129: 831 | B129: https://github.com/EaminC/AgentBug-Smith/tree/main/results/all_combined_f2p/issue_831_20260814T161354Z | C129: Y | D129: Y | E129: Y | J129: 5781 | K129: https://github.com/EaminC/AgentBug-Smith/blob/main/data/issues_70/issue_5781.json | L129: Y | M129: Y | N129: Y
A130: 9 | B130: https://github.com/EaminC/AgentBug-Smith/tree/main/results/all_combined_f2p/issue_9_20260522T230911Z | C130: Y | D130: Y | E130: Y | J130: 5950 | K130: https://github.com/EaminC/AgentBug-Smith/blob/main/data/issues_70/issue_5950.json | L130: Y | M130: Y | N130: Y
A131: 962 | B131: https://github.com/EaminC/AgentBug-Smith/tree/main/results/all_combined_f2p/issue_962_20260623T024247Z | C131: Y | D131: Y | E131: Y | J131: 596 | K131: https://github.com/EaminC/AgentBug-Smith/blob/main/data/issues_70/issue_596.json | L131: Y | M131: Y | N131: Y
A132: 974 | B132: https://github.com/EaminC/AgentBug-Smith/tree/main/results/all_combined_f2p/issue_974_20260511T001744Z | C132: Y | D132: Y | E132: Y | J132: 610 | K132: https://github.com/EaminC/AgentBug-Smith/blob/main/data/issues_70/issue_610.json | L132: Y | M132: Y | N132: Y
A133: 974 | B133: https://github.com/EaminC/AgentBug-Smith/tree/main/results/all_combined_f2p/issue_974_20260811T072652Z | C133: Y | D133: Y | E133: Y | J133: 650 | K133: https://github.com/EaminC/AgentBug-Smith/blob/main/data/issues_70/issue_650.json | L133: Y | M133: Y | N133: Y
C136: Alfin | D136: Yiming | E136: Human Golden | I136: Yes | J136: No
A137: 1037 | B137: https://github.com/EaminC/AgentBug-Smith/blob/main/data/issues_80/issue_1037.json | C137: Y | D137: Y | E137: Y | F137: =COUNTIF($A$2:$A$133,A137) -> 0 | H137: Alfin | I137: =COUNTIF(C137:C361, "Y") -> 208 | J137: =COUNTIF(C137:C361, "N") -> 17 | K137: =I137/225 -> 0.92444444
A138: 109 | B138: https://github.com/EaminC/AgentBug-Smith/blob/main/data/issues_80/issue_109.json | C138: Y | D138: Y | E138: Y | F138: =COUNTIF($A$2:$A$133,A138) -> 0 | H138: Yiming | I138: =COUNTIF(D137:D361, "Y") -> 208 | J138: =COUNTIF(D137:D361, "N") -> 17 | K138: =I138/225 -> 0.92444444
A139: 1129 | B139: https://github.com/EaminC/AgentBug-Smith/blob/main/data/issues_80/issue_1129.json | C139: Y | D139: Y | E139: Y | F139: =COUNTIF($A$2:$A$133,A139) -> 0 | H139: Human Golden | I139: =COUNTIF(E137:E361, "Y") -> 207 | J139: =COUNTIF(E137:E361, "N") -> 18 | K139: =I139/225 -> 0.92
A140: 1136 | B140: https://github.com/EaminC/AgentBug-Smith/blob/main/data/issues_80/issue_1136.json | C140: Y | D140: Y | E140: Y | F140: =COUNTIF($A$2:$A$133,A140) -> 1
A141: 1197 | B141: https://github.com/EaminC/AgentBug-Smith/blob/main/data/issues_80/issue_1197.json | C141: Y | D141: Y | E141: Y | F141: =COUNTIF($A$2:$A$133,A141) -> 1 | H141: Total Label | I141: 225
A142: 121 | B142: https://github.com/EaminC/AgentBug-Smith/blob/main/data/issues_80/issue_121.json | C142: Y | D142: Y | E142: Y | F142: =COUNTIF($A$2:$A$133,A142) -> 1
A143: 1222 | B143: https://github.com/EaminC/AgentBug-Smith/blob/main/data/issues_80/issue_1222.json | C143: Y | D143: Y | E143: Y | F143: =COUNTIF($A$2:$A$133,A143) -> 1 | H143: Yiming vs Human Golden | I143: =(224/225) -> 0.99555556
A144: 1277 | B144: https://github.com/EaminC/AgentBug-Smith/blob/main/data/issues_80/issue_1277.json | C144: Y | D144: Y | E144: Y | F144: =COUNTIF($A$2:$A$133,A144) -> 1 | H144: Alfin vs Human Golden | I144: =222/225 -> 0.98666667
A145: 1280 | B145: https://github.com/EaminC/AgentBug-Smith/blob/main/data/issues_80/issue_1280.json | C145: Y | D145: Y | E145: Y | F145: =COUNTIF($A$2:$A$133,A145) -> 1 | H145: Alfin vs Yiming | I145: =221/225 -> 0.98222222
A146: 137 | B146: https://github.com/EaminC/AgentBug-Smith/blob/main/data/issues_80/issue_137.json | C146: Y | D146: Y | E146: Y | F146: =COUNTIF($A$2:$A$133,A146) -> 0
A147: 1437 | B147: https://github.com/EaminC/AgentBug-Smith/blob/main/data/issues_80/issue_1437.json | C147: Y | D147: Y | E147: Y | F147: =COUNTIF($A$2:$A$133,A147) -> 0
A148: 1439 | B148: https://github.com/EaminC/AgentBug-Smith/blob/main/data/issues_80/issue_1439.json | C148: Y | D148: Y | E148: Y | F148: =COUNTIF($A$2:$A$133,A148) -> 1
A149: 1445 | B149: https://github.com/EaminC/AgentBug-Smith/blob/main/data/issues_80/issue_1445.json | C149: Y | D149: Y | E149: Y | F149: =COUNTIF($A$2:$A$133,A149) -> 0
A150: 1455 | B150: https://github.com/EaminC/AgentBug-Smith/blob/main/data/issues_80/issue_1455.json | C150: Y | D150: Y | E150: Y | F150: =COUNTIF($A$2:$A$133,A150) -> 0
A151: 149 | B151: https://github.com/EaminC/AgentBug-Smith/blob/main/data/issues_80/issue_149.json | C151: Y | D151: Y | E151: Y | F151: =COUNTIF($A$2:$A$133,A151) -> 0
A152: 1511 | B152: https://github.com/EaminC/AgentBug-Smith/blob/main/data/issues_80/issue_1511.json | C152: Y | D152: Y | E152: Y | F152: =COUNTIF($A$2:$A$133,A152) -> 0
A153: 1583 | B153: https://github.com/EaminC/AgentBug-Smith/blob/main/data/issues_80/issue_1583.json | C153: Y | D153: Y | E153: Y | F153: =COUNTIF($A$2:$A$133,A153) -> 0
A154: 1675 | B154: https://github.com/EaminC/AgentBug-Smith/blob/main/data/issues_80/issue_1675.json | C154: Y | D154: Y | E154: Y | F154: =COUNTIF($A$2:$A$133,A154) -> 1
A155: 169 | B155: https://github.com/EaminC/AgentBug-Smith/blob/main/data/issues_80/issue_169.json | C155: Y | D155: Y | E155: Y | F155: =COUNTIF($A$2:$A$133,A155) -> 1
A156: 174 | B156: https://github.com/EaminC/AgentBug-Smith/blob/main/data/issues_80/issue_174.json | C156: Y | D156: Y | E156: Y | F156: =COUNTIF($A$2:$A$133,A156) -> 0
A157: 177 | B157: https://github.com/EaminC/AgentBug-Smith/blob/main/data/issues_80/issue_177.json | C157: Y | D157: Y | E157: Y | F157: =COUNTIF($A$2:$A$133,A157) -> 0
... A170: 325 | B170: https://github.com/EaminC/AgentBug-Smith/blob/main/data/issues_80/issue_325.json | C170: Y | D170: Y | E170: Y | F170: =COUNTIF($A$2:$A$133,A170) -> 0
A171: 33 | B171: https://github.com/EaminC/AgentBug-Smith/blob/main/data/issues_80/issue_33.json | C171: Y | D171: Y | E171: Y | F171: 0
A172: 33 | B172: https://github.com/EaminC/AgentBug-Smith/blob/main/data/issues_80/issue_33_MLE.json | C172: Y | D172: Y | E172: Y | F172: =COUNTIF($A$2:$A$133,A172) -> 1
A173: 388 | B173: https://github.com/EaminC/AgentBug-Smith/blob/main/data/issues_80/issue_388.json | C173: Y | D173: Y | E173: Y | F173: =COUNTIF($A$2:$A$133,A173) -> 1
A174: 3979 | B174: https://github.com/EaminC/AgentBug-Smith/blob/main/data/issues_80/issue_3979.json | C174: Y | D174: Y | E174: Y | F174: =COUNTIF($A$2:$A$133,A174) -> 0
...

Sheet RQ2（Eamin）
A1: issue_number | B1: url | C1: Alfin | D1: Yiming
A2: 3828 | B2: https://github.com/EaminC/AgentBug-Smith/tree/main/results/all_combined_f2p/issue_3828_20260525T192413Z | C2: Y | D2: Y
A3: 1297 | B3: https://github.com/EaminC/AgentBug-Smith/tree/main/results/all_combined_f2p/issue_1297_20260624T043153Z | C3: Y | D3: Y
A4: 1112 | B4: https://github.com/EaminC/AgentBug-Smith/tree/main/results/all_combined_f2p/issue_1112_20260623T030619Z | C4: Y | D4: Y
A5: 71 | B5: https://github.com/EaminC/AgentBug-Smith/tree/main/results/all_combined_f2p/issue_71_20260510T083954Z | C5: Y | D5: N
A6: 1765 | B6: https://github.com/EaminC/AgentBug-Smith/tree/main/results/all_combined_f2p/issue_1765_20260729T112754Z | C6: Y | D6: Y
A7: 1714 | B7: https://github.com/EaminC/AgentBug-Smith/tree/main/results/all_combined_f2p/issue_1714_20260818T071421Z | C7: Y | D7: Y
A8: 1702 | B8: https://github.com/EaminC/AgentBug-Smith/tree/main/results/all_combined_f2p/issue_1702_20260818T063539Z | C8: Y | D8: Y
A9: 1439 | B9: https://github.com/EaminC/AgentBug-Smith/tree/main/results/all_combined_f2p/issue_1439_20260802T002117Z | C9: Y | D9: Y
A10: 70 | B10: https://github.com/EaminC/AgentBug-Smith/tree/main/results/all_combined_f2p/issue_70_20260512T041132Z | C10: Y | D10: N
A11: 1280 | B11: https://github.com/EaminC/AgentBug-Smith/tree/main/results/all_combined_f2p/issue_1280_20260717T161006Z | C11: Y | D11: Y
A12: 529 | B12: https://github.com/EaminC/AgentBug-Smith/tree/main/results/all_combined_f2p/issue_529_20260813T191356Z | C12: Y | D12: Y
A13: 2910 | B13: https://github.com/EaminC/AgentBug-Smith/tree/main/results/all_combined_f2p/issue_2910_20260826T221655Z | C13: Y | D13: N
... A133: 1176 | B133: https://github.com/EaminC/AgentBug-Smith/tree/main/results/all_combined_f2p/issue_1176_20260815T110931Z | C133: Y | D133: Y
A135: DO NOT LABEL THIS LIST YET! I RE-WATCHED THE VIDEO AND I THINK THIS LIST IS NOT THE ONES WE SHOULD JUDGE.
A136: You can label the list below. Thanks!
A138: 1037 | B138: https://github.com/EaminC/AgentBug-Smith/blob/main/data/issues_80/issue_1037.json | D138: Y
A139: 109 | B139: https://github.com/EaminC/AgentBug-Smith/blob/main/data/issues_80/issue_109.json | D139: Y
A140: 1129 | B140: https://github.com/EaminC/AgentBug-Smith/blob/main/data/issues_80/issue_1129.json | D140: Y
A141: 1136 | B141: https://github.com/EaminC/AgentBug-Smith/blob/main/data/issues_80/issue_1136.json | C141: Y | D141: Y | E141: Y
A142: 1197 | B142: https://github.com/EaminC/AgentBug-Smith/blob/main/data/issues_80/issue_1197.json | C142: Y | D142: Y | E142: Y
A143: 121 | B143: https://github.com/EaminC/AgentBug-Smith/blob/main/data/issues_80/issue_121.json | C143: Y | D143: Y | E143: Y
A144: 1222 | B144: https://github.com/EaminC/AgentBug-Smith/blob/main/data/issues_80/issue_1222.json | C144: Y | D144: Y | E144: Y
A145: 1277 | B145: https://github.com/EaminC/AgentBug-Smith/blob/main/data/issues_80/issue_1277.json | C145: Y | D145: Y | E145: Y
A146: 1280 | B146: https://github.com/EaminC/AgentBug-Smith/blob/main/data/issues_80/issue_1280.json | C146: Y | D146: Y | E146: Y
A147: 137 | B147: https://github.com/EaminC/AgentBug-Smith/blob/main/data/issues_80/issue_137.json | D147: Y
A148: 1437 | B148: https://github.com/EaminC/AgentBug-Smith/blob/main/data/issues_80/issue_1437.json | D148: Y
A149: 1439 | B149: https://github.com/EaminC/AgentBug-Smith/blob/main/data/issues_80/issue_1439.json | C149: Y | D149: Y | E149: Y
A150: 1445 | B150: https://github.com/EaminC/AgentBug-Smith/blob/main/data/issues_80/issue_1445.json | D150: Y
A151: 1455 | B151: https://github.com/EaminC/AgentBug-Smith/blob/main/data/issues_80/issue_1455.json | D151: Y
A152: 149 | B152: https://github.com/EaminC/AgentBug-Smith/blob/main/data/issues_80/issue_149.json | D152: Y
A153: 1511 | B153: https://github.com/EaminC/AgentBug-Smith/blob/main/data/issues_80/issue_1511.json | D153: Y
A154: 1583 | B154: https://github.com/EaminC/AgentBug-Smith/blob/main/data/issues_80/issue_1583.json | D154: Y
A155: 1675 | B155: https://github.com/EaminC/AgentBug-Smith/blob/main/data/issues_80/issue_1675.json | C155: Y | D155: Y | E155: Y
A156: 169 | B156: https://github.com/EaminC/AgentBug-Smith/blob/main/data/issues_80/issue_169.json | C156: Y | D156: Y | E156: Y
A157: 174 | B157: https://github.com/EaminC/AgentBug-Smith/blob/main/data/issues_80/issue_174.json | D157: Y
A158: 177 | B158: https://github.com/EaminC/AgentBug-Smith/blob/main/data/issues_80/issue_177.json | D158: Y
A159: 1851 | B159: https://github.com/EaminC/AgentBug-Smith/blob/main/data/issues_80/issue_1851.json | D159: Y
A160: 1886 | B160: https://github.com/EaminC/AgentBug-Smith/blob/main/data/issues_80/issue_1886.json | D160: Y
A161: 1887 | B161: https://github.com/EaminC/AgentBug-Smith/blob/main/data/issues_80/issue_1887.json | D161: N
A162: 209 | B162: https://github.com/EaminC/AgentBug-Smith/blob/main/data/issues_80/issue_209.json | C162: Y | D162: Y | E162: Y
A163: 2390 | B163: https://github.com/EaminC/AgentBug-Smith/blob/main/data/issues_80/issue_2390.json | D163: Y
A164: 255 | B164: https://github.com/EaminC/AgentBug-Smith/blob/main/data/issues_80/issue_255.json | D164: Y
A165: 256 | B165: https://github.com/EaminC/AgentBug-Smith/blob/main/data/issues_80/issue_256.json | D165: Y
A166: 259 | B166: https://github.com/EaminC/AgentBug-Smith/blob/main/data/issues_80/issue_259.json | D166: Y
A167: 273 | B167: https://github.com/EaminC/AgentBug-Smith/blob/main/data/issues_80/issue_273.json | D167: Y
A168: 288 | B168: https://github.com/EaminC/AgentBug-Smith/blob/main/data/issues_80/issue_288.json | D168: Y
A169: 29 | B169: https://github.com/EaminC/AgentBug-Smith/blob/main/data/issues_80/issue_29.json | C169: Y | D169: Y | E169: Y
A170: 313 | B170: https://github.com/EaminC/AgentBug-Smith/blob/main/data/issues_80/issue_313.json | D170: N
A171: 325 | B171: https://github.com/EaminC/AgentBug-Smith/blob/main/data/issues_80/issue_325.json | D171: Y
A172: 33 | B172: https://github.com/EaminC/AgentBug-Smith/blob/main/data/issues_80/issue_33.json | D172: Y
A173: 33 | B173: https://github.com/EaminC/AgentBug-Smith/blob/main/data/issues_80/issue_33_MLE.json | C173: Y | D173: Y | E173: Y
A174: 388 | B174: https://github.com/EaminC/AgentBug-Smith/blob/main/data/issues_80/issue_388.json | C174: Y | D174: Y | E174: Y
A175: 3979 | B175: https://github.com/EaminC/AgentBug-Smith/blob/main/data/issues_80/issue_3979.json | D175: Y
A176: 3988 | B176: https://github.com/EaminC/AgentBug-Smith/blob/main/data/issues_80/issue_3988.json | D176: Y
A177: 40 | B177: https://github.com/EaminC/AgentBug-Smith/blob/main/data/issues_80/issue_40.json | D177: Y
A178: 4072 | B178: https://github.com/EaminC/AgentBug-Smith/blob/main/data/issues_80/issue_4072.json | D178: Y
A179: 4109 | B179: https://github.com/EaminC/AgentBug-Smith/blob/main/data/issues_80/issue_4109.json | C179: Y | D179: Y | E179: Y
A180: 411 | B180: https://github.com/EaminC/AgentBug-Smith/blob/main/data/issues_80/issue_411.json | C180: Y | D180: Y | E180: Y
A181: 4229 | B181: https://github.com/EaminC/AgentBug-Smith/blob/main/data/issues_80/issue_4229.json | D181: Y
A182: 429 | B182: https://github.com/EaminC/AgentBug-Smith/blob/main/data/issues_80/issue_429.json | D182: Y
A183: 441 | B183: https://github.com/EaminC/AgentBug-Smith/blob/main/data/issues_80/issue_441.json | D183: Y
A184: 4543 | B184: https://github.com/EaminC/AgentBug-Smith/blob/main/data/issues_80/issue_4543.json | D184: Y
A185: 4841 | B185: https://github.com/EaminC/AgentBug-Smith/blob/main/data/issues_80/issue_4841.json | D185: Y
A186: 513 | B186: https://github.com/EaminC/AgentBug-Smith/blob/main/data/issues_80/issue_513.json | D186: N
A187: 5557 | B187: https://github.com/EaminC/AgentBug-Smith/blob/main/data/issues_80/issue_5557.json | D187: N
A188: 56 | B188: https://github.com/EaminC/AgentBug-Smith/blob/main/data/issues_80/issue_56.json | D188: Y
A189: 5700 | B189: https://github.com/EaminC/AgentBug-Smith/blob/main/data/issues_80/issue_5700.json | C189: Y | D189: Y | E189: Y
A190: 5739 | B190: https://github.com/EaminC/AgentBug-Smith/blob/main/data/issues_80/issue_5739.json | D190: Y
A191: 5741 | B191: https://github.com/EaminC/AgentBug-Smith/blob/main/data/issues_80/issue_5741.json | D191: Y
A192: 5769 | B192: https://github.com/EaminC/AgentBug-Smith/blob/main/data/issues_80/issue_5769.json | D192: N
A193: 5784 | B193: https://github.com/EaminC/AgentBug-Smith/blob/main/data/issues_80/issue_5784.json | C193: Y | D193: Y | E193: Y
A194: 5787 | B194: https://github.com/EaminC/AgentBug-Smith/blob/main/data/issues_80/issue_5787.json | C194: Y | D194: Y | E194: Y
A195: 6050 | B195: https://github.com/EaminC/AgentBug-Smith/blob/main/data/issues_80/issue_6050.json | C195: Y | D195: Y | E195: Y
A196: 6072 | B196: https://github.com/EaminC/AgentBug-Smith/blob/main/data/issues_80/issue_6072.json | D196: Y
A197: 6212 | B197: https://github.com/EaminC/AgentBug-Smith/blob/main/data/issues_80/issue_6212.json | D197: Y
A198: 6302 | B198: https://github.com/EaminC/AgentBug-Smith/blob/main/data/issues_80/issue_6302.json | D198: Y
A199: 6409 | B199: https://github.com/EaminC/AgentBug-Smith/blob/main/data/issues_80/issue_6409.json | D199: Y
A200: 6465 | B200: https://github.com/EaminC/AgentBug-Smith/blob/main/data/issues_80/issue_6465.json | D200: Y
A201: 6585 | B201: https://github.com/EaminC/AgentBug-Smith/blob/main/data/issues_80/issue_6585.json | C201: Y | D201: Y | E201: Y
A202: 66 | B202: https://github.com/EaminC/AgentBug-Smith/blob/main/data/issues_80/issue_66.json | D202: Y
A203: 682 | B203: https://github.com/EaminC/AgentBug-Smith/blob/main/data/issues_80/issue_682.json | D203: Y
A204: 70 | B204: https://github.com/EaminC/AgentBug-Smith/blob/main/data/issues_80/issue_70.json | C204: N | D204: N | E204: N
A205: 700 | B205: https://github.com/EaminC/AgentBug-Smith/blob/main/data/issues_80/issue_700.json | D205: Y
A206: 71 | B206: https://github.com/EaminC/AgentBug-Smith/blob/main/data/issues_80/issue_71.json | C206: Y | D206: Y | E206: N
A207: 768 | B207: https://github.com/EaminC/AgentBug-Smith/blob/main/data/issues_80/issue_768.json | D207: Y
A208: 793 | B208: https://github.com/EaminC/AgentBug-Smith/blob/main/data/issues_80/issue_793.json | D208: Y
A209: 83 | B209: https://github.com/EaminC/AgentBug-Smith/blob/main/data/issues_80/issue_83.json | C209: Y | D209: Y | E209: Y
A210: 87 | B210: https://github.com/EaminC/AgentBug-Smith/blob/main/data/issues_80/issue_87.json | D210: Y
A211: 878 | B211: https://github.com/EaminC/AgentBug-Smith/blob/main/data/issues_80/issue_878.json | D211: Y
A212: 91 | B212: https://github.com/EaminC/AgentBug-Smith/blob/main/data/issues_80/issue_91.json | D212: Y
A213: 921 | B213: https://github.com/EaminC/AgentBug-Smith/blob/main/data/issues_80/issue_921.json | D213: Y
A214: 923 | B214: https://github.com/EaminC/AgentBug-Smith/blob/main/data/issues_80/issue_923.json | D214: Y
A215: 928 | B215: https://github.com/EaminC/AgentBug-Smith/blob/main/data/issues_80/issue_928.json | D215: Y
A216: 942 | B216: https://github.com/EaminC/AgentBug-Smith/blob/main/data/issues_80/issue_942.json | D216: Y
A217: 974 | B217: https://github.com/EaminC/AgentBug-Smith/blob/main/data/issues_80/issue_974.json | C217: Y | D217: Y | E217: Y
A218: 1016 | B218: https://github.com/EaminC/AgentBug-Smith/blob/main/data/issues_70/issue_1016.json | D218: Y
A219: 1059 | B219: https://github.com/EaminC/AgentBug-Smith/blob/main/data/issues_70/issue_1059.json | D219: Y
A220: 1112 | B220: https://github.com/EaminC/AgentBug-Smith/blob/main/data/issues_70/issue_1112.json | C220: Y | D220: Y | E220: Y
A221: 1115 | B221: https://github.com/EaminC/AgentBug-Smith/blob/main/data/issues_70/issue_1115.json | C221: Y | D221: Y | E221: Y
...

Sheet Summary
C2: GPT-4.1-mini | O2: Official price: | P2: $0.4 - input token/1M
P3: $1.6 - output token/1M
A4: No | B4: Pipeline | C4: F2P App (w/ in-Patch) | D4: F2P App (w/o in-patch) | E4: F2P App | F4: F2P Framework (w/ in-Patch) | G4: F2P Framework (w/o in-patch) | H4: F2P Framework | I4: Total F2P (w/ in-patch) | J4: Total F2P (w/o in-patch) | K4: Total F2P | L4: Avg. Duration | M4: Avg. Cost | N4: Avg. Token Consumption | O4: Env. build | P4: Avg. Input Token | Q4: Avg. Output Token
A5: 1 | B5: AgentBug-Smith | C5: =3+0+0+0 -> 3 | D5: =6+3+4+0 -> 13 | E5: =C5+D5 -> 16 | F5: =6+1+14+0 -> 21 | G5: =4+0+2+2 -> 8 | H5: =F5+G5 -> 29 | I5: =C5+F5 -> 24 | J5: =D5+G5 -> 21 | K5: =I5+J5 -> 45 | L5: 58m 10s | M5: =((P5/1000000)*0.4)+((Q5/1000000)*1.6) -> 0.5595124 | N5: =P5+Q5 -> 1287247 | O5: 84 | P5: 1250069 | Q5: 37178 | S5: *calc token by sampling 5 issues
A6: 2 | B6: SWE-Factory | C6: =3+0+0+0 -> 3 | D6: 0 | E6: =C6+D6 -> 3 | F6: =8+0+10+0 -> 18 | G6: 0 | H6: =F6+G6 -> 18 | I6: =C6+F6 -> 21 | J6: =D6+G6 -> 0 | K6: =I6+J6 -> 21 | L6: 5m 45s | M6: =((P6/1000000)*0.4)+((Q6/1000000)*1.6) -> 0.0906424 | N6: =P6+Q6 -> 167176 | O6: 36 | P6: 147366 | Q6: 19810 | S6: *calc token by sampling 5 issues
A7: 3 | B7: SWE-bench-Live | C7: =1+0+0+0 -> 1 | D7: 0 | E7: =C7+D7 -> 1 | F7: =3+1+1+0 -> 5 | G7: 0 | H7: =F7+G7 -> 5 | I7: =C7+F7 -> 6 | J7: =D7+G7 -> 0 | K7: =I7+J7 -> 6 | L7: 22m 19s | M7: =((P7/1000000)*0.4)+((Q7/1000000)*1.6) -> 0.4091236 | N7: =P7+Q7 -> 1007209 | O7: 33 | P7: 1002009 | Q7: 5200 | S7: *calc token by sampling 5 issues | V7: Use tuzi-gpt-mini
C11: Deepseek-v3.2 | O11: Official price | P11: $0.28 - input token/1M
P12: $0.4 - output token/1M
A13: No | B13: Pipeline | C13: F2P App (w/ in-Patch) | D13: F2P App (w/o in-patch) | E13: F2P App | F13: F2P Framework (w/ in-Patch) | G13: F2P Framework (w/o in-patch) | H13: F2P Framework | I13: Total F2P (w/ in-patch) | J13: Total F2P (w/o in-patch) | K13: Total F2P | L13: Avg. Duration | M13: Avg. Cost | N13: Avg. Token Consumption | O13: Env. build | P13: Avg. Input Token | Q13: Avg. Output Token
A14: 1 | B14: AgentBug-Smith | C14: 5 | D14: 21 | E14: =C14+D14 -> 26 | F14: 29 | G14: 8 | H14: =F14+G14 -> 37 | I14: =F14+C14 -> 34 | J14: =G14+D14 -> 29 | K14: =I14+J14 -> 63 | L14: 76m 26s | M14: =((P14/1000000)*0.28)+((Q14/1000000)*0.4) -> 2.4390618 | N14: =P14+Q14 -> 8667177 | O14: 93 | P14: 8565075 | Q14: 102102 | S14: *calc token by sampling 24 issues
A15: 2 | B15: SWE-Factory | C15: 3 | D15: 0 | E15: =C15+D15 -> 3 | F15: 28 | G15: 0 | H15: =F15+G15 -> 28 | I15: =F15+C15 -> 31 | J15: =G15+D15 -> 0 | K15: =I15+J15 -> 31 | L15: 6m 27s | M15: =((P15/1000000)*0.28)+((Q15/1000000)*0.4) -> 0.30701028 | N15: =P15+Q15 -> 1039926 | O15: 44 | P15: 908001 | Q15: 131925 | S15: *calc token using 2nd batch data
A16: 3 | B16: SWE-bench-Live | C16: 0 | D16: 0 | E16: =C16+D16 -> 0 | F16: 1 | G16: 0 | H16: =F16+G16 -> 1 | I16: =F16+C16 -> 1 | J16: =G16+D16 -> 0 | K16: =I16+J16 -> 1 | L16: 17m 22s | M16: =((P16/1000000)*0.28)+((Q16/1000000)*0.4) -> 1.0495557 | N16: =P16+Q16 -> 3738206 | O16: 14 | P16: 3714389 | Q16: 23817 | S16: *calc token by sampling 5 issues | V16: Use tuzi-baseline
C20: Kimi-k2.5 | O20: Official price | P20: $0.6 - input token/1M
P21: $3 - output token/1M
A22: No | B22: Pipeline | C22: F2P App (w/ in-Patch) | D22: F2P App (w/o in-patch) | E22: F2P App | F22: F2P Framework (w/ in-Patch) | G22: F2P Framework (w/o in-patch) | H22: F2P Framework | I22: Total F2P (w/ in-patch) | J22: Total F2P (w/o in-patch) | K22: Total F2P | L22: Avg. Duration | M22: Avg. Cost | N22: Avg. Token Consumption | O22: Env. build | P22: Avg. Input Token | Q22: Avg. Output Token
A23: 1 | B23: AgentBug-Smith | C23: 3 | D23: 22 | E23: =C23+D23 -> 25 | F23: 17 | G23: 4 | H23: =F23+G23 -> 21 | I23: =C23+F23 -> 20 | J23: =D23+G23 -> 26 | K23: =J23+I23 -> 46 | L23: 57m 15s | M23: =((P23/1000000)*0.6)+((Q23/1000000)*3) -> 0.9140562 | N23: =P23+Q23 -> 1285523 | O23: 53 | P23: 1226047 | Q23: 59476
A24: 2 | B24: SWE-Factory | C24: 2 | D24: 0 | E24: =C24+D24 -> 2 | F24: 17 | G24: 0 | H24: =F24+G24 -> 17 | I24: =C24+F24 -> 19 | J24: =D24+G24 -> 0 | K24: =J24+I24 -> 19 | L24: 4m 48s | M24: =((P24/1000000)*0.6)+((Q24/1000000)*3) -> 0.365214 | N24: =P24+Q24 -> 592602 | O24: 27 | P24: 588580 | Q24: 4022 | V24: Use tuzi-baseline
A25: 3 | B25: SWE-bench-Live | C25: 2 | D25: 0 | E25: =C25+D25 -> 2 | F25: 4 | G25: 0 | H25: =F25+G25 -> 4 | I25: =C25+F25 -> 6 | J25: =D25+G25 -> 0 | K25: =J25+I25 -> 6 | L25: 25m 14s | M25: =((P25/1000000)*0.6)+((Q25/1000000)*3) -> 0.6554874 | N25: =P25+Q25 -> 1065259 | O25: 29 | P25: 1058454 | Q25: 6805 | V25: Use tuzi-baseline
A28: AGENTBUG-SMITH
A29: No. | B29: Models | C29: App/Frame | D29: Agent Name | E29: Issue ID | F29: Issue PR | G29: In Patch? | H29: Agent Harness Component | I29: Reason | K29: Total F2P Across all models: | L29: 75 | N29: w/ IPT | O29: =COUNTIF(G30:G104,"Y") -> 35 | P29: 114 | Q29: =O29+P29 -> 149
A30: 1 | B30: GPT | Kimi | C30: Application | D30: gpt-engineer | E30: 9 | F30: 40 | H30: Lifecycle & Orchestration Loop | I30: Managing LLM backend routing, dynamic initialization fallbacks, and provider error recovery directly governs how the agent lifecycle initializes and executes its core generation turns. | N30: wo/ IPT | O30: =L29-O29 -> 40 | P30: 11 | Q30: =O30+P30 -> 51
A31: 2 | B31: Deepseek | Kimi | C31: Application | D31: mle-agent | E31: 29 | F31: 30 | H31: Lifecycle & Orchestration Loop | I31: This bug and its resolution pertain to how the agent structures its high-level execution stages, manages user-in-the-loop task planning, and orchestrates the setup steps prior to code synthesis and execution. | L31: w/ in-patch | M31: wo/ in-patch | N31: Total F2P | Q31: =Q29/200 -> 0.745
A32: 3 | B32: Deepseek | C32: Application | D32: mle-agent | E32: 33 | F32: 34 | H32: Lifecycle & Orchestration Loop | I32: Modifying the order of sequential stages, phase transitions, and user-in-the-loop interaction checkpoints directly alters the agent's high-level planning and lifecycle orchestration control flow. | K32: GPT only | L32: 0 | M32: 4 | N32: 4
A33: 4 | B33: Kimi | C33: Application | D33: mle-agent | E33: 56 | F33: 59 | H33: Tool Registry & Action Interface | I33: This issue directly concerns the setup, configuration, and interface initialization of an external tool provider (SearchAgent / search engine integration) before the agent can invoke it. | K33: Deepseek only | L33: 6 | M33: 7 | N33: 13
A34: 5 | B34: GPT | Deepseek | Kimi | C34: Application | D34: mle-agent | E34: 70 | F34: 73 | H34: Observability & Environment | I34: This enhancement directly serves user-facing inspection, operational visualization, and trajectory/state presentation of the agent's internal planning process without changing the underlying planning logic or execution control loop. | K34: Kimi only | L34: 0 | M34: 3 | N34: 3
A35: 6 | B35: GPT | Deepseek | Kimi | C35: Framework | D35: agentscope | E35: 71 | F35: 76 | H35: Context & Memory Management | I35: This issue directly concerns message/chat history data structures, prompt payload validation, and formatting representations as messages are converted from agent state/memory into model-consumable context lists. | K35: GPT | Deepseek | L35: 9 | M35: 3 | N35: 12
A36: 7 | B36: Deepseek | Kimi | C36: Framework | D36: dapr-agents | E36: 83 | F36: 84 | H36: Tool Registry & Action Interface | I36: This issue is fundamentally about tool result protocol parsing, serialization, and bidirectional communication between external tool interfaces (MCP) and the agent framework. | K36: GPT | Kimi | L36: 0 | M36: 5 | N36: 5
A37: 8 | B37: GPT | C37: Framework | D37: agentscope | E37: 91 | F37: 93 | H37: Lifecycle & Orchestration Loop | I37: This issue concerns multi-agent coordination, turn execution protocols, and message dispatch conventions within a multi-agent orchestration pattern (msghub). | K37: Deepseek | Kimi | L37: 5 | M37: 9 | N37: 14
A38: 9 | B38: GPT | Deepseek | C38: Framework | D38: agentscope | E38: 102 | F38: 106 | H38: Observability & Environment | I38: AgentScope Studio and its corresponding logging utilities form the monitoring, telemetry, and debugging interface used to trace and visualize agent conversations and runtime outputs. | K38: GPT | Deepseek | Kimi | L38: 14 | M38: 10 | N38: 24
A39: 10 | B39: Deepseek | Kimi | C39: Application | D39: mle-agent | E39: 121 | F39: 123 | H39: Context & Memory Management | I39: Session checkpointing, cross-session state persistence, and restoring serialized memory/context state across executions fall squarely under managing persistent agent memory and long-term state.
A40: 11 | B40: GPT | Deepseek |Kimi | C40: Application | D40: gpt-engineer | E40: 169 | F40: 173 | G40: Y | H40: Tool Registry & Action Interface | I40: This issue directly involves response parsing, action extraction, and output deserialization (parsing unstructured model generation into concrete environment actions and file operations).
A41: 12 | B41: Deepseek | Kimi | C41: Application | D41: mle-agent | E41: 182 | F41: 184 | H41: Observability & Environment | I41: The web dashboard and report viewer function as the user-facing inspection, operational monitoring, and visualization UI for the agent system's outputs and analytics.
A42: 13 | B42: GPT | Kimi | C42: Application | D42: mle-agent | E42: 159 | F42: 187 | H42: Lifecycle & Orchestration Loop | I42: This issue and fix directly modify the agent's interactive decision flow, clarifying question logic, and human-in-the-loop task planning loop during the initiation phase of the workflow. | K42: {=UNIQUE(D30:D104)} -> gpt-engineer | L42: =COUNTIF($D$30:$D$104,K42) -> 10
A43: 14 | B43: GPT | Deepseek | Kimi | C43: Framework | D43: agentscope | E43: 194 | F43: 197 | G43: Y | H43: Context & Memory Management | I43: This bug and patch directly address memory data models, memory loading/deserialization, and conversation history persistence within the agent's memory component. | K43: mle-agent | L43: =COUNTIF($D$30:$D$104,K43) -> 14
A44: 15 | B44: Deepseek | C44: Framework | D44: agentscope | E44: 196 | F44: 212 | H44: Lifecycle & Orchestration Loop | I44: This bug and fix directly govern game turn sequencing, environment state transitions, and episode termination conditions (stopping criteria) in an interactive multi-agent control loop. | K44: agentscope | L44: =COUNTIF($D$30:$D$104,K44) -> 16
A45: 16 | B45: GPT | C45: Application | D45: mle-agent | E45: 174 | F45: 217 | H45: Tool Registry & Action Interface | I45: Configuring, overriding, and adapting communication endpoints and initialization protocols for external APIs/LLM backends sits in the Action Interface layer (managing how the agent dials out to the model or tools). | K45: dapr-agents | L45: =COUNTIF($D$30:$D$104,K45) -> 2
A46: 17 | B46: GPT | Kimi | C46: Application | D46: mle-agent | E46: 166 | F46: 230 | H46: Tool Registry & Action Interface | I46: Integrating an LLM engine with function-calling capabilities requires implementing the tool schema translation, parameter serialization, and action dispatch layer between the agent framework and the provider API. | K46: open-interpreter | L46: =COUNTIF($D$30:$D$104,K46) -> 2
A47: 18 | B47: Deepseek | C47: Application | D47: mle-agent | E47: 259 | F47: 262 | H47: Observability & Environment | I47: This bug and fix directly impact the configuration, routing, and operational file storage of the agent framework's logging and telemetry subsystems. | K47: aider | L47: =COUNTIF($D$30:$D$104,K47) -> 7
A48: 19 | B48: GPT | Deepseek | Kimi | C48: Application | D48: mle-agent | E48: 266 | F48: 269 | H48: Context & Memory Management | I48: This issue directly modifies the underlying vector store and long-term memory retrieval/persistence layer used to store and manage external knowledge, facts, and embeddings for the agent. | K48: strands-agents | L48: =COUNTIF($D$30:$D$104,K48) -> 1
A49: 20 | B49: GPT | Kimi | C49: Application | D49: mle-agent | E49: 270 | F49: 271 | H49: Context & Memory Management | I49: The core functionality directly manages the ingestion, vector storage, indexing, and CRUD lifecycle of external knowledge and long-term memory for the agent. | K49: crewai | L49: =COUNTIF($D$30:$D$104,K49) -> 16
A50: 21 | B50: Deepseek | Kimi | C50: Application | D50: mle-agent | E50: 273 | F50: 274 | H50: Context & Memory Management | I50: The defect involves memory lifecycle initialization, config binding, and setup errors within the agent's persistent vector memory component. | K50: AutoGPT | L50: =COUNTIF($D$30:$D$104,K50) -> 2
A51: 22 | B51: GPT | Deepseek | Kimi | C51: Framework | D51: dapr-agents | E51: 209 | F51: 279 | H51: Lifecycle & Orchestration Loop | I51: This feature directly affects the agent execution lifecycle, workflow termination handling, and orchestration callback mechanisms governing the completion state of the agent loop. | K51: langgraph | L51: =COUNTIF($D$30:$D$104,K51) -> 5
A52: 23 | B52: Deepseek | C52: Application | D52: mle-agent | E52: 298 | F52: 310 | H52: Context & Memory Management | I52: This enhancement directly adds a new long-term context retention and memory retrieval backend (Mem0) to the agent framework's memory capabilities, augmenting how it stores and searches historical session knowledge.
A53: 24 | B53: Deepseek | Kimi | C53: Application | D53: gpt-engineer | E53: 388 | F53: 409 | G53: Y | H53: Context & Memory Management | I53: This change manages how agent run state, conversation memories, and intermediate session artifacts are persisted, snapshotted, rotated, and isolated across runs.
A54: 25 | B54: GPT | Deepseek | Kimi | C54: Framework | D54: agentscope | E54: 411 | F54: 420 | H54: Governance, Security & Verification | I54: This is a classic runtime policy enforcement and safety guardrail issue designed to govern and restrict agent actions against malicious or high-risk command patterns. | K54: TOTAL | L54: =SUM(L42:L52) -> 75
A55: 26 | B55: GPT | Deepseek | Kimi | C55: Framework | D55: agentscope | E55: 441 | F55: 443 | G55: Y | H55: Context & Memory Management | I55: This issue concerns prompt assembly, role tagging/mapping, and message format preparation when transforming conversation context and history into the provider-ready prompt payload.
A56: 27 | B56: GPT | C56: Application | D56: gpt-engineer | E56: 240 | F56: 463 | H56: Observability & Environment | I56: This functionality directly serves system evaluation, operational reporting, benchmark tracking, and historical run performance metrics across agent trajectories.
A57: 28 | B57: Deepseek | Kimi | C57: Application | D57: gpt-engineer | E57: 563 | F57: 568 | H57: Context & Memory Management | I57: System preprompts, static persona templates, and instructions injected into the context window are core assets managed by the prompt assembly and context construction layer.
A58: 29 | B58: Kimi | C58: Application | D58: open-interpreter | E58: 596 | F58: 607 | H58: Observability & Environment | I58: Token usage monitoring, cost estimation, and runtime consumption analytics fall directly under the agent harness's telemetry, operational metrics, and observability layer.
A59: 30 | B59: GPT | Deepseek | Kimi | C59: Application | D59: aider | E59: 700 | F59: 703 | H59: Tool Registry & Action Interface | I59: This issue concerns provider model registry configurations, action format bindings (specifying how model outputs are structured into diff/edit action protocols), and communication adapters between the agent harness and model endpoints.
A60: 31 | B60: Deepseek | Kimi | C60: Application | D60: gpt-engineer | E60: 682 | F60: 727 | H60: Lifecycle & Orchestration Loop | I60: This feature defines an automated self-correction/feedback loop, error recovery policy, retry mechanism, and control-flow step sequence within the agent's core execution lifecycle.
A61: 32 | B61: GPT | Kimi | C61: Framework | D61: strands-agents | E61: 974 | F61: 994 | G61: Y | H61: Context & Memory Management | I61: This issue directly governs context window boundaries, prompt token budgeting limits, and context overflow handling used by conversation management and memory pruning strategies.
A62: 33 | B62: GPT | Deepseek | Kimi | C62: Framework | D62: agentscope | E62: 959 | F62: 962 | G62: Y | H62: Tool Registry & Action Interface | I62: This issue concerns tool registry management, dynamic tool exposure/schema filtering, and action dispatch validation (governing which tools are active and callable by the model at any given point).
A63: 34 | B63: Deepseek | C63: Application | D63: open-interpreter | E63: 962 | F63: 977 | H63: Context & Memory Management | I63: This bug and fix directly concern conversation history persistence, schema deserialization, and restoring prior session state from disk back into the active agent context.
A64: 35 | B64: GPT | Deepseek | Kimi | C64: Framework | D64: agentscope | E64: 1058 | F64: 1097 | G64: Y | H64: Tool Registry & Action Interface | I64: This issue concerns tool call serialization/deserialization, argument parsing pipelines, and stream-decoding protocols that translate raw LLM outputs into structured tool invocation inputs.
A65: 36 | B65: Kimi | C65: Application | D65: gpt-engineer | E65: 1115 | F65: 1120 | H65: Observability & Environment | I65: The Learning pipeline is part of the telemetry, session feedback capture, trajectory logging, and operational data collection infrastructure used to record run metrics and user evaluation data.
A66: 37 | B66: Deepseek | Kimi | C66: Application | D66: gpt-engineer | E66: 1112 | F66: 1121 | H66: Context & Memory Management | I66: This issue concerns multimodal input handling, prompt construction, and context assembly (determining whether and how image inputs are integrated into the prompt payload sent to the LLM).
A67: 38 | B67: GPT | Deepseek | Kimi | C67: Framework | D67: agentscope | E67: 1136 | F67: 1141 | G67: Y | H67: Context & Memory Management | I67: This issue lies in prompt assembly, chat history serialization, and message schema formatting when structuring multi-turn context and message blocks into provider-compliant prompt payloads.
A68: 39 | B68: GPT | Deepseek | Kimi | C68: Application | D68: gpt-engineer | E68: 1153 | F68: 1170 | H68: Tool Registry & Action Interface | I68: This issue directly concerns LLM provider client configuration, API endpoint/version parameter binding, and the external interface adapter protocol for communicating with model providers.
A69: 40 | B69: GPT | Deepseek | Kimi | C69: Application | D69: gpt-engineer | E69: 1197 | F69: 1198 | G69: Y | H69: Tool Registry & Action Interface | I69: This issue lies in the agent's action parsing and formatting layer—specifically deserializing model-generated structured diff action representations into deterministic workspace file mutations.
A70: 41 | B70: GPT | Deepseek | C70: Application | D70: aider | E70: 1222 | F70: 1239 | G70: Y | H70: Tool Registry & Action Interface | I70: This bug and fix directly target action block deserialization, format parsing, and decoding model-generated action representations (SEARCH/REPLACE edit protocol blocks) into actionable file mutations.
A71: 42 | B71: GPT | Deepseek | Kimi | C71: Framework | D71: agentscope | E71: 1280 | F71: 1279 | G71: Y | H71: Lifecycle & Orchestration Loop | I71: PlanNotebook manages the sub-task decomposition, hierarchical plan execution, and plan lifecycle state transitions. The missing hook invocation directly impacts agent workflow event dispatching, planning loop state synchronization, and execution lifecycle orchestration.
A72: 43 | B72: GPT | Deepseek | Kimi | C72: Framework | D72: agentscope | E72: 1277 | F72: 1290 | G72: Y | H72: Tool Registry & Action Interface | I72: This issue directly concerns the model provider client adapter, asynchronous communication protocols, and interface transport handling between the agent framework and the remote LLM endpoint.
A73: 44 | B73: GPT | Deepseek | C73: Framework | D73: agentscope | E73: 1297 | F73: 1298 | H73: Observability & Environment | I73: AgentScope Studio hooks serve as an operational observability, web UI visualization, and trajectory/event logging stream. Preventing telemetry export failures from breaking core execution is a standard observability and logging resilience concern.
A74: 45 | B74: GPT | Deepseek | C74: Framework | D74: agentscope | E74: 1336 | F74: 1341 | H74: Context & Memory Management | I74: This fix resides directly in the message formatting and prompt assembly layer, specifically handling the ingestion, formatting, and serialization of multimodal input blocks into the context payload provided to the LLM.
A75: 46 | B75: GPT | Deepseek | Kimi | C75: Framework | D75: agentscope | E75: 1351 | F75: 1356 | G75: Y | H75: Tool Registry & Action Interface | I75: This bug and fix reside directly in the streaming action deserialization and tool call parameter parsing pipeline, which translates partial/streamed model outputs into valid, structured tool invocation arguments.
A76: 47 | B76: GPT | Deepseek | C76: Framework | D76: agentscope | E76: 1381 | F76: 1390 | G76: Y | H76: Context & Memory Management | I76: This issue directly concerns relational/persistent memory storage backends, state persistence mechanisms, and thread/coroutine-safe conversation history storage across agent interactions.
A77: 48 | B77: GPT | Deepseek | Kimi | C77: Application | D77: aider | E77: 1583 | F77: 1590 | H77: Tool Registry & Action Interface | I77: This issue directly concerns model provider client configuration, request parameter adapters, and the external communication/dispatch protocol between the agent framework and model provider APIs.
A78: 49 | B78: GPT | C78: Framework | D78: crewai | E78: 1723 | F78: 1724 | H78: Context & Memory Management | I78: This bug and fix directly target vector storage management, short-term memory cleanup/invalidation, and persistent storage backend lifecycles across agent memory modules.
A79: 50 | B79: GPT | Deepseek | Kimi | C79: Framework | D79: crewai | E79: 1703 | F79: 1818 | G79: Y | H79: Context & Memory Management | I79: This issue directly concerns knowledge source integration, RAG/knowledge retrieval, and prompt context assembly (ensuring external and pre-loaded agent knowledge is ingested and made available in the agent's context window).
A80: 51 | B80: GPT | Deepseek | Kimi | C80: Application | D80: aider | E80: 1851 | F80: 1852 | H80: Context & Memory Management | I80: System prompt templates, prompt engineering instructions, and context assembly directives injected into the model's context window are core assets managed by the prompt engineering and context management layer.
A81: 52 | B81: Deepseek | C81: Application | D81: aider | E81: 1675 | F81: 1982 | H81: Context & Memory Management | I81: Managing the active file set, tracking files in the conversation context window, and disambiguating in-context file references are core responsibilities of the context and session state management layer.
A82: 53 | B82: GPT | Deepseek | C82: Framework | D82: crewai | E82: 2175 | F82: 2231 | G82: Y | H82: Lifecycle & Orchestration Loop | I82: This bug and its corresponding fix reside directly in the workflow control flow graph, routing event dispatch, and conditional DAG/multi-agent execution loop.
A83: 54 | B83: GPT | Deepseek | C83: Framework | D83: crewai | E83: 2330 | F83: 2336 | G83: Y | H83: Tool Registry & Action Interface | I83: function_calling_llm configures the dedicated model executor specifically assigned to parse schemas, handle tool calling protocols, and generate structured function invocation payloads for an agent. Mapping and instantiating this dedicated action executor falls under the tool protocol, action interface, and function execution setup layer.
A84: 55 | B84: GPT | Deepseek | C84: Framework | D84: crewai | E84: 2551 | F84: 2552 | G84: Y | H84: Tool Registry & Action Interface | I84: This issue and patch concern the model provider adapter definitions, client endpoint configurations, and supported backend LLM interface registries that the agent harness uses to communicate with remote models.
A85: 56 | B85: GPT | Deepseek | C85: Framework | D85: crewai | E85: 2561 | F85: 2562 | G85: Y | H85: Tool Registry & Action Interface | I85: This enhancement directly modifies the tool registry and action declaration interface, defining how tool definitions are constructed, decorated, and converted into executable action handlers within the harness.
A86: 57 | B86: Deepseek | C86: Framework | D86: crewai | E86: 2434 | F86: 2570 | G86: Y | H86: Tool Registry & Action Interface | I86: This bug and fix reside directly in the tool execution and action dispatch interface, specifically handling coroutine serialization, runtime tool protocol execution, and mapping raw tool return values into structured action observations.
A87: 58 | B87: Deepseek | C87: Application | D87: AutoGPT | E87: 2390 | F87: 2587 | H87: Context & Memory Management | I87: This issue and patch directly modify system prompt assembly and environment context injection, ensuring the host runtime context is formatted and passed into the agent's context window.
A88: 59 | B88: Deepseek | C88: Framework | D88: crewai | E88: 2587 | F88: 2588 | G88: Y | H88: Context & Memory Management | I88: This issue and fix directly concern agent memory backends, vector store configurations, embedding model settings for memory storage, and state persistence across interactions.
A89: 60 | B89: Deepseek | C89: Framework | D89: crewai | E89: 2776 | F89: 2893 | G89: Y | H89: Context & Memory Management | I89: This enhancement directly modifies the memory architecture, vector memory retrieval algorithms, state persistence schemas, and context storage layer used across agent executions.
A90: 61 | B90: GPT | Deepseek | C90: Framework | D90: crewai | E90: 2899 | F90: 3057 | G90: Y | H90: Context & Memory Management | I90: This issue directly targets the memory management subsystem—specifically the operational maintenance, invalidation, and state reset workflows for persistent agent memory, knowledge stores, and conversation context.
A91: 62 | B91: Deepseek | C91: Framework | D91: crewai | E91: 2968 | F91: 3072 | G91: Y | H91: Tool Registry & Action Interface | I91: This issue directly concerns model provider authentication, client configuration adapters, and interface setup required for the agent harness to establish communication with the LLM endpoint.
A92: 63 | B92: Deepseek | C92: Application | D92: AutoGPT | E92: 942 | F92: 3144 | G92: Y | H92: Tool Registry & Action Interface | I92: This issue and patch directly concern LLM endpoint configuration, model adapter selection, and client invocation parameters used by the agent harness to communicate with backend model APIs.
A93: 64 | B93: GPT | Deepseek | C93: Framework | D93: crewai | E93: 3152 | F93: 3187 | G93: Y | H93: Context & Memory Management | I93: This issue directly targets the memory persistence backend, external memory storage interfaces, and conversation history serialization for long-/short-term agent state persistence.
A94: 65 | B94: GPT | Deepseek | C94: Framework | D94: crewai | E94: 3391 | F94: 3390 | G94: Y | H94: Context & Memory Management | I94: This issue directly targets memory storage serialization, persistent context state pruning, and external memory ingestion within the agent's memory subsystem.
A95: 66 | B95: GPT | Deepseek | Kimi | C95: Framework | D95: crewai | E95: 3828 | F95: 3839 | G95: Y | H95: Lifecycle & Orchestration Loop | I95: Although the unpickleable lock originated from an internal dependency when memory was enabled, the failure and fix reside directly in the workflow orchestrator's state transition, listener dispatch, and execution snapshot lifecycle within the flow orchestration loop.
A96: 67 | B96: GPT | Deepseek | Kimi | C96: Framework | D96: crewai | E96: 3899 | F96: 3904 | G96: Y | H96: Lifecycle & Orchestration Loop | I96: This issue directly governs multi-agent task delegation, conversation turn management, termination criteria, and control-flow coordination between distributed agent entities.
A97: 68 | B97: GPT | Deepseek | Kimi | C97: Framework | D97: crewai | E97: 3988 | F97: 3994 | G97: Y | H97: Lifecycle & Orchestration Loop | I97: This issue directly targets the instantiation, declaration, and structural assembly of agent graph nodes, task pipelines, and multi-agent execution orchestrators within the framework's core lifecycle loop.
A98: 69 | B98: Deepseek | Kimi | C98: Application | D98: aider | E98: 4109 | F98: 4022 | H98: Tool Registry & Action Interface | I98: This issue directly targets model provider API routing, endpoint identification schema conventions, and the client adapter communication layer that connects the harness to remote model backends.
A99: 70 | B99: GPT | Deepseek | Kimi | C99: Application | D99: aider | E99: 4543 | F99: 4544 | H99: Tool Registry & Action Interface | I99: This change configures the model adapter, invocation settings, and provider client interface that connect the agent harness to the Amazon Bedrock LLM endpoint.
A100: 71 | B100: Deepseek | Kimi | C100: Framework | D100: langgraph | E100: 5700 | F100: 5707 | G100: Y | H100: Lifecycle & Orchestration Loop | I100: This issue and patch directly concern runtime execution propagation, hierarchical graph/subgraph call loops, node-to-node execution state inheritance, and control-flow orchestration across nested workflow graphs.
A101: 72 | B101: Deepseek | Kimi | C101: Framework | D101: langgraph | E101: 5784 | F101: 5801 | G101: Y | H101: Lifecycle & Orchestration Loop | I101: This issue and patch directly govern the agent's decision loop, step-budget tracking, iteration limits (remaining_steps), and loop termination conditions within the orchestration engine.
A102: 73 | B102: Deepseek | C102: Framework | D102: langgraph | E102: 5787 | F102: 5798 | G102: Y | H102: Lifecycle & Orchestration Loop | I102: This issue concerns the graph runtime's signature introspection, parameter injection, and dispatch contract used to pass execution configurations into individual graph steps and runnable callbacks during graph traversal.
A103: 74 | B103: Deepseek | Kimi | C103: Framework | D103: langgraph | E103: 6050 | F103: 6161 | G103: Y | H103: Lifecycle & Orchestration Loop | I103: This issue and patch directly govern checkpoint resumption mechanics, interrupt/resume control flow, task-execution deduping, and state-loop step replay within hierarchical graph orchestration.
A104: 75 | B104: Deepseek | Kimi | C104: Framework | D104: langgraph | E104: 6585 | F104: 6586 | G104: Y | H104: Context & Memory Management | I104: Checkpointers and stores represent the core state persistence, memory checkpointing, and thread history layers in the harness architecture. This change directly enforces contract validation for the checkpointer persistence interface.
A108: Extended Benchmark
A109: No. | B109: Model | C109: App/Frame | D109: Agent Name | E109: Issue ID | F109: Issue PR | G109: In Patch? | H109: Agent Harness Component | I109: Reason | L109: w/ in-patch | M109: wo/ in-patch | N109: Total F2P
A110: 1 | B110: GPT | C110: Framework | D110: agentscope | E110: 88 | F110: 92 | G110: Y | H110: Tool Registry & Action Interface | I110: This issue and patch directly target LLM/VLM provider client adapters, endpoint routing definitions, and multimodal API payload serialization interfaces connecting the agent harness to external model backends.
A111: 2 | B111: GPT | C111: Framework | D111: agentscope | E111: 141 | F111: 142 | H111: Tool Registry & Action Interface | I111: This issue concerns model adapter initialization schemas, provider parameter specifications, and endpoint configuration protocols required to connect the harness to Ollama model services. | K111: GPT | L111: =COUNTIF(G110:G234,"Y") -> 114 | M111: =COUNTIF(G110:G234,"") -> 11 | N111: =L111+M111 -> 125
A112: 3 | B112: GPT | C112: Application | D112: mle-agent | E112: 160 | F112: 170 | H112: Tool Registry & Action Interface | I112: This issue and patch directly target tool schema conversion, provider tool-call protocol adapters, and action execution/result serialization between the model client and agent tools.
...

Sheet SE Agent Experiment
A1: Resolved by 3 agents | B1: Correctly resolved by mini-swe-agent & auto-code-rover | C1: Correctly resolved by mini-swe-agent and openhands | D1: Correct resolved by auto-code-rover & openhands
A3: Mini-swe-agent | C3: * the generated patch has similar fix but it has either less or more changes than ground truth
A4: Issue ID | B4: Harness Component | C4: Correctly Resolved | E4: Summary of Plausible Resolved
A5: 141 | B5: {=_xlfn.XLOOKUP(A5, Summary!$E$30:$E$234,Summary!$H$30:$H$234, "Not Found")} -> Tool Registry & Action Interface | C5: N | E5: {=UNIQUE(B5:B43)} -> Tool Registry & Action Interface | F5: =COUNTIF($B$5:$B$43,E5) -> 12
A6: 159 | B6: {=_xlfn.XLOOKUP(A6, Summary!$E$30:$E$234,Summary!$H$30:$H$234, "Not Found")} -> Lifecycle & Orchestration Loop | C6: N | D6: * | E6: Lifecycle & Orchestration Loop | F6: =COUNTIF($B$5:$B$43,E6) -> 11
A7: 160 | B7: {=_xlfn.XLOOKUP(A7, Summary!$E$30:$E$234,Summary!$H$30:$H$234, "Not Found")} -> Tool Registry & Action Interface | C7: N | E7: Context & Memory Management | F7: =COUNTIF($B$5:$B$43,E7) -> 9
A8: 298 | B8: {=_xlfn.XLOOKUP(A8, Summary!$E$30:$E$234,Summary!$H$30:$H$234, "Not Found")} -> Context & Memory Management | C8: N | E8: Observability & Environment | F8: =COUNTIF($B$5:$B$43,E8) -> 7
A9: 509 | B9: {=_xlfn.XLOOKUP(A9, Summary!$E$30:$E$234,Summary!$H$30:$H$234, "Not Found")} -> Context & Memory Management | C9: N
A10: 962 | B10: {=_xlfn.XLOOKUP(A10, Summary!$E$30:$E$234,Summary!$H$30:$H$234, "Not Found")} -> Context & Memory Management | C10: N | E10: Total Correctly Resolved | F10: =COUNTIF(C5:C43, "Y") -> 18
A11: 974 | B11: {=_xlfn.XLOOKUP(A11, Summary!$E$30:$E$234,Summary!$H$30:$H$234, "Not Found")} -> Context & Memory Management | C11: Y
A12: 1210 | B12: {=_xlfn.XLOOKUP(A12, Summary!$E$30:$E$234,Summary!$H$30:$H$234, "Not Found")} -> Tool Registry & Action Interface | C12: Y | E12: Summary of Correctly Resolved
A13: 1277 | B13: {=_xlfn.XLOOKUP(A13, Summary!$E$30:$E$234,Summary!$H$30:$H$234, "Not Found")} -> Tool Registry & Action Interface | C13: Y | E13: {=UNIQUE(B5:B43)} -> Tool Registry & Action Interface | F13: =COUNTIFS($B$5:$B$43,E13,$C$5:$C$43,"Y") -> 6
A14: 1280 | B14: {=_xlfn.XLOOKUP(A14, Summary!$E$30:$E$234,Summary!$H$30:$H$234, "Not Found")} -> Lifecycle & Orchestration Loop | C14: Y | E14: Lifecycle & Orchestration Loop | F14: =COUNTIFS($B$5:$B$43,E14,$C$5:$C$43,"Y") -> 5
A15: 1297 | B15: {=_xlfn.XLOOKUP(A15, Summary!$E$30:$E$234,Summary!$H$30:$H$234, "Not Found")} -> Observability & Environment | C15: Y | E15: Context & Memory Management | F15: =COUNTIFS($B$5:$B$43,E15,$C$5:$C$43,"Y") -> 3
A16: 1583 | B16: {=_xlfn.XLOOKUP(A16, Summary!$E$30:$E$234,Summary!$H$30:$H$234, "Not Found")} -> Tool Registry & Action Interface | C16: N | E16: Observability & Environment | F16: =COUNTIFS($B$5:$B$43,E16,$C$5:$C$43,"Y") -> 4
A17: 1596 | B17: {=_xlfn.XLOOKUP(A17, Summary!$E$30:$E$234,Summary!$H$30:$H$234, "Not Found")} -> Lifecycle & Orchestration Loop | C17: N
A18: 1688 | B18: {=_xlfn.XLOOKUP(A18, Summary!$E$30:$E$234,Summary!$H$30:$H$234, "Not Found")} -> Lifecycle & Orchestration Loop | C18: N
A19: 1702 | B19: {=_xlfn.XLOOKUP(A19, Summary!$E$30:$E$234,Summary!$H$30:$H$234, "Not Found")} -> Lifecycle & Orchestration Loop | C19: N
A20: 1792 | B20: {=_xlfn.XLOOKUP(A20, Summary!$E$30:$E$234,Summary!$H$30:$H$234, "Not Found")} -> Observability & Environment | C20: N
A21: 1813 | B21: {=_xlfn.XLOOKUP(A21, Summary!$E$30:$E$234,Summary!$H$30:$H$234, "Not Found")} -> Tool Registry & Action Interface | C21: Y
A22: 1885 | B22: {=_xlfn.XLOOKUP(A22, Summary!$E$30:$E$234,Summary!$H$30:$H$234, "Not Found")} -> Observability & Environment | C22: N
A23: 1900 | B23: {=_xlfn.XLOOKUP(A23, Summary!$E$30:$E$234,Summary!$H$30:$H$234, "Not Found")} -> Tool Registry & Action Interface | C23: N | D23: *
A24: 1904 | B24: {=_xlfn.XLOOKUP(A24, Summary!$E$30:$E$234,Summary!$H$30:$H$234, "Not Found")} -> Lifecycle & Orchestration Loop | C24: Y
A25: 2007 | B25: {=_xlfn.XLOOKUP(A25, Summary!$E$30:$E$234,Summary!$H$30:$H$234, "Not Found")} -> Observability & Environment | C25: Y
A26: 2055 | B26: {=_xlfn.XLOOKUP(A26, Summary!$E$30:$E$234,Summary!$H$30:$H$234, "Not Found")} -> Observability & Environment | C26: N
A27: 2089 | B27: {=_xlfn.XLOOKUP(A27, Summary!$E$30:$E$234,Summary!$H$30:$H$234, "Not Found")} -> Lifecycle & Orchestration Loop | C27: Y
A28: 2166 | B28: {=_xlfn.XLOOKUP(A28, Summary!$E$30:$E$234,Summary!$H$30:$H$234, "Not Found")} -> Observability & Environment | C28: Y
A29: 2173 | B29: {=_xlfn.XLOOKUP(A29, Summary!$E$30:$E$234,Summary!$H$30:$H$234, "Not Found")} -> Context & Memory Management | C29: N
A30: 2177 | B30: {=_xlfn.XLOOKUP(A30, Summary!$E$30:$E$234,Summary!$H$30:$H$234, "Not Found")} -> Tool Registry & Action Interface | C30: Y
A31: 2179 | B31: {=_xlfn.XLOOKUP(A31, Summary!$E$30:$E$234,Summary!$H$30:$H$234, "Not Found")} -> Tool Registry & Action Interface | C31: N
A32: 2235 | B32: {=_xlfn.XLOOKUP(A32, Summary!$E$30:$E$234,Summary!$H$30:$H$234, "Not Found")} -> Observability & Environment | C32: Y
A33: 2266 | B33: {=_xlfn.XLOOKUP(A33, Summary!$E$30:$E$234,Summary!$H$30:$H$234, "Not Found")} -> Lifecycle & Orchestration Loop | C33: N
A34: 2330 | B34: {=_xlfn.XLOOKUP(A34, Summary!$E$30:$E$234,Summary!$H$30:$H$234, "Not Found")} -> Tool Registry & Action Interface | C34: N
A35: 2587 | B35: {=_xlfn.XLOOKUP(A35, Summary!$E$30:$E$234,Summary!$H$30:$H$234, "Not Found")} -> Context & Memory Management | C35: N
... A43: 6050 | B43: {=_xlfn.XLOOKUP(A43, Summary!$E$30:$E$234,Summary!$H$30:$H$234, "Not Found")} -> Lifecycle & Orchestration Loop | C43: Y
A46: auto-code-rover
A47: Issue ID | B47: Harness Component | C47: Correctly Resolved | E47: Summary of Plausible Resolved
A48: 56 | B48: {=_xlfn.XLOOKUP(A48, Summary!$E$30:$E$234,Summary!$H$30:$H$234, "Not Found")} -> Tool Registry & Action Interface | C48: N | E48: {=UNIQUE(B48:B59)} -> Tool Registry & Action Interface | F48: =COUNTIF($B$48:$B$59,E48) -> 4
A49: 83 | B49: {=_xlfn.XLOOKUP(A49, Summary!$E$30:$E$234,Summary!$H$30:$H$234, "Not Found")} -> Tool Registry & Action Interface | C49: N | E49: Context & Memory Management | F49: =COUNTIF($B$48:$B$59,E49) -> 2
A50: 1112 | B50: {=_xlfn.XLOOKUP(A50, Summary!$E$30:$E$234,Summary!$H$30:$H$234, "Not Found")} -> Context & Memory Management | C50: N | E50: Lifecycle & Orchestration Loop | F50: =COUNTIF($B$48:$B$59,E50) -> 3
A51: 1280 | B51: {=_xlfn.XLOOKUP(A51, Summary!$E$30:$E$234,Summary!$H$30:$H$234, "Not Found")} -> Lifecycle & Orchestration Loop | C51: Y | E51: Observability & Environment | F51: =COUNTIF($B$48:$B$59,E51) -> 3
A52: 1334 | B52: {=_xlfn.XLOOKUP(A52, Summary!$E$30:$E$234,Summary!$H$30:$H$234, "Not Found")} -> Tool Registry & Action Interface | C52: Y
A53: 1596 | B53: {=_xlfn.XLOOKUP(A53, Summary!$E$30:$E$234,Summary!$H$30:$H$234, "Not Found")} -> Lifecycle & Orchestration Loop | C53: N | E53: Total Correctly Resolved | F53: =COUNTIF(C48:C59, "Y") -> 7
A54: 1792 | B54: {=_xlfn.XLOOKUP(A54, Summary!$E$30:$E$234,Summary!$H$30:$H$234, "Not Found")} -> Observability & Environment | C54: N
A55: 1892 | B55: {=_xlfn.XLOOKUP(A55, Summary!$E$30:$E$234,Summary!$H$30:$H$234, "Not Found")} -> Tool Registry & Action Interface | C55: Y | E55: Summary of Correctly Resolved
A56: 2007 | B56: {=_xlfn.XLOOKUP(A56, Summary!$E$30:$E$234,Summary!$H$30:$H$234, "Not Found")} -> Observability & Environment | C56: Y | E56: {=UNIQUE(B48:B59)} -> Tool Registry & Action Interface | F56: =COUNTIFS($B$48:$B$59,E56,$C$48:$C$59,"Y") -> 2
A57: 2089 | B57: {=_xlfn.XLOOKUP(A57, Summary!$E$30:$E$234,Summary!$H$30:$H$234, "Not Found")} -> Lifecycle & Orchestration Loop | C57: Y | E57: Context & Memory Management | F57: =COUNTIFS($B$48:$B$59,E57,$C$48:$C$59,"Y") -> 1
A58: 2166 | B58: {=_xlfn.XLOOKUP(A58, Summary!$E$30:$E$234,Summary!$H$30:$H$234, "Not Found")} -> Observability & Environment | C58: Y | E58: Lifecycle & Orchestration Loop | F58: =COUNTIFS($B$48:$B$59,E58,$C$48:$C$59,"Y") -> 2
A59: 2587 | B59: {=_xlfn.XLOOKUP(A59, Summary!$E$30:$E$234,Summary!$H$30:$H$234, "Not Found")} -> Context & Memory Management | C59: Y | E59: Observability & Environment | F59: =COUNTIFS($B$48:$B$59,E59,$C$48:$C$59,"Y") -> 2
A62: OpenHands
A63: Issue ID | B63: Harness Component | C63: Correctly Resolved | E63: Summary of Plausible Resolved
A64: 56 | B64: {=_xlfn.XLOOKUP(A64, Summary!$E$30:$E$234,Summary!$H$30:$H$234, "Not Found")} -> Tool Registry & Action Interface | C64: N | E64: {=UNIQUE(B64:B98)} -> Tool Registry & Action Interface | F64: =COUNTIF($B$64:$B$98,E64) -> 14
A65: 83 | B65: {=_xlfn.XLOOKUP(A65, Summary!$E$30:$E$234,Summary!$H$30:$H$234, "Not Found")} -> Tool Registry & Action Interface | C65: N | E65: Context & Memory Management | F65: =COUNTIF($B$64:$B$98,E65) -> 8
A66: 169 | B66: {=_xlfn.XLOOKUP(A66, Summary!$E$30:$E$234,Summary!$H$30:$H$234, "Not Found")} -> Tool Registry & Action Interface | C66: N | E66: Lifecycle & Orchestration Loop | F66: =COUNTIF($B$64:$B$98,E66) -> 6
A67: 441 | B67: {=_xlfn.XLOOKUP(A67, Summary!$E$30:$E$234,Summary!$H$30:$H$234, "Not Found")} -> Context & Memory Management | C67: Y | E67: Observability & Environment | F67: =COUNTIF($B$64:$B$98,E67) -> 7
A68: 974 | B68: {=_xlfn.XLOOKUP(A68, Summary!$E$30:$E$234,Summary!$H$30:$H$234, "Not Found")} -> Context & Memory Management | C68: Y
A69: 1112 | B69: {=_xlfn.XLOOKUP(A69, Summary!$E$30:$E$234,Summary!$H$30:$H$234, "Not Found")} -> Context & Memory Management | C69: N | E69: Total Correctly Resolved | F69: =COUNTIF(C64:C98, "Y") -> 17
A70: 1210 | B70: {=_xlfn.XLOOKUP(A70, Summary!$E$30:$E$234,Summary!$H$30:$H$234, "Not Found")} -> Tool Registry & Action Interface | C70: Y
A71: 1277 | B71: {=_xlfn.XLOOKUP(A71, Summary!$E$30:$E$234,Summary!$H$30:$H$234, "Not Found")} -> Tool Registry & Action Interface | C71: N | E71: Summary of Correctly Resolved
A72: 1280 | B72: {=_xlfn.XLOOKUP(A72, Summary!$E$30:$E$234,Summary!$H$30:$H$234, "Not Found")} -> Lifecycle & Orchestration Loop | C72: Y | E72: {=UNIQUE(B64:B98)} -> Tool Registry & Action Interface | F72: =COUNTIFS($B$64:$B$98,E72,$C$64:$C$98,"Y") -> 6
A73: 1297 | B73: {=_xlfn.XLOOKUP(A73, Summary!$E$30:$E$234,Summary!$H$30:$H$234, "Not Found")} -> Observability & Environment | C73: N | E73: Context & Memory Management | F73: =COUNTIFS($B$64:$B$98,E73,$C$64:$C$98,"Y") -> 5
A74: 1334 | B74: {=_xlfn.XLOOKUP(A74, Summary!$E$30:$E$234,Summary!$H$30:$H$234, "Not Found")} -> Tool Registry & Action Interface | C74: Y | E74: Lifecycle & Orchestration Loop | F74: =COUNTIFS($B$64:$B$98,E74,$C$64:$C$98,"Y") -> 3
A75: 1336 | B75: {=_xlfn.XLOOKUP(A75, Summary!$E$30:$E$234,Summary!$H$30:$H$234, "Not Found")} -> Context & Memory Management | C75: N | E75: Observability & Environment | F75: =COUNTIFS($B$64:$B$98,E75,$C$64:$C$98,"Y") -> 3
A76: 1702 | B76: {=_xlfn.XLOOKUP(A76, Summary!$E$30:$E$234,Summary!$H$30:$H$234, "Not Found")} -> Lifecycle & Orchestration Loop | C76: N
A77: 1792 | B77: {=_xlfn.XLOOKUP(A77, Summary!$E$30:$E$234,Summary!$H$30:$H$234, "Not Found")} -> Observability & Environment | C77: N
A78: 1885 | B78: {=_xlfn.XLOOKUP(A78, Summary!$E$30:$E$234,Summary!$H$30:$H$234, "Not Found")} -> Observability & Environment | C78: N
A79: 1892 | B79: {=_xlfn.XLOOKUP(A79, Summary!$E$30:$E$234,Summary!$H$30:$H$234, "Not Found")} -> Tool Registry & Action Interface | C79: Y
A80: 1904 | B80: {=_xlfn.XLOOKUP(A80, Summary!$E$30:$E$234,Summary!$H$30:$H$234, "Not Found")} -> Lifecycle & Orchestration Loop | C80: Y
A81: 2007 | B81: {=_xlfn.XLOOKUP(A81, Summary!$E$30:$E$234,Summary!$H$30:$H$234, "Not Found")} -> Observability & Environment | C81: Y
A82: 2055 | B82: {=_xlfn.XLOOKUP(A82, Summary!$E$30:$E$234,Summary!$H$30:$H$234, "Not Found")} -> Observability & Environment | C82: N
A83: 2089 | B83: {=_xlfn.XLOOKUP(A83, Summary!$E$30:$E$234,Summary!$H$30:$H$234, "Not Found")} -> Lifecycle & Orchestration Loop | C83: Y
A84: 2090 | B84: {=_xlfn.XLOOKUP(A84, Summary!$E$30:$E$234,Summary!$H$30:$H$234, "Not Found")} -> Tool Registry & Action Interface | C84: Y
A85: 2166 | B85: {=_xlfn.XLOOKUP(A85, Summary!$E$30:$E$234,Summary!$H$30:$H$234, "Not Found")} -> Observability & Environment | C85: Y
A86: 2173 | B86: {=_xlfn.XLOOKUP(A86, Summary!$E$30:$E$234,Summary!$H$30:$H$234, "Not Found")} -> Context & Memory Management | C86: N
A87: 2207 | B87: {=_xlfn.XLOOKUP(A87, Summary!$E$30:$E$234,Summary!$H$30:$H$234, "Not Found")} -> Tool Registry & Action Interface | C87: N
... A98: 3938 | B98: {=_xlfn.XLOOKUP(A98, Summary!$E$30:$E$234,Summary!$H$30:$H$234, "Not Found")} -> Tool Registry & Action Interface | C98: Y

Sheet Agent Harness Components
A2: No. | B2: Components | C2: Description
A3: 1 | B3: Tool Registry & Action Interface | C3: The registry, interface, and protocol (e.g., MCP, function schemas) for discovering tools, formatting calls, and parsing observations/tool results.
A4: 2 | B4: Context & Memory Management | C4: Context window assembly, token budgeting, persistent storage (vector/relational/KV memory), retrieval (RAG), and state tracking.
A5: 3 | B5: Lifecycle & Orchestration Loop | C5: The agent control flow: the observe-think-act inner loop, multi-agent coordination, sub-task planning/routing, retry strategies, and termination conditions.
A6: 4 | B6: Observability & Environment | C6: Trajectory tracing, token/cost tracking, error logging, event telemetry, and debugging/replay infrastructure.
A7: 5 | B7: Governance, Security & Verification | C7: Runtime policy enforcement (permissions, guardrails, human-in-the-loop gates) and trajectory evaluation/verification (grounding, deterministic checks, safety assertions).

Sheet Agent Distribution - GPT
A1: AGENT FRAMEWORKS
I2: GPT-4.1-Mini
A3: No | B3: Repository | C3: Repo link | D3: Language | E3: Stars | F3: License | G3: Total Issues with In-Patch (on 80) | H3: Total Issues without In-Patch (on 80) | I3: Total Issues (on 80) | J3: Total F2P With In-Patch (on 80) | K3: Total F2P Without In-Patch (on 80) | L3: Total F2P (on 80) | M3: 第 13 列 | N3: Total Issues with In-Patch (on 70) | O3: Total Issues without In-Patch (on 70) | P3: Total Issues (on 70) | Q3: Total F2P With In-Patch (on 70) | R3: Total F2P Without In-Patch (on 70) | S3: Total F2P (on 70) | T3: Column 17 | U3: Total Issues with In-Patch (on 50) | V3: Total Issues without In-Patch (on 50) | W3: Total Issues (on 50) | X3: Total F2P With In-Patch (on 50) | Y3: Total F2P Without In-Patch (on 50) | Z3: Total F2P (data: 50) | AA3: Column 17 2 | AB3: Total Issues with In-Patch (on 25) | AC3: Total Issues without In-Patch (on 25) | AD3: Total Issues (on 25) | AE3: Total F2P With In-Patch (on 25) | AF3: Total F2P Without In-Patch (on 25) | AG3: Total F2P (data: 25) | AH3: Column 17 3 | AI3: Total Issues with In-Patch | AJ3: Total Issues without In-Patch | AK3: Total Issues | AL3: Total F2P
A4: 1 | B4: dapr/dapr-agents | C4: https://github.com/dapr/dapr-agents/ | D4: Python | E4: 650 | F4: Apache-2.0 license | G4: 1 | H4: 2 | I4: =G4+H4 -> 3 | J4: 0 | K4: 1 | L4: =J4+K4 -> 1 | N4: 0 | O4: 0 | P4: =N4+O4 -> 0 | S4: =Q4+R4 -> 0 | U4: 0 | V4: 0 | W4: =U4+V4 -> 0 | Z4: =X4+Y4 -> 0 | AD4: =AB4+AC4 -> 0 | AG4: =AE4+AF4 -> 0 | AI4: =G4+N4+U4+AB4 -> 1 | AJ4: =H4+O4+V4+AC4 -> 2 | AK4: =I4+P4+W4+AD4 -> 3 | AL4: =L4+S4+Z4+AG4 -> 1
A5: 2 | B5: VoltAgent/voltagent | C5: https://github.com/VoltAgent/voltagent/ | D5: Typescript | E5: 7.1k | F5: MIT license | G5: 0 | H5: 1 | I5: =G5+H5 -> 1 | L5: =J5+K5 -> 0 | N5: 0 | O5: 0 | P5: =N5+O5 -> 0 | S5: =Q5+R5 -> 0 | U5: 0 | V5: 0 | W5: =U5+V5 -> 0 | Z5: =X5+Y5 -> 0 | AD5: =AB5+AC5 -> 0 | AG5: =AE5+AF5 -> 0 | AI5: =G5+N5+U5+AB5 -> 0 | AJ5: =H5+O5+V5+AC5 -> 1 | AK5: =I5+P5+W5+AD5 -> 1 | AL5: =L5+S5+Z5+AG5 -> 0
A6: 3 | B6: agentscope-ai/agentscope | C6: https://github.com/agentscope-ai/agentscope/ | D6: Python | E6: 22.5k | F6: Apache-2.0 license | G6: 4 | H6: 8 | I6: =G6+H6 -> 12 | J6: 4 | K6: 3 | L6: =J6+K6 -> 7 | N6: 2 | O6: 0 | P6: =N6+O6 -> 2 | Q6: 1 | R6: 0 | S6: =Q6+R6 -> 1 | U6: 4 | V6: 6 | W6: =U6+V6 -> 10 | X6: 4 | Y6: 2 | Z6: =X6+Y6 -> 6 | AB6: 0 | AC6: 5 | AD6: =AB6+AC6 -> 5 | AE6: 0 | AF6: 1 | AG6: =AE6+AF6 -> 1 | AI6: =G6+N6+U6+AB6 -> 10 | AJ6: =H6+O6+V6+AC6 -> 19 | AK6: =I6+P6+W6+AD6 -> 29 | AL6: =L6+S6+Z6+AG6 -> 15
A7: 4 | B7: crewAIInc/crewAI | C7: https://github.com/crewAIInc/crewAI | D7: Python | E7: 47.6k | F7: MIT license | G7: 2 | H7: 5 | I7: =G7+H7 -> 7 | J7: 1 | K7: 0 | L7: =J7+K7 -> 1 | N7: 0 | O7: 0 | P7: =N7+O7 -> 0 | S7: =Q7+R7 -> 0 | U7: 26 | V7: 0 | W7: =U7+V7 -> 26 | X7: 10 | Y7: 0 | Z7: =X7+Y7 -> 10 | AB7: 0 | AC7: 16 | AD7: =AB7+AC7 -> 16 | AE7: 0 | AF7: 1 | AG7: =AE7+AF7 -> 1 | AI7: =G7+N7+U7+AB7 -> 28 | AJ7: =H7+O7+V7+AC7 -> 21 | AK7: =I7+P7+W7+AD7 -> 49 | AL7: =L7+S7+Z7+AG7 -> 12
A8: 5 | B8: strands-agents/harness-sdk | C8: https://github.com/strands-agents/sdk-python | D8: Python | E8: 5.5k | F8: Apache-2.0 license | G8: 1 | H8: 0 | I8: =G8+H8 -> 1 | J8: 1 | K8: 0 | L8: =J8+K8 -> 1 | N8: 0 | O8: 0 | P8: =N8+O8 -> 0 | S8: =Q8+R8 -> 0 | U8: 0 | V8: 0 | W8: =U8+V8 -> 0 | Z8: =X8+Y8 -> 0 | AD8: =AB8+AC8 -> 0 | AG8: =AE8+AF8 -> 0 | AI8: =G8+N8+U8+AB8 -> 1 | AJ8: =H8+O8+V8+AC8 -> 0 | AK8: =I8+P8+W8+AD8 -> 1 | AL8: =L8+S8+Z8+AG8 -> 1
A9: 6 | B9: mastra-ai/mastra | C9: https://github.com/mastra-ai/mastra | D9: Typescript | E9: 22.5k | F9: Apache-2.0 license | G9: 0 | H9: 2 | I9: =G9+H9 -> 2 | L9: =J9+K9 -> 0 | N9: 0 | O9: 0 | P9: =N9+O9 -> 0 | S9: =Q9+R9 -> 0 | U9: 0 | V9: 0 | W9: =U9+V9 -> 0 | Z9: =X9+Y9 -> 0 | AB9: 0 | AC9: 1 | AD9: =AB9+AC9 -> 1 | AG9: =AE9+AF9 -> 0 | AI9: =G9+N9+U9+AB9 -> 0 | AJ9: =H9+O9+V9+AC9 -> 3 | AK9: =I9+P9+W9+AD9 -> 3 | AL9: =L9+S9+Z9+AG9 -> 0
A10: 7 | B10: langchain-ai/langgraph | C10: https://github.com/langchain-ai/langgraph | D10: Python | E10: 28.4k | F10: MIT license | G10: 11 | H10: 2 | I10: =G10+H10 -> 13 | L10: =J10+K10 -> 0 | N10: 0 | O10: 0 | P10: =N10+O10 -> 0 | S10: =Q10+R10 -> 0 | U10: 0 | V10: 0 | W10: =U10+V10 -> 0 | Z10: =X10+Y10 -> 0 | AD10: =AB10+AC10 -> 0 | AG10: =AE10+AF10 -> 0 | AI10: =G10+N10+U10+AB10 -> 11 | AJ10: =H10+O10+V10+AC10 -> 2 | AK10: =I10+P10+W10+AD10 -> 13 | AL10: =L10+S10+Z10+AG10 -> 0
A11: 8 | B11: langflow-ai/langflow | C11: https://github.com/langflow-ai/langflow | D11: Python | E11: 148k | F11: MIT license | G11: 0 | H11: 0 | I11: =G11+H11 -> 0 | L11: =J11+K11 -> 0 | N11: 9 | O11: 2 | P11: =N11+O11 -> 11 | S11: =Q11+R11 -> 0 | U11: 0 | V11: 0 | W11: =U11+V11 -> 0 | Z11: =X11+Y11 -> 0 | AD11: =AB11+AC11 -> 0 | AG11: =AE11+AF11 -> 0 | AI11: =G11+N11+U11+AB11 -> 9 | AJ11: =H11+O11+V11+AC11 -> 2 | AK11: =I11+P11+W11+AD11 -> 11 | AL11: =L11+S11+Z11+AG11 -> 0
A12: 9 | B12: geekan/MetaGPT | C12: https://github.com/geekan/MetaGPT | D12: Python | E12: 67.9k | F12: MIT license | G12: 1 | H12: 0 | I12: =G12+H12 -> 1 | L12: =J12+K12 -> 0 | N12: 6 | O12: 5 | P12: =N12+O12 -> 11 | S12: =Q12+R12 -> 0 | U12: 0 | V12: 0 | W12: =U12+V12 -> 0 | Z12: =X12+Y12 -> 0 | AD12: =AB12+AC12 -> 0 | AG12: =AE12+AF12 -> 0 | AI12: =G12+N12+U12+AB12 -> 7 | AJ12: =H12+O12+V12+AC12 -> 5 | AK12: =I12+P12+W12+AD12 -> 12 | AL12: =L12+S12+Z12+AG12 -> 0
A13: 10 | B13: tensorzero/tensorzero | C13: https://github.com/tensorzero/tensorzero | D13: Rust | E13: 11.4k | F13: Apache-2.0 license | G13: 0 | H13: 0 | I13: =G13+H13 -> 0 | L13: =J13+K13 -> 0 | N13: 11 | O13: 0 | P13: =N13+O13 -> 11 | S13: =Q13+R13 -> 0 | U13: 0 | V13: 0 | W13: =U13+V13 -> 0 | Z13: =X13+Y13 -> 0 | AD13: =AB13+AC13 -> 0 | AG13: =AE13+AF13 -> 0 | AI13: =G13+N13+U13+AB13 -> 11 | AJ13: =H13+O13+V13+AC13 -> 0 | AK13: =I13+P13+W13+AD13 -> 11 | AL13: =L13+S13+Z13+AG13 -> 0
B14: TOTAL | G14: =SUM(G4:G13) -> 20 | H14: =SUM(H4:H13) -> 20 | I14: =SUM(I4:I13) -> 40 | J14: =SUM(J4:J13) -> 6 | K14: =SUM(K4:K13) -> 4 | L14: =SUM(L4:L13) -> 10 | N14: =SUM(N4:N13) -> 28 | O14: =SUM(O4:O13) -> 7 | P14: =SUM(P4:P13) -> 35 | Q14: =SUM(Q4:Q13) -> 1 | R14: =SUM(R4:R13) -> 0 | S14: =SUM(S4:S13) -> 1 | U14: =SUM(U4:U13) -> 30 | V14: =SUM(V4:V13) -> 6 | W14: =SUM(W4:W13) -> 36 | X14: =SUM(X4:X13) -> 14 | Y14: =SUM(Y4:Y13) -> 2 | Z14: =SUM(Z4:Z13) -> 16 | AB14: =SUM(AB4:AB13) -> 0 | AC14: =SUM(AC4:AC13) -> 22 | AD14: =SUM(AD4:AD13) -> 22 | AE14: =SUM(AE4:AE13) -> 0 | AF14: =SUM(AF4:AF13) -> 2 | AG14: =SUM(AG4:AG13) -> 2 | AI14: =G14+N14+U14+AB14 -> 78 | AJ14: =H14+O14+V14+AC14 -> 55 | AK14: =SUM(AK4:AK13) -> 133 | AL14: =SUM(AL4:AL13) -> 29
A17: AGENT APPLICATIONS
I18: GPT-4.1-Mini
A19: No | B19: Repository | C19: Repo link | D19: Language | E19: Stars | F19: License | G19: Total Issues with In-Patch (on 80) | H19: Total Issues without In-Patch (on 80) | I19: Total Issues (on 80) | J19: Total F2P In-Patch (on 80) | K19: Total F2P No In-Patch (on 80) | L19: Total F2P (on 80) | M19: 第 13 列 | N19: Total Issues with In-Patch (on 70) | O19: Total Issues without In-Patch (on 70) | P19: Total Issues (on 70) | Q19: Total F2P With In-Patch (on 70) | R19: Total F2P Without In-Patch (on 70) | S19: Total F2P (on 70) | T19: Column 17 | U19: Total Issues with In-Patch (on 50) | V19: Total Issues without In-Patch (on 50) | W19: Total Issues (on 50) | X19: Total F2P With In-Patch (on 50) | Y19: Total F2P Without In-Patch (on 50) | Z19: Total F2P (data: 50) | AA19: Column 17 2 | AB19: Total Issues with In-Patch (on 25) | AC19: Total Issues without In-Patch (on 25) | AD19: Total Issues (on 25) | AE19: Total F2P With In-Patch (on 25) | AF19: Total F2P Without In-Patch (on 25) | AG19: Total F2P (data: 25) | AH19: Column 17 3 | AI19: Total Issues with In-Patch | AJ19: Total Issues without In-Patch | AK19: Total Issues | AL19: Total F2P
A20: 1 | B20: Significant-Gravitas/AutoGPT | C20: https://github.com/Significant-Gravitas/AutoGPT | D20: Python | E20: 183k | F20: MIT License & PolyForm Shield License 1.0.0 | G20: 4 | H20: 1 | I20: =G20+H20 -> 5 | L20: =J20+K20 -> 0 | N20: 0 | O20: 0 | P20: =N20+O20 -> 0 | U20: 6 | V20: 2 | W20: =U20+V20 -> 8 | Z20: =X20+Y20 -> 0 | AD20: =AB20+AC20 -> 0 | AG20: =AE20+AF20 -> 0 | AI20: =G20+N20+U20+AB20 -> 10 | AJ20: =H20+O20+V20+AC20 -> 3 | AK20: =I20+P20+W20+AD20 -> 13 | AL20: =L20+S20+Z20+AG20 -> 0
A21: 2 | B21: MLSysOps/MLE-agent | C21: https://github.com/MLSysOps/MLE-agent/ | D21: Python | E21: 1.5k | F21: MIT license | G21: 0 | H21: 9 | I21: =G21+H21 -> 9 | J21: 0 | K21: 2 | L21: =J21+K21 -> 2 | N21: 0 | O21: 8 | P21: =N21+O21 -> 8 | Q21: 0 | R21: 3 | S21: 3 | U21: 0 | V21: 1 | W21: =U21+V21 -> 1 | X21: 0 | Y21: 1 | Z21: =X21+Y21 -> 1 | AB21: 0 | AC21: 3 | AD21: =AB21+AC21 -> 3 | AE21: 0 | AF21: 0 | AG21: =AE21+AF21 -> 0 | AI21: =G21+N21+U21+AB21 -> 0 | AJ21: =H21+O21+V21+AC21 -> 21 | AK21: =I21+P21+W21+AD21 -> 21 | AL21: =L21+S21+Z21+AG21 -> 6
A22: 3 | B22: always-further/AgentUp | C22: https://github.com/always-further/AgentUp/ | D22: Python | E22: 100 | F22: Apache-2.0 license | G22: 0 | H22: 2 | I22: =G22+H22 -> 2 | L22: =J22+K22 -> 0 | N22: 0 | O22: 0 | P22: =N22+O22 -> 0 | U22: 0 | V22: 0 | W22: =U22+V22 -> 0 | Z22: =X22+Y22 -> 0 | AD22: =AB22+AC22 -> 0 | AG22: =AE22+AF22 -> 0 | AI22: =G22+N22+U22+AB22 -> 0 | AJ22: =H22+O22+V22+AC22 -> 2 | AK22: =I22+P22+W22+AD22 -> 2 | AL22: =L22+S22+Z22+AG22 -> 0
A23: 4 | B23: Canner/WrenAI | C23: https://github.com/Canner/WrenAI | D23: Python | E23: 14.9k | F23: AGPL-3.0 license | G23: 0 | H23: 1 | I23: =G23+H23 -> 1 | L23: =J23+K23 -> 0 | N23: 0 | O23: 0 | P23: =N23+O23 -> 0 | U23: 0 | V23: 0 | W23: =U23+V23 -> 0 | Z23: =X23+Y23 -> 0 | AD23: =AB23+AC23 -> 0 | AG23: =AE23+AF23 -> 0 | AI23: =G23+N23+U23+AB23 -> 0 | AJ23: =H23+O23+V23+AC23 -> 1 | AK23: =I23+P23+W23+AD23 -> 1 | AL23: =L23+S23+Z23+AG23 -> 0
A24: 5 | B24: reworkd/AgentGPT | C24: https://github.com/reworkd/AgentGPT | D24: Python | E24: 35.9k | F24: GPL-3.0 license | G24: 1 | H24: 4 | I24: =G24+H24 -> 5 | L24: =J24+K24 -> 0 | N24: 0 | O24: 0 | P24: =N24+O24 -> 0 | U24: 0 | V24: 0 | W24: =U24+V24 -> 0 | Z24: =X24+Y24 -> 0 | AD24: =AB24+AC24 -> 0 | AG24: =AE24+AF24 -> 0 | AI24: =G24+N24+U24+AB24 -> 1 | AJ24: =H24+O24+V24+AC24 -> 4 | AK24: =I24+P24+W24+AD24 -> 5 | AL24: =L24+S24+Z24+AG24 -> 0
A25: 6 | B25: Aider-AI/aider | C25: https://github.com/Aider-AI/aider | D25: Python | E25: 42.8k | F25: Apache-2.0 license | G25: 1 | H25: 6 | I25: =G25+H25 -> 7 | J25: 1 | K25: 4 | L25: =J25+K25 -> 5 | N25: 0 | O25: 0 | P25: =N25+O25 -> 0 | U25: 0 | V25: 0 | W25: =U25+V25 -> 0 | Z25: =X25+Y25 -> 0 | AD25: =AB25+AC25 -> 0 | AG25: =AE25+AF25 -> 0 | AI25: =G25+N25+U25+AB25 -> 1 | AJ25: =H25+O25+V25+AC25 -> 6 | AK25: =I25+P25+W25+AD25 -> 7 | AL25: =L25+S25+Z25+AG25 -> 5
A26: 7 | B26: ValueCell-ai/valuecell | C26: https://github.com/ValueCell-ai/valuecell | D26: Python | E26: 10.2k | F26: Apache-2.0 license | G26: 0 | H26: 4 | I26: =G26+H26 -> 4 | L26: =J26+K26 -> 0 | N26: 0 | O26: 1 | P26: =N26+O26 -> 1 | U26: 0 | V26: 0 | W26: =U26+V26 -> 0 | Z26: =X26+Y26 -> 0 | AD26: =AB26+AC26 -> 0 | AG26: =AE26+AF26 -> 0 | AI26: =G26+N26+U26+AB26 -> 0 | AJ26: =H26+O26+V26+AC26 -> 5 | AK26: =I26+P26+W26+AD26 -> 5 | AL26: =L26+S26+Z26+AG26 -> 0
A27: 8 | B27: AntonOsika/gpt-engineer | C27: https://github.com/AntonOsika/gpt-engineer | D27: Python | E27: 55.2k | F27: MIT license | G27: 4 | H27: 3 | I27: =G27+H27 -> 7 | J27: 2 | K27: 0 | L27: =J27+K27 -> 2 | N27: 4 | O27: 3 | P27: =N27+O27 -> 7 | U27: 1 | V27: 4 | W27: =U27+V27 -> 5 | X27: 0 | Y27: 3 | Z27: =X27+Y27 -> 3 | AD27: =AB27+AC27 -> 0 | AG27: =AE27+AF27 -> 0 | AI27: =G27+N27+U27+AB27 -> 9 | AJ27: =H27+O27+V27+AC27 -> 10 | AK27: =I27+P27+W27+AD27 -> 19 | AL27: =L27+S27+Z27+AG27 -> 5
A28: 9 | B28: OpenInterpreter/open-interpreter | C28: https://github.com/OpenInterpreter/open-interpreter | D28: Python | E28: 11.4k | F28: Apache-2.0 license | G28: 0 | H28: 0 | I28: =G28+H28 -> 0 | L28: =J28+K28 -> 0 | N28: 0 | O28: 12 | P28: =N28+O28 -> 12 | U28: 0 | V28: 0 | W28: =U28+V28 -> 0 | Z28: =X28+Y28 -> 0 | AD28: =AB28+AC28 -> 0 | AG28: =AE28+AF28 -> 0 | AI28: =G28+N28+U28+AB28 -> 0 | AJ28: =H28+O28+V28+AC28 -> 12 | AK28: =I28+P28+W28+AD28 -> 12 | AL28: =L28+S28+Z28+AG28 -> 0
A29: 10 | B29: lobehub/lobehub | C29: https://github.com/lobehub/lobehub | D29: Typescript | E29: 77k | F29: Apache-2.0 license | G29: 0 | H29: 0 | I29: =G29+H29 -> 0 | L29: =J29+K29 -> 0 | N29: 7 | O29: 0 | P29: =N29+O29 -> 7 | U29: 0 | V29: 0 | W29: =U29+V29 -> 0 | Z29: =X29+Y29 -> 0 | AD29: =AB29+AC29 -> 0 | AG29: =AE29+AF29 -> 0 | AI29: =G29+N29+U29+AB29 -> 7 | AJ29: =H29+O29+V29+AC29 -> 0 | AK29: =I29+P29+W29+AD29 -> 7 | AL29: =L29+S29+Z29+AG29 -> 0
B30: TOTAL | G30: =G29+G28+G27+G26+G25+G24+G23+G22+G21+G20 -> 10 | H30: =H29+H28+H27+H26+H25+H24+H23+H22+H21+H20 -> 30 | I30: =SUM(I20:I29) -> 40 | J30: =SUM(J20:J29) -> 3 | K30: =SUM(K20:K29) -> 6 | L30: =SUM(L20:L29) -> 9 | N30: =SUM(AGENT_APPLICATIONS[Total Issues with In-Patch (on 70)]) -> 11 | O30: =SUM(AGENT_APPLICATIONS[Total Issues without In-Patch (on 70)]) -> 24 | P30: =SUM(P20:P29) -> 35 | Q30: =SUM(Q20:Q29) -> 0 | R30: =SUM(R20:R29) -> 3 | S30: =SUM(S20:S29) -> 3 | U30: =SUM(U20:U29) -> 7 | V30: =SUM(V20:V29) -> 7 | W30: =SUM(W20:W29) -> 14 | X30: =SUM(X20:X29) -> 0 | Y30: =SUM(Y20:Y29) -> 4 | Z30: =SUM(Z20:Z29) -> 4 | AB30: =SUM(AGENT_APPLICATIONS[Total Issues with In-Patch (on 25)]) -> 0 | AC30: =SUM(AGENT_APPLICATIONS[Total Issues without In-Patch (on 25)]) -> 3 | AD30: =SUM(AGENT_APPLICATIONS[Total Issues (on 25)]) -> 3 | AE30: 0 | AF30: 0 | AG30: 0 | AK30: =SUM(AGENT_APPLICATIONS[Total Issues]) -> 92 | AL30: =SUM(AGENT_APPLICATIONS[Total F2P]) -> 16
A33: SUMMARY
A35: No | B35: Batch | C35: Issues with In-Patch | D35: Issues without In-Patch | E35: F2P with In-Patch | F35: F2P without In-Patch | G35: Total F2P | H35: SWE-Factory F2P | I35: SWE-bench-Live F2P
A36: 1 | B36: First Batch (80 issues) | C36: =G30+G14 -> 30 | D36: =H30+H14 -> 50 | E36: =J30+J14 -> 9 | F36: =K30+K14 -> 10 | G36: =L30+L14 -> 19 | H36: 11 | I36: 4
A37: 2 | B37: Second Batch (70 issues) | C37: =N30+N14 -> 39 | D37: =O30+O14 -> 31 | E37: =Q30+Q14 -> 1 | F37: =R30+R14 -> 3 | G37: =S30+S14 -> 4 | H37: 0 | I37: 1
A38: 3 | B38: Third Batch (50 issues) | C38: =U30+U14 -> 37 | D38: =V30+V14 -> 13 | E38: =X30+X14 -> 14 | F38: =Y30+Y14 -> 6 | G38: =Z30+Z14 -> 20 | H38: 10 | I38: 1
A39: 4 | B39: Fourth Batch (25 issues) | C39: =AB30+AB14 -> 0 | D39: =AC30+AC14 -> 25 | E39: =AE30+AE14 -> 0 | F39: =AF30+AF14 -> 2 | G39: =AG30+AG14 -> 2 | H39: 0 | I39: 0
B40: TOTAL | C40: =SUM(C36:C39) -> 106 | D40: =SUM(D36:D39) -> 119 | E40: =SUM(E36:E39) -> 24 | F40: =SUM(F36:F39) -> 21 | G40: =SUM(G36:G39) -> 45 | H40: =SUM(H36:H39) -> 21 | I40: =SUM(I36:I39) -> 6
A44: Programming Language Distribution
A46: No | B46: Batch | C46: Total Issues (Python) | D46: Total F2P (Python) | E46: Total Issues (Typescript) | F46: Total F2P (Typescript) | G46: Total Issues (Rust) | H46: Total F2P (Rust)
A47: 1 | B47: First Batch (80 issues) | C47: 73 | D47: 19 | E47: 7 | F47: 0 | G47: 0 | H47: 0
A48: 2 | B48: Second Batch (70 issues) | C48: 53 | D48: 4 | E48: 8 | F48: 0 | G48: 9 | H48: 0
A49: 3 | B49: Third Batch (50 issues) | C49: 50 | D49: 20 | E49: 0 | F49: 0 | G49: 0 | H49: 0
A50: 4 | B50: Fourth Batch (25 issues) | C50: 24 | D50: 2 | E50: 1 | F50: 0 | G50: 0 | H50: 0
B51: TOTAL | C51: =SUM(C47:C50) -> 200 | D51: =SUM(D47:D50) -> 45 | E51: =SUM(E47:E50) -> 16 | F51: =SUM(F47:F50) -> 0 | G51: =SUM(G47:G50) -> 9 | H51: =SUM(H47:H50) -> 0
C55: GPT-4.1-mini | O55: Official price: | P55: $0.4 - input token/1M
P56: $1.6 - output token/1M
A57: No | B57: Pipeline | C57: F2P App (w/ in-Patch) | D57: F2P App (w/o in-patch) | E57: F2P App | F57: F2P Framework (w/ in-Patch) | G57: F2P Framework (w/o in-patch) | H57: F2P Framework | I57: Total F2P (w/ in-patch) | J57: Total F2P (w/o in-patch) | K57: Total F2P | L57: Avg. Duration | M57: Avg. Cost | N57: Avg. Token Consumption | O57: Env. build | P57: Avg. Input Token | Q57: Avg. Output Token
A58: 1 | B58: AgentBug-Smith | C58: =3+0+0+0 -> 3 | D58: =6+3+4+0 -> 13 | E58: =C58+D58 -> 16 | F58: =6+1+14+0 -> 21 | G58: =4+0+2+2 -> 8 | H58: =F58+G58 -> 29 | I58: =C58+F58 -> 24 | J58: =D58+G58 -> 21 | K58: =I58+J58 -> 45 | L58: 58m 10s | M58: =((P58/1000000)*0.4)+((Q58/1000000)*1.6) -> 0.5595124 | N58: =P58+Q58 -> 1287247 | O58: 84 | P58: 1250069 | Q58: 37178 | S58: *calc token by sampling 5 issues
A59: 2 | B59: SWE-Factory | C59: =3+0+0+0 -> 3 | D59: 0 | E59: =C59+D59 -> 3 | F59: =8+0+10+0 -> 18 | G59: 0 | H59: =F59+G59 -> 18 | I59: =C59+F59 -> 21 | J59: =D59+G59 -> 0 | K59: =I59+J59 -> 21 | L59: 24m 54s | O59: 36 | S59: ? This is done using old api key, how are we going to calc the tokens? Sampling?
A60: 3 | B60: SWE-bench-Live | C60: =1+0+0+0 -> 1 | D60: 0 | E60: =C60+D60 -> 1 | F60: =3+1+1+0 -> 5 | G60: 0 | H60: =F60+G60 -> 5 | I60: =C60+F60 -> 6 | J60: =D60+G60 -> 0 | K60: =I60+J60 -> 6 | L60: 47m 44s | O60: 33 | S60: ? This is done using old api key, how are we going to calc the tokens? Sampling?
C64: Deepseek-v3.2 | O64: Official price | P64: $0.28 - input token/1M
P65: $0.4 - output token/1M
A66: No | B66: Pipeline | C66: F2P App (w/ in-Patch) | D66: F2P App (w/o in-patch) | E66: F2P App | F66: F2P Framework (w/ in-Patch) | G66: F2P Framework (w/o in-patch) | H66: F2P Framework | I66: Total F2P (w/ in-patch) | J66: Total F2P (w/o in-patch) | K66: Total F2P | L66: Avg. Duration | M66: Avg. Cost | N66: Avg. Token Consumption | O66: Env. build | P66: Avg. Input Token | Q66: Avg. Output Token
A67: 1 | B67: AgentBug-Smith | M67: =((P67/1000000)*0.28)+((Q67/1000000)*0.4) -> 2.4390618 | N67: =P67+Q67 -> 8667177 | P67: 8565075 | Q67: 102102 | S67: *calc token by sampling 24 issues
A68: 2 | B68: SWE-Factory | C68: 3 | D68: 0 | E68: =C68+D68 -> 3 | F68: 28 | G68: 0 | H68: =F68+G68 -> 28 | I68: =F68+C68 -> 31 | J68: =G68+D68 -> 0 | K68: =I68+J68 -> 31 | L68: 21m 35s | M68: =((P68/1000000)*0.28)+((Q68/1000000)*0.4) -> 0.30701028 | N68: =P68+Q68 -> 1039926 | O68: 44 | P68: 908001 | Q68: 131925 | S68: *calc token using 2nd batch data
A69: 3 | B69: SWE-bench-Live | C69: 0 | D69: 0 | E69: =C69+D69 -> 0 | F69: 1 | G69: 0 | H69: =F69+G69 -> 1 | I69: =F69+C69 -> 1 | J69: =G69+D69 -> 0 | K69: =I69+J69 -> 1 | L69: 85m 41s | O69: 14 | S69: ? This is done using old api key, how are we going to calc the tokens? Sampling?
C73: Kimi-k2.5
A75: No | B75: Pipeline | C75: F2P App (w/ in-Patch) | D75: F2P App (w/o in-patch) | E75: F2P App | F75: F2P Framework (w/ in-Patch) | G75: F2P Framework (w/o in-patch) | H75: F2P Framework | I75: Total F2P (w/ in-patch) | J75: Total F2P (w/o in-patch) | K75: Total F2P | L75: Avg. Duration | M75: Avg. Cost | N75: Avg. Token Consumption | O75: Env. build | P75: Avg. Input Token | Q75: Avg. Output Token
A76: 1 | B76: AgentBug-Smith
A77: 2 | B77: SWE-Factory
A78: 3 | B78: SWE-bench-Live

Sheet Agent Distribution - Deepseek
A1: AGENT FRAMEWORKS
I2: Deepseek-v3.2
A3: No | B3: Repository | C3: Repo link | D3: Language | E3: Stars | F3: License | G3: Total Issues with In-Patch (on 80) | H3: Total Issues without In-Patch (on 80) | I3: Total Issues (on 80) | J3: Total F2P With In-Patch (on 80) | K3: Total F2P Without In-Patch (on 80) | L3: Total F2P (on 80) | M3: 第 13 列 | N3: Total Issues with In-Patch (on 70) | O3: Total Issues without In-Patch (on 70) | P3: Total Issues (on 70) | Q3: Total F2P With In-Patch (on 70) | R3: Total F2P Without In-Patch (on 70) | S3: Total F2P (on 70) | T3: Column 17 | U3: Total Issues with In-Patch (on 50) | V3: Total Issues without In-Patch (on 50) | W3: Total Issues (on 50) | X3: Total F2P With In-Patch (on 50) | Y3: Total F2P Without In-Patch (on 50) | Z3: Total F2P (data: 50) | AA3: Column 17 2 | AB3: Total Issues with In-Patch (on 25) | AC3: Total Issues without In-Patch (on 25) | AD3: Total Issues (on 25) | AE3: Total F2P With In-Patch (on 25) | AF3: Total F2P Without In-Patch (on 25) | AG3: Total F2P (data: 25) | AH3: Column 17 3 | AI3: Total Issues | AJ3: Total F2P
A4: 1 | B4: dapr/dapr-agents | C4: https://github.com/dapr/dapr-agents/ | D4: Python | E4: 650 | F4: Apache-2.0 license | G4: 1 | H4: 2 | I4: =G4+H4 -> 3 | K4: 2 | L4: =J4+K4 -> 2 | N4: 0 | O4: 0 | P4: =N4+O4 -> 0 | S4: =Q4+R4 -> 0 | U4: 0 | V4: 0 | W4: =U4+V4 -> 0 | Z4: =X4+Y4 -> 0 | AD4: =AB4+AC4 -> 0 | AG4: =AE4+AF4 -> 0 | AI4: =I4+P4+W4+AD4 -> 3 | AJ4: =L4+S4+Z4+AG4 -> 2
A5: 2 | B5: VoltAgent/voltagent | C5: https://github.com/VoltAgent/voltagent/ | D5: Typescript | E5: 7.1k | F5: MIT license | G5: 0 | H5: 1 | I5: =G5+H5 -> 1 | L5: =J5+K5 -> 0 | N5: 0 | O5: 0 | P5: =N5+O5 -> 0 | S5: =Q5+R5 -> 0 | U5: 0 | V5: 0 | W5: =U5+V5 -> 0 | Z5: =X5+Y5 -> 0 | AD5: =AB5+AC5 -> 0 | AG5: =AE5+AF5 -> 0 | AI5: =I5+P5+W5+AD5 -> 1 | AJ5: =L5+S5+Z5+AG5 -> 0
A6: 3 | B6: agentscope-ai/agentscope | C6: https://github.com/agentscope-ai/agentscope/ | D6: Python | E6: 22.5k | F6: Apache-2.0 license | G6: 4 | H6: 8 | I6: =G6+H6 -> 12 | J6: 4 | K6: 2 | L6: =J6+K6 -> 6 | N6: 2 | O6: 0 | P6: =N6+O6 -> 2 | Q6: 1 | S6: =Q6+R6 -> 1 | U6: 4 | V6: 6 | W6: =U6+V6 -> 10 | X6: 4 | Y6: 2 | Z6: =X6+Y6 -> 6 | AB6: 0 | AC6: 5 | AD6: =AB6+AC6 -> 5 | AF6: 2 | AG6: =AE6+AF6 -> 2 | AI6: =I6+P6+W6+AD6 -> 29 | AJ6: =L6+S6+Z6+AG6 -> 15
A7: 4 | B7: crewAIInc/crewAI | C7: https://github.com/crewAIInc/crewAI | D7: Python | E7: 47.6k | F7: MIT license | G7: 2 | H7: 5 | I7: =G7+H7 -> 7 | J7: 1 | L7: =J7+K7 -> 1 | N7: 0 | O7: 0 | P7: =N7+O7 -> 0 | S7: =Q7+R7 -> 0 | U7: 26 | V7: 0 | W7: =U7+V7 -> 26 | X7: 14 | Z7: =X7+Y7 -> 14 | AB7: 0 | AC7: 16 | AD7: =AB7+AC7 -> 16 | AG7: =AE7+AF7 -> 0 | AI7: =I7+P7+W7+AD7 -> 49 | AJ7: =L7+S7+Z7+AG7 -> 15
A8: 5 | B8: strands-agents/harness-sdk | C8: https://github.com/strands-agents/sdk-python | D8: Python | E8: 5.5k | F8: Apache-2.0 license | G8: 1 | H8: 0 | I8: =G8+H8 -> 1 | L8: =J8+K8 -> 0 | N8: 0 | O8: 0 | P8: =N8+O8 -> 0 | S8: =Q8+R8 -> 0 | U8: 0 | V8: 0 | W8: =U8+V8 -> 0 | Z8: =X8+Y8 -> 0 | AD8: =AB8+AC8 -> 0 | AG8: =AE8+AF8 -> 0 | AI8: =I8+P8+W8+AD8 -> 1 | AJ8: =L8+S8+Z8+AG8 -> 0
A9: 6 | B9: mastra-ai/mastra | C9: https://github.com/mastra-ai/mastra | D9: Typescript | E9: 22.5k | F9: Apache-2.0 license | G9: 0 | H9: 2 | I9: =G9+H9 -> 2 | L9: =J9+K9 -> 0 | N9: 0 | O9: 0 | P9: =N9+O9 -> 0 | S9: =Q9+R9 -> 0 | U9: 0 | V9: 0 | W9: =U9+V9 -> 0 | Z9: =X9+Y9 -> 0 | AB9: 0 | AC9: 1 | AD9: =AB9+AC9 -> 1 | AG9: =AE9+AF9 -> 0 | AI9: =I9+P9+W9+AD9 -> 3 | AJ9: =L9+S9+Z9+AG9 -> 0
A10: 7 | B10: langchain-ai/langgraph | C10: https://github.com/langchain-ai/langgraph | D10: Python | E10: 28.4k | F10: MIT license | G10: 11 | H10: 2 | I10: =G10+H10 -> 13 | J10: 5 | L10: =J10+K10 -> 5 | N10: 0 | O10: 0 | P10: =N10+O10 -> 0 | S10: =Q10+R10 -> 0 | U10: 0 | V10: 0 | W10: =U10+V10 -> 0 | Z10: =X10+Y10 -> 0 | AD10: =AB10+AC10 -> 0 | AG10: =AE10+AF10 -> 0 | AI10: =I10+P10+W10+AD10 -> 13 | AJ10: =L10+S10+Z10+AG10 -> 5
A11: 8 | B11: langflow-ai/langflow | C11: https://github.com/langflow-ai/langflow | D11: Python | E11: 148k | F11: MIT license | G11: 0 | H11: 0 | I11: =G11+H11 -> 0 | L11: =J11+K11 -> 0 | N11: 9 | O11: 2 | P11: =N11+O11 -> 11 | S11: =Q11+R11 -> 0 | U11: 0 | V11: 0 | W11: =U11+V11 -> 0 | Z11: =X11+Y11 -> 0 | AD11: =AB11+AC11 -> 0 | AG11: =AE11+AF11 -> 0 | AI11: =I11+P11+W11+AD11 -> 11 | AJ11: =L11+S11+Z11+AG11 -> 0
A12: 9 | B12: geekan/MetaGPT | C12: https://github.com/geekan/MetaGPT | D12: Python | E12: 67.9k | F12: MIT license | G12: 1 | H12: 0 | I12: =G12+H12 -> 1 | L12: =J12+K12 -> 0 | N12: 6 | O12: 5 | P12: =N12+O12 -> 11 | S12: =Q12+R12 -> 0 | U12: 0 | V12: 0 | W12: =U12+V12 -> 0 | Z12: =X12+Y12 -> 0 | AD12: =AB12+AC12 -> 0 | AG12: =AE12+AF12 -> 0 | AI12: =I12+P12+W12+AD12 -> 12 | AJ12: =L12+S12+Z12+AG12 -> 0
A13: 10 | B13: tensorzero/tensorzero | C13: https://github.com/tensorzero/tensorzero | D13: Rust | E13: 11.4k | F13: Apache-2.0 license | G13: 0 | H13: 0 | I13: =G13+H13 -> 0 | L13: =J13+K13 -> 0 | N13: 11 | O13: 0 | P13: =N13+O13 -> 11 | S13: =Q13+R13 -> 0 | U13: 0 | V13: 0 | W13: =U13+V13 -> 0 | Z13: =X13+Y13 -> 0 | AD13: =AB13+AC13 -> 0 | AG13: =AE13+AF13 -> 0 | AI13: =I13+P13+W13+AD13 -> 11 | AJ13: =L13+S13+Z13+AG13 -> 0
B14: TOTAL | G14: =SUM(G4:G13) -> 20 | H14: =SUM(H4:H13) -> 20 | I14: =SUM(I4:I13) -> 40 | J14: =SUM(J4:J13) -> 10 | K14: =SUM(K4:K13) -> 4 | L14: =SUM(L4:L13) -> 14 | N14: =SUM(N4:N13) -> 28 | O14: =SUM(O4:O13) -> 7 | P14: =SUM(P4:P13) -> 35 | Q14: =SUM(Q4:Q13) -> 1 | R14: =SUM(R4:R13) -> 0 | S14: =SUM(S4:S13) -> 1 | U14: =SUM(U4:U13) -> 30 | V14: =SUM(V4:V13) -> 6 | W14: =SUM(W4:W13) -> 36 | X14: =SUM(X4:X13) -> 18 | Y14: =SUM(Y4:Y13) -> 2 | Z14: =SUM(Z4:Z13) -> 20 | AB14: =SUM(AB4:AB13) -> 0 | AC14: =SUM(AC4:AC13) -> 22 | AD14: =SUM(AD4:AD13) -> 22 | AE14: =SUM(AE4:AE13) -> 0 | AF14: =SUM(AF4:AF13) -> 2 | AG14: =SUM(AG4:AG13) -> 2 | AI14: =SUM(AI4:AI13) -> 133 | AJ14: =SUM(AJ4:AJ13) -> 37
A17: AGENT APPLICATIONS
I18: Deepseek-v3.2
A19: No | B19: Repository | C19: Repo link | D19: Language | E19: Stars | F19: License | G19: Total Issues with In-Patch (on 80) | H19: Total Issues without In-Patch (on 80) | I19: Total Issues (on 80) | J19: Total F2P In-Patch (on 80) | K19: Total F2P No In-Patch (on 80) | L19: Total F2P (on 80) | M19: 第 13 列 | N19: Total Issues with In-Patch (on 70) | O19: Total Issues without In-Patch (on 70) | P19: Total Issues (on 70) | Q19: Total F2P With In-Patch (on 70) | R19: Total F2P Without In-Patch (on 70) | S19: Total F2P (on 70) | T19: Column 17 | U19: Total Issues with In-Patch (on 50) | V19: Total Issues without In-Patch (on 50) | W19: Total Issues (on 50) | X19: Total F2P With In-Patch (on 50) | Y19: Total F2P Without In-Patch (on 50) | Z19: Total F2P (data: 50) | AA19: Column 17 2 | AB19: Total Issues with In-Patch (on 25) | AC19: Total Issues without In-Patch (on 25) | AD19: Total Issues (on 25) | AE19: Total F2P With In-Patch (on 25) | AF19: Total F2P Without In-Patch (on 25) | AG19: Total F2P (data: 25) | AH19: Column 17 3 | AI19: Total Issues | AJ19: Total F2P
A20: 1 | B20: Significant-Gravitas/AutoGPT | C20: https://github.com/Significant-Gravitas/AutoGPT | D20: Python | E20: 183k | F20: MIT License & PolyForm Shield License 1.0.0 | G20: 4 | H20: 1 | I20: =G20+H20 -> 5 | J20: 1 | K20: 1 | L20: =J20+K20 -> 2 | N20: 0 | O20: 0 | P20: =N20+O20 -> 0 | S20: =Q20+R20 -> 0 | U20: 6 | V20: 2 | W20: =U20+V20 -> 8 | Z20: =X20+Y20 -> 0 | AD20: =AB20+AC20 -> 0 | AG20: =AE20+AF20 -> 0 | AI20: =I20+P20+W20+AD20 -> 13 | AJ20: =L20+S20+Z20+AG20 -> 2
A21: 2 | B21: MLSysOps/MLE-agent | C21: https://github.com/MLSysOps/MLE-agent/ | D21: Python | E21: 1.5k | F21: MIT license | G21: 0 | H21: 9 | I21: =G21+H21 -> 9 | K21: 6 | L21: =J21+K21 -> 6 | N21: 0 | O21: 8 | P21: =N21+O21 -> 8 | R21: 2 | S21: =Q21+R21 -> 2 | U21: 0 | V21: 1 | W21: =U21+V21 -> 1 | Z21: =X21+Y21 -> 0 | AB21: 0 | AC21: 3 | AD21: =AB21+AC21 -> 3 | AF21: 1 | AG21: =AE21+AF21 -> 1 | AI21: =I21+P21+W21+AD21 -> 21 | AJ21: =L21+S21+Z21+AG21 -> 9
A22: 3 | B22: always-further/AgentUp | C22: https://github.com/always-further/AgentUp/ | D22: Python | E22: 100 | F22: Apache-2.0 license | G22: 0 | H22: 2 | I22: =G22+H22 -> 2 | L22: =J22+K22 -> 0 | N22: 0 | O22: 0 | P22: =N22+O22 -> 0 | S22: =Q22+R22 -> 0 | U22: 0 | V22: 0 | W22: =U22+V22 -> 0 | Z22: =X22+Y22 -> 0 | AD22: =AB22+AC22 -> 0 | AG22: =AE22+AF22 -> 0 | AI22: =I22+P22+W22+AD22 -> 2 | AJ22: =L22+S22+Z22+AG22 -> 0
A23: 4 | B23: Canner/WrenAI | C23: https://github.com/Canner/WrenAI | D23: Python | E23: 14.9k | F23: AGPL-3.0 license | G23: 0 | H23: 1 | I23: =G23+H23 -> 1 | L23: =J23+K23 -> 0 | N23: 0 | O23: 0 | P23: =N23+O23 -> 0 | S23: =Q23+R23 -> 0 | U23: 0 | V23: 0 | W23: =U23+V23 -> 0 | Z23: =X23+Y23 -> 0 | AD23: =AB23+AC23 -> 0 | AG23: =AE23+AF23 -> 0 | AI23: =I23+P23+W23+AD23 -> 1 | AJ23: =L23+S23+Z23+AG23 -> 0
A24: 5 | B24: reworkd/AgentGPT | C24: https://github.com/reworkd/AgentGPT | D24: Python | E24: 35.9k | F24: GPL-3.0 license | G24: 1 | H24: 4 | I24: =G24+H24 -> 5 | L24: =J24+K24 -> 0 | N24: 0 | O24: 0 | P24: =N24+O24 -> 0 | S24: =Q24+R24 -> 0 | U24: 0 | V24: 0 | W24: =U24+V24 -> 0 | Z24: =X24+Y24 -> 0 | AD24: =AB24+AC24 -> 0 | AG24: =AE24+AF24 -> 0 | AI24: =I24+P24+W24+AD24 -> 5 | AJ24: =L24+S24+Z24+AG24 -> 0
A25: 6 | B25: Aider-AI/aider | C25: https://github.com/Aider-AI/aider | D25: Python | E25: 42.8k | F25: Apache-2.0 license | G25: 1 | H25: 6 | I25: =G25+H25 -> 7 | J25: 1 | K25: 6 | L25: =J25+K25 -> 7 | N25: 0 | O25: 0 | P25: =N25+O25 -> 0 | S25: =Q25+R25 -> 0 | U25: 0 | V25: 0 | W25: =U25+V25 -> 0 | Z25: =X25+Y25 -> 0 | AD25: =AB25+AC25 -> 0 | AG25: =AE25+AF25 -> 0 | AI25: =I25+P25+W25+AD25 -> 7 | AJ25: =L25+S25+Z25+AG25 -> 7
A26: 7 | B26: ValueCell-ai/valuecell | C26: https://github.com/ValueCell-ai/valuecell | D26: Python | E26: 10.2k | F26: Apache-2.0 license | G26: 0 | H26: 4 | I26: =G26+H26 -> 4 | L26: =J26+K26 -> 0 | N26: 0 | O26: 1 | P26: =N26+O26 -> 1 | S26: =Q26+R26 -> 0 | U26: 0 | V26: 0 | W26: =U26+V26 -> 0 | Z26: =X26+Y26 -> 0 | AD26: =AB26+AC26 -> 0 | AG26: =AE26+AF26 -> 0 | AI26: =I26+P26+W26+AD26 -> 5 | AJ26: =L26+S26+Z26+AG26 -> 0
A27: 8 | B27: AntonOsika/gpt-engineer | C27: https://github.com/AntonOsika/gpt-engineer | D27: Python | E27: 55.2k | F27: MIT license | G27: 4 | H27: 3 | I27: =G27+H27 -> 7 | J27: 3 | K27: 1 | L27: =J27+K27 -> 4 | N27: 4 | O27: 3 | P27: =N27+O27 -> 7 | R27: 1 | S27: =Q27+R27 -> 1 | U27: 1 | V27: 4 | W27: =U27+V27 -> 5 | Y27: 2 | Z27: =X27+Y27 -> 2 | AD27: =AB27+AC27 -> 0 | AG27: =AE27+AF27 -> 0 | AI27: =I27+P27+W27+AD27 -> 19 | AJ27: =L27+S27+Z27+AG27 -> 7
A28: 9 | B28: OpenInterpreter/open-interpreter | C28: https://github.com/OpenInterpreter/open-interpreter | D28: Python | E28: 11.4k | F28: Apache-2.0 license | G28: 0 | H28: 0 | I28: =G28+H28 -> 0 | L28: =J28+K28 -> 0 | N28: 0 | O28: 12 | P28: =N28+O28 -> 12 | R28: 1 | S28: =Q28+R28 -> 1 | U28: 0 | V28: 0 | W28: =U28+V28 -> 0 | Z28: =X28+Y28 -> 0 | AD28: =AB28+AC28 -> 0 | AG28: =AE28+AF28 -> 0 | AI28: =I28+P28+W28+AD28 -> 12 | AJ28: =L28+S28+Z28+AG28 -> 1
A29: 10 | B29: lobehub/lobehub | C29: https://github.com/lobehub/lobehub | D29: Typescript | E29: 77k | F29: Apache-2.0 license | G29: 0 | H29: 0 | I29: =G29+H29 -> 0 | L29: =J29+K29 -> 0 | N29: 7 | O29: 0 | P29: =N29+O29 -> 7 | S29: =Q29+R29 -> 0 | U29: 0 | V29: 0 | W29: =U29+V29 -> 0 | Z29: =X29+Y29 -> 0 | AD29: =AB29+AC29 -> 0 | AG29: =AE29+AF29 -> 0 | AI29: =I29+P29+W29+AD29 -> 7 | AJ29: =L29+S29+Z29+AG29 -> 0
B30: TOTAL | G30: =G29+G28+G27+G26+G25+G24+G23+G22+G21+G20 -> 10 | H30: =H29+H28+H27+H26+H25+H24+H23+H22+H21+H20 -> 30 | I30: =SUM(I20:I29) -> 40 | J30: =SUM(J20:J29) -> 5 | K30: =SUM(K20:K29) -> 14 | L30: =SUM(L20:L29) -> 19 | N30: =SUM(表格_2[Total Issues with In-Patch (on 70)]) -> 11 | O30: =SUM(表格_2[Total Issues without In-Patch (on 70)]) -> 24 | P30: =SUM(P20:P29) -> 35 | Q30: =SUM(Q20:Q29) -> 0 | R30: =SUM(R20:R29) -> 4 | S30: =SUM(S20:S29) -> 4 | U30: =SUM(U20:U29) -> 7 | V30: =SUM(V20:V29) -> 7 | W30: =SUM(W20:W29) -> 14 | X30: =SUM(X20:X29) -> 0 | Y30: =SUM(Y20:Y29) -> 2 | Z30: =SUM(Z20:Z29) -> 2 | AB30: =SUM(表格_2[Total Issues with In-Patch (on 25)]) -> 0 | AC30: =SUM(表格_2[Total Issues without In-Patch (on 25)]) -> 3 | AD30: =SUM(表格_2[Total Issues (on 25)]) -> 3 | AE30: 0 | AF30: =SUM(表格_2[Total F2P Without In-Patch (on 25)]) -> 1 | AG30: =SUM(表格_2[Total F2P (data: 25)]) -> 1 | AI30: =SUM(表格_2[Total Issues]) -> 92 | AJ30: =SUM(表格_2[Total F2P]) -> 26
A33: SUMMARY
A35: No | B35: Batch | C35: Issues with In-Patch | D35: Issues without In-Patch | E35: F2P with In-Patch | F35: F2P without In-Patch | G35: Total F2P | H35: SWE-Factory F2P | I35: SWE-bench-Live F2P
A36: 1 | B36: First Batch (80 issues) | C36: =G14+表格_2[[#TOTALS],[Total Issues with In-Patch (on 80)]] -> 30 | D36: =H14+表格_2[[#TOTALS],[Total Issues without In-Patch (on 80)]] -> 50 | E36: =J14+表格_2[[#TOTALS],[Total F2P In-Patch (on 80)]] -> 15 | F36: =K14+表格_2[[#TOTALS],[Total F2P No In-Patch (on 80)]] -> 18 | G36: =L14+表格_2[[#TOTALS],[Total F2P (on 80)]] -> 33 | H36: 15 | I36: 1
A37: 2 | B37: Second Batch (70 issues) | C37: =N14+表格_2[[#TOTALS],[Total Issues with In-Patch (on 70)]] -> 39 | D37: =O14+表格_2[[#TOTALS],[Total Issues without In-Patch (on 70)]] -> 31 | E37: =Q14+表格_2[[#TOTALS],[Total F2P With In-Patch (on 70)]] -> 1 | F37: =R14+表格_2[[#TOTALS],[Total F2P Without In-Patch (on 70)]] -> 4 | G37: =S14+表格_2[[#TOTALS],[Total F2P (on 70)]] -> 5 | H37: 2 | I37: 0
A38: 3 | B38: Third Batch (50 issues) | C38: =U14+表格_2[[#TOTALS],[Total Issues with In-Patch (on 50)]] -> 37 | D38: =V14+表格_2[[#TOTALS],[Total Issues without In-Patch (on 50)]] -> 13 | E38: =X14+表格_2[[#TOTALS],[Total F2P With In-Patch (on 50)]] -> 18 | F38: =Y14+表格_2[[#TOTALS],[Total F2P Without In-Patch (on 50)]] -> 4 | G38: =Z14+表格_2[[#TOTALS],[Total F2P (data: 50)]] -> 22 | H38: 14 | I38: 0
A39: 4 | B39: Fourth Batch (25 issues) | C39: =AB14+表格_2[[#TOTALS],[Total Issues with In-Patch (on 25)]] -> 0 | D39: =AC14+表格_2[[#TOTALS],[Total Issues without In-Patch (on 25)]] -> 25 | E39: 0 | F39: =AF14+表格_2[[#TOTALS],[Total F2P Without In-Patch (on 25)]] -> 3 | G39: =AG14+表格_2[[#TOTALS],[Total F2P (data: 25)]] -> 3 | H39: 0 | I39: 0
B40: TOTAL | C40: =SUM(C36:C39) -> 106 | D40: =SUM(D36:D39) -> 119 | E40: =SUM(E36:E39) -> 34 | F40: =SUM(F36:F39) -> 29 | G40: =SUM(G36:G39) -> 63 | H40: =SUM(H36:H39) -> 31 | I40: =SUM(I36:I39) -> 1
A44: Programming Language Distribution
A46: No | B46: Batch | C46: Total Issues (Python) | D46: Total F2P (Python) | E46: Total Issues (Typescript) | F46: Total F2P (Typescript) | G46: Total Issues (Rust) | H46: Total F2P (Rust)
A47: 1 | B47: First Batch (80 issues) | C47: 73 | D47: 23 | E47: 7 | F47: 0 | G47: 0 | H47: 0
A48: 2 | B48: Second Batch (70 issues) | C48: 53 | D48: 5 | E48: 8 | F48: 0 | G48: 9 | H48: 0
A49: 3 | B49: Third Batch (50 issues) | C49: 50 | D49: 16 | E49: 0 | F49: 0 | G49: 0 | H49: 0
A50: 4 | B50: Fourth Batch (25 issues) | C50: 24 | D50: 3 | E50: 1 | F50: 0 | G50: 0 | H50: 0
B51: TOTAL | C51: =SUM(C47:C50) -> 200 | D51: =SUM(D47:D50) -> 47 | E51: =SUM(E47:E50) -> 16 | F51: =SUM(F47:F50) -> 0 | G51: =SUM(G47:G50) -> 9 | H51: =SUM(H47:H50) -> 0

Sheet Agent Distribution - Kimi
A1: AGENT FRAMEWORKS
I2: Deepseek-v3.2
A3: No | B3: Repository | C3: Repo link | D3: Language | E3: Stars | F3: License | G3: Total Issues with In-Patch (on 80) | H3: Total Issues without In-Patch (on 80) | I3: Total Issues (on 80) | J3: Total F2P With In-Patch (on 80) | K3: Total F2P Without In-Patch (on 80) | L3: Total F2P (on 80) | M3: 第 13 列 | N3: Total Issues with In-Patch (on 70) | O3: Total Issues without In-Patch (on 70) | P3: Total Issues (on 70) | Q3: Total F2P With In-Patch (on 70) | R3: Total F2P Without In-Patch (on 70) | S3: Total F2P (on 70) | T3: Column 17 | U3: Total Issues with In-Patch (on 50) | V3: Total Issues without In-Patch (on 50) | W3: Total Issues (on 50) | X3: Total F2P With In-Patch (on 50) | Y3: Total F2P Without In-Patch (on 50) | Z3: Total F2P (data: 50) | AA3: Column 17 2 | AB3: Total Issues with In-Patch (on 25) | AC3: Total Issues without In-Patch (on 25) | AD3: Total Issues (on 25) | AE3: Total F2P With In-Patch (on 25) | AF3: Total F2P Without In-Patch (on 25) | AG3: Total F2P (data: 25) | AH3: Column 17 3 | AI3: Total Issues | AJ3: Total F2P
A4: 1 | B4: dapr/dapr-agents | C4: https://github.com/dapr/dapr-agents/ | D4: Python | E4: 650 | F4: Apache-2.0 license | G4: 1 | H4: 2 | I4: =G4+H4 -> 3 | K4: 2 | L4: =J4+K4 -> 2 | N4: 0 | O4: 0 | P4: =N4+O4 -> 0 | S4: =Q4+R4 -> 0 | U4: 0 | V4: 0 | W4: =U4+V4 -> 0 | Z4: =X4+Y4 -> 0 | AD4: =AB4+AC4 -> 0 | AG4: =AE4+AF4 -> 0 | AI4: =I4+P4+W4+AD4 -> 3 | AJ4: =L4+S4+Z4+AG4 -> 2
A5: 2 | B5: VoltAgent/voltagent | C5: https://github.com/VoltAgent/voltagent/ | D5: Typescript | E5: 7.1k | F5: MIT license | G5: 0 | H5: 1 | I5: =G5+H5 -> 1 | L5: =J5+K5 -> 0 | N5: 0 | O5: 0 | P5: =N5+O5 -> 0 | S5: =Q5+R5 -> 0 | U5: 0 | V5: 0 | W5: =U5+V5 -> 0 | Z5: =X5+Y5 -> 0 | AD5: =AB5+AC5 -> 0 | AG5: =AE5+AF5 -> 0 | AI5: =I5+P5+W5+AD5 -> 1 | AJ5: =L5+S5+Z5+AG5 -> 0
A6: 3 | B6: agentscope-ai/agentscope | C6: https://github.com/agentscope-ai/agentscope/ | D6: Python | E6: 22.5k | F6: Apache-2.0 license | G6: 4 | H6: 8 | I6: =G6+H6 -> 12 | J6: 4 | K6: 2 | L6: =J6+K6 -> 6 | N6: 2 | O6: 0 | P6: =N6+O6 -> 2 | Q6: 1 | S6: =Q6+R6 -> 1 | U6: 4 | V6: 6 | W6: =U6+V6 -> 10 | X6: 3 | Z6: =X6+Y6 -> 3 | AB6: 0 | AC6: 5 | AD6: =AB6+AC6 -> 5 | AG6: =AE6+AF6 -> 0 | AI6: =I6+P6+W6+AD6 -> 29 | AJ6: =L6+S6+Z6+AG6 -> 10
A7: 4 | B7: crewAIInc/crewAI | C7: https://github.com/crewAIInc/crewAI | D7: Python | E7: 47.6k | F7: MIT license | G7: 2 | H7: 5 | I7: =G7+H7 -> 7 | J7: 1 | L7: =J7+K7 -> 1 | N7: 0 | O7: 0 | P7: =N7+O7 -> 0 | S7: =Q7+R7 -> 0 | U7: 26 | V7: 0 | W7: =U7+V7 -> 26 | X7: 3 | Z7: =X7+Y7 -> 3 | AB7: 0 | AC7: 16 | AD7: =AB7+AC7 -> 16 | AG7: =AE7+AF7 -> 0 | AI7: =I7+P7+W7+AD7 -> 49 | AJ7: =L7+S7+Z7+AG7 -> 4
A8: 5 | B8: strands-agents/harness-sdk | C8: https://github.com/strands-agents/sdk-python | D8: Python | E8: 5.5k | F8: Apache-2.0 license | G8: 1 | H8: 0 | I8: =G8+H8 -> 1 | J8: 1 | L8: =J8+K8 -> 1 | N8: 0 | O8: 0 | P8: =N8+O8 -> 0 | S8: =Q8+R8 -> 0 | U8: 0 | V8: 0 | W8: =U8+V8 -> 0 | Z8: =X8+Y8 -> 0 | AD8: =AB8+AC8 -> 0 | AG8: =AE8+AF8 -> 0 | AI8: =I8+P8+W8+AD8 -> 1 | AJ8: =L8+S8+Z8+AG8 -> 1
A9: 6 | B9: mastra-ai/mastra | C9: https://github.com/mastra-ai/mastra | D9: Typescript | E9: 22.5k | F9: Apache-2.0 license | G9: 0 | H9: 2 | I9: =G9+H9 -> 2 | L9: =J9+K9 -> 0 | N9: 0 | O9: 0 | P9: =N9+O9 -> 0 | S9: =Q9+R9 -> 0 | U9: 0 | V9: 0 | W9: =U9+V9 -> 0 | Z9: =X9+Y9 -> 0 | AB9: 0 | AC9: 1 | AD9: =AB9+AC9 -> 1 | AG9: =AE9+AF9 -> 0 | AI9: =I9+P9+W9+AD9 -> 3 | AJ9: =L9+S9+Z9+AG9 -> 0
A10: 7 | B10: langchain-ai/langgraph | C10: https://github.com/langchain-ai/langgraph | D10: Python | E10: 28.4k | F10: MIT license | G10: 11 | H10: 2 | I10: =G10+H10 -> 13 | J10: 4 | L10: =J10+K10 -> 4 | N10: 0 | O10: 0 | P10: =N10+O10 -> 0 | S10: =Q10+R10 -> 0 | U10: 0 | V10: 0 | W10: =U10+V10 -> 0 | Z10: =X10+Y10 -> 0 | AD10: =AB10+AC10 -> 0 | AG10: =AE10+AF10 -> 0 | AI10: =I10+P10+W10+AD10 -> 13 | AJ10: =L10+S10+Z10+AG10 -> 4
A11: 8 | B11: langflow-ai/langflow | C11: https://github.com/langflow-ai/langflow | D11: Python | E11: 148k | F11: MIT license | G11: 0 | H11: 0 | I11: =G11+H11 -> 0 | L11: =J11+K11 -> 0 | N11: 9 | O11: 2 | P11: =N11+O11 -> 11 | S11: =Q11+R11 -> 0 | U11: 0 | V11: 0 | W11: =U11+V11 -> 0 | Z11: =X11+Y11 -> 0 | AD11: =AB11+AC11 -> 0 | AG11: =AE11+AF11 -> 0 | AI11: =I11+P11+W11+AD11 -> 11 | AJ11: =L11+S11+Z11+AG11 -> 0
A12: 9 | B12: geekan/MetaGPT | C12: https://github.com/geekan/MetaGPT | D12: Python | E12: 67.9k | F12: MIT license | G12: 1 | H12: 0 | I12: =G12+H12 -> 1 | L12: =J12+K12 -> 0 | N12: 6 | O12: 5 | P12: =N12+O12 -> 11 | S12: =Q12+R12 -> 0 | U12: 0 | V12: 0 | W12: =U12+V12 -> 0 | Z12: =X12+Y12 -> 0 | AD12: =AB12+AC12 -> 0 | AG12: =AE12+AF12 -> 0 | AI12: =I12+P12+W12+AD12 -> 12 | AJ12: =L12+S12+Z12+AG12 -> 0
A13: 10 | B13: tensorzero/tensorzero | C13: https://github.com/tensorzero/tensorzero | D13: Rust | E13: 11.4k | F13: Apache-2.0 license | G13: 0 | H13: 0 | I13: =G13+H13 -> 0 | L13: =J13+K13 -> 0 | N13: 11 | O13: 0 | P13: =N13+O13 -> 11 | S13: =Q13+R13 -> 0 | U13: 0 | V13: 0 | W13: =U13+V13 -> 0 | Z13: =X13+Y13 -> 0 | AD13: =AB13+AC13 -> 0 | AG13: =AE13+AF13 -> 0 | AI13: =I13+P13+W13+AD13 -> 11 | AJ13: =L13+S13+Z13+AG13 -> 0
B14: TOTAL | G14: =SUM(G4:G13) -> 20 | H14: =SUM(H4:H13) -> 20 | I14: =SUM(I4:I13) -> 40 | J14: =SUM(J4:J13) -> 10 | K14: =SUM(K4:K13) -> 4 | L14: =SUM(L4:L13) -> 14 | N14: =SUM(N4:N13) -> 28 | O14: =SUM(O4:O13) -> 7 | P14: =SUM(P4:P13) -> 35 | Q14: =SUM(Q4:Q13) -> 1 | R14: =SUM(R4:R13) -> 0 | S14: =SUM(S4:S13) -> 1 | U14: =SUM(U4:U13) -> 30 | V14: =SUM(V4:V13) -> 6 | W14: =SUM(W4:W13) -> 36 | X14: =SUM(X4:X13) -> 6 | Y14: =SUM(Y4:Y13) -> 0 | Z14: =SUM(Z4:Z13) -> 6 | AB14: =SUM(AB4:AB13) -> 0 | AC14: =SUM(AC4:AC13) -> 22 | AD14: =SUM(AD4:AD13) -> 22 | AE14: =SUM(AE4:AE13) -> 0 | AF14: =SUM(AF4:AF13) -> 0 | AG14: =SUM(AG4:AG13) -> 0 | AI14: =SUM(AI4:AI13) -> 133 | AJ14: =SUM(AJ4:AJ13) -> 21
A17: AGENT APPLICATIONS
I18: Deepseek-v3.2
A19: No | B19: Repository | C19: Repo link | D19: Language | E19: Stars | F19: License | G19: Total Issues with In-Patch (on 80) | H19: Total Issues without In-Patch (on 80) | I19: Total Issues (on 80) | J19: Total F2P In-Patch (on 80) | K19: Total F2P No In-Patch (on 80) | L19: Total F2P (on 80) | M19: 第 13 列 | N19: Total Issues with In-Patch (on 70) | O19: Total Issues without In-Patch (on 70) | P19: Total Issues (on 70) | Q19: Total F2P With In-Patch (on 70) | R19: Total F2P Without In-Patch (on 70) | S19: Total F2P (on 70) | T19: Column 17 | U19: Total Issues with In-Patch (on 50) | V19: Total Issues without In-Patch (on 50) | W19: Total Issues (on 50) | X19: Total F2P With In-Patch (on 50) | Y19: Total F2P Without In-Patch (on 50) | Z19: Total F2P (data: 50) | AA19: Column 17 2 | AB19: Total Issues with In-Patch (on 25) | AC19: Total Issues without In-Patch (on 25) | AD19: Total Issues (on 25) | AE19: Total F2P With In-Patch (on 25) | AF19: Total F2P Without In-Patch (on 25) | AG19: Total F2P (data: 25) | AH19: Column 17 3 | AI19: Total Issues | AJ19: Total F2P
A20: 1 | B20: Significant-Gravitas/AutoGPT | C20: https://github.com/Significant-Gravitas/AutoGPT | D20: Python | E20: 183k | F20: MIT License & PolyForm Shield License 1.0.0 | G20: 4 | H20: 1 | I20: =G20+H20 -> 5 | L20: =J20+K20 -> 0 | N20: 0 | O20: 0 | P20: =N20+O20 -> 0 | S20: =Q20+R20 -> 0 | U20: 6 | V20: 2 | W20: =U20+V20 -> 8 | Z20: =X20+Y20 -> 0 | AD20: =AB20+AC20 -> 0 | AG20: =AE20+AF20 -> 0 | AI20: =I20+P20+W20+AD20 -> 13 | AJ20: =L20+S20+Z20+AG20 -> 0
A21: 2 | B21: MLSysOps/MLE-agent | C21: https://github.com/MLSysOps/MLE-agent/ | D21: Python | E21: 1.5k | F21: MIT license | G21: 0 | H21: 9 | I21: =G21+H21 -> 9 | K21: 5 | L21: =J21+K21 -> 5 | N21: 0 | O21: 8 | P21: =N21+O21 -> 8 | R21: 3 | S21: =Q21+R21 -> 3 | U21: 0 | V21: 1 | W21: =U21+V21 -> 1 | Y21: 1 | Z21: =X21+Y21 -> 1 | AB21: 0 | AC21: 3 | AD21: =AB21+AC21 -> 3 | AF21: 1 | AG21: =AE21+AF21 -> 1 | AI21: =I21+P21+W21+AD21 -> 21 | AJ21: =L21+S21+Z21+AG21 -> 10
A22: 3 | B22: always-further/AgentUp | C22: https://github.com/always-further/AgentUp/ | D22: Python | E22: 100 | F22: Apache-2.0 license | G22: 0 | H22: 2 | I22: =G22+H22 -> 2 | L22: =J22+K22 -> 0 | N22: 0 | O22: 0 | P22: =N22+O22 -> 0 | S22: =Q22+R22 -> 0 | U22: 0 | V22: 0 | W22: =U22+V22 -> 0 | Z22: =X22+Y22 -> 0 | AD22: =AB22+AC22 -> 0 | AG22: =AE22+AF22 -> 0 | AI22: =I22+P22+W22+AD22 -> 2 | AJ22: =L22+S22+Z22+AG22 -> 0
A23: 4 | B23: Canner/WrenAI | C23: https://github.com/Canner/WrenAI | D23: Python | E23: 14.9k | F23: AGPL-3.0 license | G23: 0 | H23: 1 | I23: =G23+H23 -> 1 | L23: =J23+K23 -> 0 | N23: 0 | O23: 0 | P23: =N23+O23 -> 0 | S23: =Q23+R23 -> 0 | U23: 0 | V23: 0 | W23: =U23+V23 -> 0 | Z23: =X23+Y23 -> 0 | AD23: =AB23+AC23 -> 0 | AG23: =AE23+AF23 -> 0 | AI23: =I23+P23+W23+AD23 -> 1 | AJ23: =L23+S23+Z23+AG23 -> 0
A24: 5 | B24: reworkd/AgentGPT | C24: https://github.com/reworkd/AgentGPT | D24: Python | E24: 35.9k | F24: GPL-3.0 license | G24: 1 | H24: 4 | I24: =G24+H24 -> 5 | L24: =J24+K24 -> 0 | N24: 0 | O24: 0 | P24: =N24+O24 -> 0 | S24: =Q24+R24 -> 0 | U24: 0 | V24: 0 | W24: =U24+V24 -> 0 | Z24: =X24+Y24 -> 0 | AD24: =AB24+AC24 -> 0 | AG24: =AE24+AF24 -> 0 | AI24: =I24+P24+W24+AD24 -> 5 | AJ24: =L24+S24+Z24+AG24 -> 0
A25: 6 | B25: Aider-AI/aider | C25: https://github.com/Aider-AI/aider | D25: Python | E25: 42.8k | F25: Apache-2.0 license | G25: 1 | H25: 6 | I25: =G25+H25 -> 7 | K25: 5 | L25: =J25+K25 -> 5 | N25: 0 | O25: 0 | P25: =N25+O25 -> 0 | S25: =Q25+R25 -> 0 | U25: 0 | V25: 0 | W25: =U25+V25 -> 0 | Z25: =X25+Y25 -> 0 | AD25: =AB25+AC25 -> 0 | AG25: =AE25+AF25 -> 0 | AI25: =I25+P25+W25+AD25 -> 7 | AJ25: =L25+S25+Z25+AG25 -> 5
A26: 7 | B26: ValueCell-ai/valuecell | C26: https://github.com/ValueCell-ai/valuecell | D26: Python | E26: 10.2k | F26: Apache-2.0 license | G26: 0 | H26: 4 | I26: =G26+H26 -> 4 | L26: =J26+K26 -> 0 | N26: 0 | O26: 1 | P26: =N26+O26 -> 1 | S26: =Q26+R26 -> 0 | U26: 0 | V26: 0 | W26: =U26+V26 -> 0 | Z26: =X26+Y26 -> 0 | AD26: =AB26+AC26 -> 0 | AG26: =AE26+AF26 -> 0 | AI26: =I26+P26+W26+AD26 -> 5 | AJ26: =L26+S26+Z26+AG26 -> 0
A27: 8 | B27: AntonOsika/gpt-engineer | C27: https://github.com/AntonOsika/gpt-engineer | D27: Python | E27: 55.2k | F27: MIT license | G27: 4 | H27: 3 | I27: =G27+H27 -> 7 | J27: 3 | K27: 1 | L27: =J27+K27 -> 4 | N27: 4 | O27: 3 | P27: =N27+O27 -> 7 | Q27: 1 | R27: 1 | S27: =Q27+R27 -> 2 | U27: 1 | V27: 4 | W27: =U27+V27 -> 5 | Y27: 3 | Z27: =X27+Y27 -> 3 | AD27: =AB27+AC27 -> 0 | AG27: =AE27+AF27 -> 0 | AI27: =I27+P27+W27+AD27 -> 19 | AJ27: =L27+S27+Z27+AG27 -> 9
A28: 9 | B28: OpenInterpreter/open-interpreter | C28: https://github.com/OpenInterpreter/open-interpreter | D28: Python | E28: 11.4k | F28: Apache-2.0 license | G28: 0 | H28: 0 | I28: =G28+H28 -> 0 | L28: =J28+K28 -> 0 | N28: 0 | O28: 12 | P28: =N28+O28 -> 12 | R28: 1 | S28: =Q28+R28 -> 1 | U28: 0 | V28: 0 | W28: =U28+V28 -> 0 | Z28: =X28+Y28 -> 0 | AD28: =AB28+AC28 -> 0 | AG28: =AE28+AF28 -> 0 | AI28: =I28+P28+W28+AD28 -> 12 | AJ28: =L28+S28+Z28+AG28 -> 1
A29: 10 | B29: lobehub/lobehub | C29: https://github.com/lobehub/lobehub | D29: Typescript | E29: 77k | F29: Apache-2.0 license | G29: 0 | H29: 0 | I29: =G29+H29 -> 0 | L29: =J29+K29 -> 0 | N29: 7 | O29: 0 | P29: =N29+O29 -> 7 | S29: =Q29+R29 -> 0 | U29: 0 | V29: 0 | W29: =U29+V29 -> 0 | Z29: =X29+Y29 -> 0 | AD29: =AB29+AC29 -> 0 | AG29: =AE29+AF29 -> 0 | AI29: =I29+P29+W29+AD29 -> 7 | AJ29: =L29+S29+Z29+AG29 -> 0
B30: TOTAL | G30: =G29+G28+G27+G26+G25+G24+G23+G22+G21+G20 -> 10 | H30: =H29+H28+H27+H26+H25+H24+H23+H22+H21+H20 -> 30 | I30: =SUM(I20:I29) -> 40 | J30: =SUM(J20:J29) -> 3 | K30: =SUM(K20:K29) -> 11 | L30: =SUM(L20:L29) -> 14 | N30: =SUM(表格_5[Total Issues with In-Patch (on 70)]) -> 11 | O30: =SUM(表格_5[Total Issues without In-Patch (on 70)]) -> 24 | P30: =SUM(P20:P29) -> 35 | Q30: =SUM(Q20:Q29) -> 1 | R30: =SUM(R20:R29) -> 5 | S30: =SUM(S20:S29) -> 6 | U30: =SUM(U20:U29) -> 7 | V30: =SUM(V20:V29) -> 7 | W30: =SUM(W20:W29) -> 14 | X30: =SUM(X20:X29) -> 0 | Y30: =SUM(Y20:Y29) -> 4 | Z30: =SUM(Z20:Z29) -> 4 | AB30: =SUM(表格_5[Total Issues with In-Patch (on 25)]) -> 0 | AC30: =SUM(表格_5[Total Issues without In-Patch (on 25)]) -> 3 | AD30: =SUM(表格_5[Total Issues (on 25)]) -> 3 | AE30: 0 | AF30: =SUM(表格_5[Total F2P Without In-Patch (on 25)]) -> 1 | AG30: =SUM(表格_5[Total F2P (data: 25)]) -> 1 | AI30: =SUM(表格_5[Total Issues]) -> 92 | AJ30: =SUM(表格_5[Total F2P]) -> 25
A33: SUMMARY
A35: No | B35: Batch | C35: Issues with In-Patch | D35: Issues without In-Patch | E35: F2P with In-Patch | F35: F2P without In-Patch | G35: Total F2P | H35: SWE-Factory F2P | I35: SWE-bench-Live F2P
A36: 1 | B36: First Batch (80 issues) | C36: =G14+表格_5[[#TOTALS],[Total Issues with In-Patch (on 80)]] -> 30 | D36: =H14+表格_5[[#TOTALS],[Total Issues without In-Patch (on 80)]] -> 50 | E36: =J14+表格_5[[#TOTALS],[Total F2P In-Patch (on 80)]] -> 13 | F36: =K14+表格_5[[#TOTALS],[Total F2P No In-Patch (on 80)]] -> 15 | G36: =L14+表格_5[[#TOTALS],[Total F2P (on 80)]] -> 28 | H36: 14 | I36: 5
A37: 2 | B37: Second Batch (70 issues) | C37: =N14+表格_5[[#TOTALS],[Total Issues with In-Patch (on 70)]] -> 39 | D37: =O14+表格_5[[#TOTALS],[Total Issues without In-Patch (on 70)]] -> 31 | E37: =Q14+表格_5[[#TOTALS],[Total F2P With In-Patch (on 70)]] -> 2 | F37: =R14+表格_5[[#TOTALS],[Total F2P Without In-Patch (on 70)]] -> 5 | G37: =S14+表格_5[[#TOTALS],[Total F2P (on 70)]] -> 7 | H37: 0 | I37: 1
A38: 3 | B38: Third Batch (50 issues) | C38: =U14+表格_5[[#TOTALS],[Total Issues with In-Patch (on 50)]] -> 37 | D38: =V14+表格_5[[#TOTALS],[Total Issues without In-Patch (on 50)]] -> 13 | E38: =X14+表格_5[[#TOTALS],[Total F2P With In-Patch (on 50)]] -> 6 | F38: =Y14+表格_5[[#TOTALS],[Total F2P Without In-Patch (on 50)]] -> 4 | G38: =Z14+表格_5[[#TOTALS],[Total F2P (data: 50)]] -> 10 | H38: 5 | I38: 0
A39: 4 | B39: Fourth Batch (25 issues) | C39: =AB14+表格_5[[#TOTALS],[Total Issues with In-Patch (on 25)]] -> 0 | D39: =AC14+表格_5[[#TOTALS],[Total Issues without In-Patch (on 25)]] -> 25 | E39: 0 | F39: =AF14+表格_5[[#TOTALS],[Total F2P Without In-Patch (on 25)]] -> 1 | G39: =AG14+表格_5[[#TOTALS],[Total F2P (data: 25)]] -> 1 | H39: 0 | I39: 0
B40: TOTAL | C40: =SUM(C36:C39) -> 106 | D40: =SUM(D36:D39) -> 119 | E40: =SUM(E36:E39) -> 21 | F40: =SUM(F36:F39) -> 25 | G40: =SUM(G36:G39) -> 46 | H40: =SUM(H36:H39) -> 19 | I40: =SUM(I36:I39) -> 6
A44: Programming Language Distribution
A46: No | B46: Batch | C46: Total Issues (Python) | D46: Total F2P (Python) | E46: Total Issues (Typescript) | F46: Total F2P (Typescript) | G46: Total Issues (Rust) | H46: Total F2P (Rust)
A47: 1 | B47: First Batch (80 issues) | C47: 73 | D47: 17 | E47: 7 | F47: 0 | G47: 0 | H47: 0
A48: 2 | B48: Second Batch (70 issues) | C48: 53 | D48: 6 | E48: 8 | F48: 0 | G48: 9 | H48: 0
A49: 3 | B49: Third Batch (50 issues) | C49: 50 | D49: 5 | E49: 0 | F49: 0 | G49: 0 | H49: 0
A50: 4 | B50: Fourth Batch (25 issues) | C50: 24 | D50: 1 | E50: 1 | F50: 0 | G50: 0 | H50: 0
B51: TOTAL | C51: =SUM(C47:C50) -> 200 | D51: =SUM(D47:D50) -> 29 | E51: =SUM(E47:E50) -> 16 | F51: =SUM(F47:F50) -> 0 | G51: =SUM(G47:G50) -> 9 | H51: =SUM(H47:H50) -> 0

Sheet Summary of Experiments
A1: GPT-4.1-MINI
A3: No | B3: Pipeline/Baseline | C3: F2P on Agent Applications | D3: F2P on Agent Frameworks | E3: Total F2P | F3: F2P In-Patch on Agent Applications | G3: F2P In-Patch on Agent Frameworks | H3: Total F2P With In-Patch | I3: Total F2P Without In-Patch | J3: Env Build | K3: Total Duration | L3: Avg. Duration | M3: Total Cost | N3: Avg. Cost | O3: Total Token
A4: 1 | B4: AgentBug-Smith | C4: 9 | D4: 10 | E4: =C4+D4 -> 19 | F4: 3 | G4: 6 | H4: =F4+G4 -> 9 | I4: =E4-H4 -> 10 | J4: 25 | K4: 66 h 7m 24s | L4: 49 m 35s
A5: 2 | B5: SWE-Factory | C5: 3 | D5: 8 | E5: =C5+D5 -> 11 | F5: 3 | G5: 8 | H5: =F5+G5 -> 11 | I5: 0 | J5: 16 | K5: 2h 12m 8s | L5: 4m 24s
A6: 3 | B6: SWE-Bench-LIVE | C6: 1 | D6: 3 | E6: =C6+D6 -> 4 | F6: 1 | G6: 3 | H6: =F6+G6 -> 4 | I6: 0 | J6: 15 | K6: 17h 26m 24s | L6: 34m 53s
A8: DETAILS F2P
A9: In Patch Test? | B9: Agent Type | C9: AgentBug-Smith (PR #) | D9: SWE-Factory (PR #) | E9: SWE-Bench-LIVE (PR #)
B10: Application | C10: 73
B11: Framework | C11: 76
B12: Framework | C12: 93
A13: Y | B13: Application | C13: 173 | D13: 173
B14: Application | C14: 217
B15: Framework | C15: 279
B16: Framework | C16: 420
A17: Y | B17: Framework | C17: 443 | D17: 443
B18: Application | C18: 703
A19: Y | B19: Framework | C19: 994 | E19: 994
A20: Y | B20: Framework | C20: 1141 | D20: 1141
A21: Y | B21: Application | C21: 1198 | D21: 1198
A22: Y | B22: Application | C22: 1239 | D22: 1239
A23: Y | B23: Framework | C23: 1290 | D23: 1290
A24: Y | B24: Framework | C24: 1279 | D24: 1279 | E24: 1279
B25: Application | C25: 1590
B26: Application | C26: 1852
A27: Y | B27: Framework | C27: 3994 | D27: 3994
B28: Application | C28: 4554
A29: Y | B29: Framework | D29: 4073
A30: Y | B30: Framework | D30: 5798
A31: Y | B31: Framework | D31: 6509
A32: Y | B32: Application | E32: 2616
A33: Y | B33: Framework | E33: 152
A39: No | B39: Pipeline/Baseline | C39: F2P on Agent Applications | D39: F2P on Agent Frameworks | E39: Total F2P | F39: F2P In-Patch on Agent Applications | G39: F2P In-Patch on Agent Frameworks | H39: Total F2P With In-Patch | I39: Total F2P Without In-Patch | J39: Env Build | K39: Total Duration | L39: Avg. Duration | M39: Total Cost | N39: Avg. Cost | O39: Total Token
A40: 1 | B40: AgentBug-Smith | C40: 3 | D40: 1 | E40: =C40+D40 -> 4 | F40: 0 | G40: 1 | H40: =F40+G40 -> 1 | I40: =E40-H40 -> 3 | J40: 19 | K40: 70h 16m 51s | L40: 62m
A41: 2 | B41: SWE-Factory | C41: 0 | D41: 0 | E41: 0 | F41: 0 | G41: 0 | H41: 0 | I41: =E41-H41 -> 0 | J41: 4 | K41: 3h 12m 57s | L41: 4m 57s
A42: 3 | B42: SWE-Bench-LIVE | C42: 0 | D42: 1 | E42: =C42+D42 -> 1 | F42: 0 | G42: 1 | H42: =F42+G42 -> 1 | I42: =E42-H42 -> 0 | J42: 12 | K42: 15h 05m 32s | L42: 23m 13s
A44: DETAILS F2P
A45: In Patch Test? | B45: Agent Type | C45: AgentBug-Smith (PR #) | D45: SWE-Factory (PR #) | E45: SWE-Bench-LIVE (PR #)
B46: Application | C46: 230
B47: Application | C47: 269
B48: Application | C48: 271
A49: Y | B49: Framework | C49: 962 | E49: 962
A55: No | B55: Pipeline/Baseline | C55: F2P on Agent Applications | D55: F2P on Agent Frameworks | E55: Total F2P | F55: F2P In-Patch on Agent Applications | G55: F2P In-Patch on Agent Frameworks | H55: Total F2P With In-Patch | I55: Total F2P Without In-Patch | J55: Env Build | K55: Total Duration | L55: Avg. Duration | M55: Total Cost | N55: Avg. Cost | O55: Total Token
A56: 1 | B56: AgentBug-Smith | C56: 4 | D56: 16 | E56: =C56+D56 -> 20 | F56: 0 | G56: 14 | H56: =F56+G56 -> 14 | I56: =E56-H56 -> 6 | J56: 26 | K56: 44h 54m 14s | L56: 53m 53s
A57: 2 | B57: SWE-Factory | C57: 0 | D57: 10 | E57: =D57+C57 -> 10 | F57: 0 | G57: 10 | H57: =F57+G57 -> 10 | I57: =E57-H57 -> 0 | J57: 16 | K57: 4h 51m 45s | L57: 7m 53s
A58: 3 | B58: SWE-Bench-LIVE | C58: 0 | D58: 1 | E58: =C58+D58 -> 1 | F58: 0 | G58: 1 | H58: =F58+G58 -> 1 | I58: =E58-H58 -> 0 | J58: 6 | K58: 5h 28m 06s | L58: 8m 52s
A60: DETAILS F2P
A61: In Patch Test? | B61: Agent Type | C61: AgentBug-Smith (PR #) | D61: SWE-Factory (PR #) | E61: SWE-Bench-LIVE (PR #)
B62: Application | C62: 40
B63: Application | C63: 187
A64: Y | B64: Framework | C64: 197 | E64: 197
B65: Application | C65: 463
A66: Y | B66: Framework | C66: 1097 | D66: 1097
B67: Application | C67: 1170
B68: Framework | C68: 1298
B69: Framework | C69: 1341
A70: Y | B70: Framework | C70: 1356 | D70: 1356
A71: Y | B71: Framework | C71: 1390
A72: Y | B72: Framework | C72: 1818 | D72: 1818
A73: Y | B73: Framework | C73: Error @pytest.mark.vcr | D73: 2063
A74: Y | B74: Framework | C74: Error @pytest.mark.vcr | D74: 2192
A75: Y | B75: Framework | C75: 2231 | D75: 2231
A76: Y | B76: Framework | C76: 2336
A77: Y | B77: Framework | C77: 2552 | D77: 2552
A78: Y | B78: Framework | C78: 2562
A79: Y | B79: Framework | C79: 3057 | D79: 3057
A80: Y | B80: Framework | C80: 3187
A81: Y | B81: Framework | C81: 3390
A82: Y | B82: Framework | C82: f2f | D82: 3072
A83: Y | B83: Framework | C83: 3839 | D83: 3839
A84: Y | B84: Framework | C84: 3904
A88: No | B88: Pipeline/Baseline | C88: F2P on Agent Applications | D88: F2P on Agent Frameworks | E88: Total F2P | F88: F2P In-Patch on Agent Applications | G88: F2P In-Patch on Agent Frameworks | H88: Total F2P With In-Patch | I88: Total F2P Without In-Patch | J88: Env Build | K88: Total Duration | L88: Avg. Duration | M88: Total Cost | N88: Avg. Cost | O88: Total Token
A89: 1 | B89: AgentBug-Smith | C89: 0 | D89: 2 | E89: =C89+D89 -> 2 | F89: 0 | G89: 0 | H89: =F89+G89 -> 0 | I89: =E89-H89 -> 2 | J89: 14 | K89: 9h 29m 56s | L89: 71m 14s
A90: 2 | B90: SWE-Factory | C90: 0 | D90: 0 | E90: =D90+C90 -> 0 | F90: 0 | G90: 0 | H90: =F90+G90 -> 0 | I90: =E90-H90 -> 0 | J90: 0 | K90: 47s | L90: 47s
A91: 3 | B91: SWE-Bench-LIVE | C91: 0 | D91: 0 | E91: =C91+D91 -> 0 | F91: 0 | G91: 0 | H91: =F91+G91 -> 0 | I91: =E91-H91 -> 0 | J91: 0 | K91: 12s | L91: 12s
A93: DETAILS F2P
A94: In Patch Test? | B94: Agent Type | C94: AgentBug-Smith (PR #) | D94: SWE-Factory (PR #) | E94: SWE-Bench-LIVE (PR #)
B95: Framework | C95: 106
B96: Framework | C96: 1724
A104: DeepSeek-v3.2
A107: No | B107: Pipeline/Baseline | C107: F2P on Agent Applications | D107: F2P on Agent Frameworks | E107: Total F2P | F107: F2P In-Patch on Agent Applications | G107: F2P In-Patch on Agent Frameworks | H107: Total F2P In-Patch | I107: Total F2P Without In-Patch | J107: Env Build | K107: Total Duration | L107: Avg. Duration | M107: Total Cost | N107: Avg. Cost | O107: Total Token
A108: 1 | B108: AgentBug-Smith | C108: 19 | D108: 14 | E108: =C108+D108 -> 33 | F108: 5 | G108: 10 | H108: =F108+G108 -> 15 | I108: =E108-H108 -> 18 | J108: 45 | K108: 88h 34m 56s | L108: 75m 55s
A109: 2 | B109: SWE-Factory | C109: 3 | D109: 12 | E109: =C109+D109 -> 15 | F109: 3 | G109: 12 | H109: =F109+G109 -> 15 | I109: =E109-H109 -> 0 | J109: 19 | K109: 02h 08m 21s | L109: 4m 16s
A110: 3 | B110: SWE-Bench-LIVE | C110: 0 | D110: 1 | E110: =C110+D110 -> 1 | F110: 0 | G110: 1 | H110: =F110+G110 -> 1 | I110: =E110-H110 -> 0 | J110: 10 | K110: 15h 19m 07s | L110: 30m 38s
A112: DETAILS F2P
A113: In Patch Test? | B113: Agent Type | C113: AgentBug-Smith (PR #) | D113: SWE-Factory (PR #) | E113: SWE-Bench-LIVE (PR #) | G113: Root cause
B114: Application | C114: 30
B115: Application | C115: 34
B116: Application | C116: 73
B117: Framework | C117: 76
B118: Framework | C118: 84
B119: Application | C119: 123
A120: Y | B120: Framework | D120: 152 | G120: No module named 'openapi_pydantic.v3.v3_0_3'
A121: Y | B121: Application | C121: 173 | D121: 173
B122: Application | C122: 262
B123: Application | C123: 274
B124: Framework | C124: 279
A125: Y | B125: Application | C125: 409
B126: Framework | C126: 420
A127: Y | B127: Framework | C127: 443 | D127: 443
B128: Application | C128: 703
...

Sheet Misc
A1: Adding openclaw issues (around 10)
A2: Remove claude code
A3: Result in claude code
A5: Focus on openscaffold
A6: Model: claude-opus, latest gpt
A7: deepsek-v3.2
A8: gpt-4.1-mini
A9: claude-sonnet-4-6
A10: kimi-k2.5
A15: Create a script to count input_tokens + output_tokens
A16: Run openclaw on other baseline
A19: 4th key for baseline
A20: CLAUDE-HAIKU-4-5
A23: No | B23: Pipeline/Baseline | C23: F2P on Agent Applications | D23: F2P on Agent Frameworks | E23: Total F2P | F23: F2P In-Patch on Agent Applications | G23: F2P In-Patch on Agent Frameworks | H23: Total F2P In-Patch | I23: Column 15 | J23: Env Build | K23: Total Duration | L23: Avg. Duration | M23: Total Cost | N23: Avg. Cost | O23: Total Token
A24: 1 | B24: AgentBug-Smith
A25: 2 | B25: SWE-Factory | C25: 3 | D25: 7 | E25: =C25+D25 -> 10 | F25: 3 | G25: 7 | H25: =F25+G25 -> 10 | J25: 17 | K25: 1h 44m 4s | L25: 1m 18s | M25: $0.251635 | N25: $0.0251635 | O25: 201511
A26: 3 | B26: SWE-Bench-LIVE
A28: DETAILS F2P
A29: In Patch Test? | B29: Agent Type | C29: AgentBug-Smith (PR #) | D29: SWE-Factory (PR #) | E29: SWE-Bench-LIVE (PR #)
A30: Y | B30: Application | D30: 173
A31: Y | B31: Application | D31: 409
A32: Y | B32: Framework | D32: 443
A33: Y | B33: Framework | D33: 994
A34: Y | B34: Framework | D34: 1141
A35: Y | B35: Application | D35: 1198
A36: Y | B36: Framework | D36: 1290
A37: Y | B37: Framework | D37: 4073
A38: Y | B38: Framework | D38: 5707
A39: Y | B39: Framework | D39: 5798
A43: tuzi-gpt
A44: Total Cost: | B44: $0.578410
A45: Forge cost: | B45: $2.7968288
A47: tuzi-baseline
A48: Cost on backend | B48: $0.092234
A49: Cost on forge | B49: $8.18904864

Sheet List of Agent Repo（副本）
A1: TOTAL DATA: 80
A2: No | B2: Pipeline/Baseline | C2: F2P on Agent Applications | D2: F2P on Agent Frameworks | E2: Total F2P | F2: F2P In-Patch on Agent Applications | G2: F2P In-Patch on Agent Frameworks | H2: Total F2P In-Patch
A3: 1 | B3: AgentBug-Smith | C3: 9 | D3: 10 | E3: =C3+D3 -> 19 | F3: 3 | G3: 6 | H3: =F3+G3 -> 9
A4: 2 | B4: SWE-Factory | C4: 3 | D4: 8 | E4: =C4+D4 -> 11
A5: 3 | B5: SWE-Bench-LIVE | C5: 1 | D5: 3 | E5: =C5+D5 -> 4
B8: AgentBug-Smith | C8: SWE-Factory | D8: SWE-Bench-LIVE
A9: BASELINE
A11: Claude-code-forge
B12: f2p count: 0 f2p issue_urls: env count: 3 env issue_urls: https://github.com/crewAIInc/crewAI/issues/1439 https://github.com/langchain-ai/langgraph/issues/6409 https://github.com/mastra-ai/mastra/issues/6302
A14: SWE-BENCH-LIVE
B15: Classification summary: fail2pass: 1 fail2fail: 0 pass2pass: 0 pass2fail: 0 error: 0 Summary JSON written to '/home/cc/SWE-bench-Live/baseline/sf_judge_f2p_summary.json' [Telemetry] Waiting 5 seconds for API metrics to sync... Ending cost tracker... Recording session end stats... Session usage summary (from 2026-04-07T20:47:41.076552+00:00 to 2026-04-08T02:53:50.293681+00:00): - Total requests: 10 - Input tokens: 244,925 - Output tokens: 677 - Total tokens: 297,826 - Cost: $0.114703 ============================================== SBL PIPELINE FUNNEL REPORT ============================================== 1. Initial JSON map : 40 items 2. RepoLaunch Generated : 1 instances (organize.jsonl) 3. Validated F2P/P2P : 1 instances ============================================== Pipeline Duration : 06:06:11 (21971 total seconds) Master Log File : /home/cc/SWE-bench-Live/logs/runs/pipeline_20260407_204740.log SWE-Factory Judge : /home/cc/SWE-bench-Live/baseline/sf_judge_f2p_summary.json ==============================================
B16: 76 | C16: 173 | D16: 152
B17: 173 | C17: 443 | D17: 994
B18: 279 | C18: 1141 | D18: 1279
B19: 420 | C19: 1198 | D19: 2616
B20: 443 | C20: 1239
B21: 703 | C21: 1279
B22: 994 | C22: 1290
B23: 1198 | C23: 3994
B24: 1239 | C24: 4073
B25: 1279 | C25: 5798
B26: 1290 | C26: 6509
B27: 1852
B28: 3994
B29: 4544
B32: AgentBug-Smith | C32: SWE-Factory | D32: SWE-Bench-LIVE
A33: App | B33: 73 | C33: 173 | D33: 152
A34: Frame | B34: 76 | C34: 443 | D34: 994
A35: Frame | B35: 93 | C35: 1141 | D35: 1279
A36: App v | B36: 173 | C36: 1198 | D36: 2616
A37: App | B37: 217 | C37: 1239
A38: Frame | B38: 279 | C38: 1279
A39: Frame | B39: 420 | C39: 1290
A40: Frame v | B40: 443 | C40: 3994
A41: App | B41: 703 | C41: 4073
A42: Frame v | B42: 994 | C42: 5798
A43: Frame v | B43: 1141 | C43: 6509
A44: App v | B44: 1198
A45: App v | B45: 1239
A46: Frame v | B46: 1290
A47: Frame v | B47: 1279
A48: App | B48: 1590
A49: App | B49: 1852
A50: Frame v | B50: 3994
A51: App | B51: 4554
A54: TOTAL DATA: 70
A55: No | B55: Pipeline/Baseline | C55: F2P on Agent Applications | D55: F2P on Agent Frameworks | E55: Total F2P | F55: F2P In-Patch on Agent Applications | G55: F2P In-Patch on Agent Frameworks | H55: Total F2P In-Patch | I55: Duration | J55: Cost | M55: Initial | N55: Built Instances | O55: F2P
A56: 1 | B56: AgentBug-Smith | C56: 0 | D56: 1 | E56: 1 | F56: 1 | G56: 7 | H56: =F56+G56 -> 8 | M56: 113 | N56: 33 | O56: 14
A57: 2 | B57: SWE-Factory | C57: 0 | D57: 1 | E57: 1 | I57: 5h 44m 12s | J57: $0.037512 | M57: 150 | N57: 15 | O57: 7
A58: 3 | B58: SWE-Bench-LIVE | C58: 0 | D58: 0 | E58: 0 | I58: 17h 32m 07s | J58: $0.265121 | M58: 150 | N58: 1 | O58: 0
A61: In Patch Test? | B61: Agent Type | C61: AgentBug-Smith | D61: SWE-Factory | E61: SWE-Bench-LIVE
A62: Y | B62: Framework | C62: 962 | D62: 962

Sheet New List
A1: No | B1: Agent | C1: Issue No. | D1: Language | E1: Result
A2: 1 | B2: agentscope-ai/agentscope | C2: 441 | D2: Python
A3: 2 | B3: agentscope-ai/agentscope | C3: 2871 | D3: Python
A4: 3 | B4: dapr/dapr-agents | C4: 149 | D4: Python
A5: 4 | B5: dapr/dapr-agents | C5: 209 | D5: Python
A6: 5

Sheet gpt-4.1-mini
A1: No | B1: Agent | C1: Issue No. | D1: Language | E1: Dockerbuild | F1: Test Script | G1: E2E | H1: Result | I1: Debug By | J1: Duration | K1: Token cost
A2: 1 | B2: MLSysOps/MLE-agent | C2: 273 | D2: Python | E2: Y | F2: Y | G2: N | H2: Buggy version: PASS ✗ (should fail!) Fixed version: PASS ✓ Overall: INVALID ✗ | J2: 1069.55 | K2: 0.01782
A3: 2 | B3: githubnext/gh-aw | C3: 1126 | D3: Golang | E3: N | F3: N | G3: N | H3: Fixed version test result: FAIL Output: Traceback (most recent call last): File "/workspace/tests/test1126.py", line 8, in <module> from pkg.workflow.claude_engine import ClaudeEngine ModuleNotFoundError: No module named 'pkg'
A4: 2 | B4: dapr/dapr-agents | C4: 209 | D4: Python | E4: Y | F4: Y | G4: Y | J4: 241.29 | K4: 0.011447
A5: 4 | B5: MLSysOps/MLE-agent | C5: 33 | D5: Python | E5: N | F5: N | G5: N | H5: AttributeError: 'NoneType' object has no attribute 'get'
A6: 3 | B6: MLSysOps/MLE-agent | C6: 56 | D6: Python | E6: Y | F6: Y | G6: N | H6: Fixed version test result: FAIL Output: Dependency Error: cannot import name 'SearchAgent' from 'agent' (/workspace/agent/__init__.py) | J6: 370.58 | K6: 0.020632
A7: 4 | B7: MLSysOps/MLE-agent | C7: 71 | D7: Python | E7: Y | F7: N | G7: N | H7: Traceback (most recent call last): File "/workspace/tests/test71.py", line 127, in <module> test_openai_model_message_check() File "/workspace/tests/test71.py", line 62, in test_openai_model_message_check model.client.chat.completions.create( ^^^^^^^^^^^^^^^^^^^^^^^^^^^^^ AttributeError: 'Chat' object has no attribute 'completions'. Did you mean: 'Completions'? | J7: 869.75 | K7: 0.019957
A8: 5 | B8: dapr/dapr-agents | C8: 83 | D8: Python | E8: Y | F8: Y | G8: N | H8: [Missing dapr full installation] Output: Dependency Error: No module named 'dapr.ext.workflow' | J8: 1022.91 | K8: $0.022099
A9: 6 | B9: MLSysOps/MLE-agent | C9: 121 | D9: Python | E9: Y | F9: Y | G9: Y | J9: 682.75 | K9: 0.019073
A10: 7 | B10: dapr/dapr-agents | C10: 149 | D10: Python | E10: Y | F10: N | G10: N | H10: Traceback (most recent call last): File "/workspace/tests/test149.py", line 17, in <module> from dapr_agents.utils.signal_handlers import add_signal_handlers_cross_platform File "/workspace/dapr_agents/__init__.py", line 1, in <module> from dapr_agents.agents.agent import Agent File "/workspace/dapr_agents/agents/__init__.py", line 1, in <module> from .base import AgentBase File "/workspace/dapr_agents/agents/base.py", line 1, in <module> from dapr_agents.memory import ( File "/workspace/dapr_agents/memory/__init__.py", line 3, in <module> from .vectorstore import ConversationVectorMemory File "/workspace/dapr_agents/memory/vectorstore.py", line 1, in <module> from dapr_agents.storage.vectorstores import VectorStoreBase File "/workspace/dapr_agents/storage/__init__.py", line 2, in <module> from .vectorstores import VectorStoreBase, ChromaVectorStore, PostgresVectorStore File "/workspace/dapr_agents/storage/vectorstores/__init__.py", line 1, in <module> from .base import VectorStoreBase File "/workspace/dapr_agents/storage/vectorstores/base.py", line 2, in <module> from dapr_agents.document.embedder.base import EmbedderBase File "/workspace/dapr_agents/document/__init__.py", line 4, in <module> from .embedder import OpenAIEmbedder, SentenceTransformerEmbedder, NVIDIAEmbedder File "/workspace/dapr_agents/document/embedder/__init__.py", line 1, in <module> from .openai import OpenAIEmbedder File "/workspace/dapr_agents/document/embedder/openai.py", line 2, in <module> from dapr_agents.llm.openai.embeddings import OpenAIEmbeddingClient File "/workspace/dapr_agents/llm/__init__.py", line 13, in <module> from .dapr import DaprChatClient File "/workspace/dapr_agents/llm/dapr/__init__.py", line 1, in <module> from .chat import DaprChatClient File "/workspace/dapr_agents/llm/dapr/chat.py", line 1, in <module> from dapr_agents.llm.dapr.client import DaprInferenceClientBase File "/workspace/dapr_agents/llm/dapr/client.py", line 3, in <module> from dapr.clients import DaprClient File "/usr/local/lib/python3.12/site-packages/dapr/clients/__init__.py", line 24, in <module> from dapr.clients.grpc.client import DaprGrpcClient, InvokeMethodResponse, MetadataTuple File "/usr/local/lib/python3.12/site-packages/dapr/clients/grpc/client.py", line 41, in <module> from dapr.clients.grpc import conversation File "/usr/local/lib/python3.12/site-packages/dapr/clients/grpc/conversation.py", line 28, in <module> from dapr.proto import api_v1 File "/usr/local/lib/python3.12/site-packages/dapr/proto/__init__.py", line 23, in <module> from dapr.proto.common.v1 import common_pb2 as common_v1 File "/usr/local/lib/python3.12/site-packages/dapr/proto/common/v1/common_pb2.py", line 12, in <module> _runtime_version.ValidateProtobufRuntimeVersion( File "/usr/local/lib/python3.12/site-packages/google/protobuf/runtime_version.py", line 100, in ValidateProtobufRuntimeVersion _ReportVersionError( File "/usr/local/lib/python3.12/site-packages/google/protobuf/runtime_version.py", line 50, in _ReportVersionError raise VersionError(msg) google.protobuf.runtime_version.VersionError: Detected incompatible Protobuf Gencode/Runtime versions when loading dapr/proto/common/v1/common.proto: gencode 6.31.1 runtime 5.29.6. Runtime version cannot be older than the linked gencode version. See Protobuf version guarantees at https://protobuf.dev/support/cross-version-runtime-guarantee. | J10: 3221.06 | K10: 0.023768
A11: 8 | B11: MLSysOps/MLE-agent | C11: 174 | D11: Python | E11: Y | F11: Y | G11: N | H11: [HALUCINATION - the module not exist] Output: Dependency Error: No module named 'mle.model.openai' | J11: 582.01 | K11: 0.018424
A12: 9 | B12: crewAIInc/crewAI | C12: 793 | D12: Python | E12: Y | F12: Y | G12: N | H12: [In docker image, the lib folder is at src/crewai/lib. In the original repo, lib is at the root directory] Output: Dependency Error: No module named 'lib' | J12: 1211.32 | K12: 0.01609
A13: 12 | B13: InternLM/lagent | C13: 49 | D13: Python | E13: N | F13: N | G13: N | H13: Output: Traceback (most recent call last): File "/workspace/tests/test49.py", line 8, in <module> from lagent.llms import HFTransformerCasualLM File "/venv/lib/python3.12/site-packages/lagent/__init__.py", line 2, in <module> from .actions import * # noqa: F401, F403 ^^^^^^^^^^^^^^^^^^^^^^ File "/venv/lib/python3.12/site-packages/lagent/actions/__init__.py", line 1, in <module> from .action_executor import ActionExecutor File "/venv/lib/python3.12/site-packages/lagent/actions/action_executor.py", line 3, in <module> from lagent.schema import ActionReturn, ActionValidCode File "/venv/lib/python3.12/site-packages/lagent/schema.py", line 66, in <module> from lmdeploy.serve.turbomind.chatbot import StatusCode ModuleNotFoundError: No module named 'lmdeploy.serve.turbomind'
A14: 10 | B14: modelscope/agentscope | C14: 411 | D14: Python | E14: Y | F14: Y | G14: N | H14: Output: Traceback (most recent call last): File "/workspace/tests/test411.py", line 51, in test_buggy_execute_shell_command result = mock_run("rm -rf /tmp/somepath", shell=True) ^^^^^^^^^^^^^^^^^^^^^^^^^^^^^^^^^^^^^^^^^^^^ File "/workspace/tests/test411.py", line 28, in mock_run raise subprocess.CalledProcessError(returncode=1, cmd=command, output="Command blocked") subprocess.CalledProcessError: Command 'rm -rf /tmp/somepath' returned non-zero exit status 1. During handling of the above exception, another exception occurred: Traceback (most recent call last): File "/workspace/tests/test411.py", line 79, in <module> test_buggy_execute_shell_command() File "/workspace/tests/test411.py", line 55, in test_buggy_execute_shell_command assert False, "Buggy version should NOT block rm -rf" ^^^^^ AssertionError: Buggy version should NOT block rm -rf | J14: 1166.98 | K14: 0.023102
A15: 14 | B15: upsonic/upsonic | C15: 52 | D15: Python | E15: N | F15: N | G15: N | H15: Output: Failed to import target llm module: cannot import name 'agents' from 'gpt_computer_assistant.utils.db' (unknown location)
A16: 11 | B16: RedDotRocket/AgentUp | C16: 313 | D16: Python | E16: Y | F16: Y | G16: Y | J16: 578.16 | K16: 0.003264
A17: 12 | B17: VoltAgent/voltagent | C17: 87 | D17: Typescript | E17: Y | F17: N | G17: N | H17: Dependency Error: No module named 'packages.anthropic_ai' | J17: 1130.6 | K17: 0.008127
A18: 13 | B18: iflytek/astron-agent | C18: 434 | D18: Java | E18: Y | F18: N | G18: N | H18: Output: Traceback (most recent call last): File "/workspace/tests/test434.py", line 42, in <module> test_open_api_schema_port(BUGGY_OPEN_API_SCHEMA) File "/workspace/tests/test434.py", line 26, in test_open_api_schema_port parsed = json.loads(open_api_schema_json) ^^^^^^^^^^^^^^^^^^^^^^^^^^^^^^^^ File "/usr/local/lib/python3.12/json/__init__.py", line 346, in loads return _default_decoder.decode(s) ^^^^^^^^^^^^^^^^^^^^^^^^^^ File "/usr/local/lib/python3.12/json/decoder.py", line 338, in decode obj, end = self.raw_decode(s, idx=_w(s, 0).end()) ^^^^^^^^^^^^^^^^^^^^^^^^^^^^^^^^^^^^^^ File "/usr/local/lib/python3.12/json/decoder.py", line 354, in raw_decode obj, end = self.scan_once(s, idx) ^^^^^^^^^^^^^^^^^^^^^^ json.decoder.JSONDecodeError: Invalid control character at: line 2 column 169 (char 169) | J18: 554.74 | K18: 0.014229
A19: 14 | B19: modelscope/agentscope | C19: 71 | D19: Python | E19: Y | F19: Y | G19: Y | H19: "Buggy version test: ✓ Failed as expected Fixed version test: ✓ Passed as expected ✓ Test verification successful!" | J19: 928.14 | K19: 0.007475
A20: 19 | B20: crewAIInc/crewAI | C20: 799 | D20: Python | E20: N | F20: N | G20: N | H20: Output: Traceback (most recent call last): File "/workspace/tests/test799.py", line 19, in <module> from crewai.agent import Agent ModuleNotFoundError: No module named 'crewai'
A21: 15 | B21: RedDotRocket/AgentUp | C21: 256 | D21: Python | E21: Y | F21: Y | G21: Y | H21: Buggy version test: ✓ Failed as expected Fixed version test: ✓ Passed as expected ✓ Test verification successful! | J21: 950.18 | K21: 0.014523
A22: 16 | B22: iflytek/astron-agent | C22: 538 | D22: Java | E22: Y | F22: N | G22: N | H22: Dependency Error: No module named 'knowledge' | J22: 581.83 | K22: 0.013153
A23: 17 | B23: iflytek/astron-agent | C23: 585 | D23: Java | E23: Y | F23: N | G23: N | H23: Dependency Error: No module named 'workflow' | J23: 776.27 | K23: 0.016431
A24: 18 | B24: modelscope/agentscope | C24: 923 | D24: Python | E24: Y | F24: Y | G24: N | H24: [Hallucination? - there is no _long_term_memory in the repo] Fixed version test result: FAIL Output: Dependency Error: No module named 'src.agentscope.memory._long_term_memory' | J24: 969.25 | K24: 0.015061
A25: 19 | B25: modelscope/agentscope | C25: 91 | D25: Python | E25: Y | F25: N | G25: N | H25: Test output: -------------------------------------------------------------------------------- Verifying image platform... Image architecture: amd64 Cleaned up temporary Dockerfile Trying method 1: python3 /workspace/tests/test91.py Fixed version test result: FAIL Output: 2026-03-12 09:32:24.305 | INFO | agentscope.models:read_model_configs:171 - Load configs for model wrapper: dummy_chat, dummy_image 2026-03-12 09:32:24.308 | INFO | agentscope.utils.monitor:_create_monitor_table:341 - Init [monitor_metrics] as the monitor table 2026-03-12 09:32:24.308 | INFO | agentscope.utils.monitor:_create_monitor_table:342 - Init [monitor_metrics_quota_exceeded] as the monitor trigger 2026-03-12 09:32:24.308 | INFO | agentscope.utils.monitor:__init__:311 - SqliteMonitor initialization completed at [./runs/run_20260312-093223_w7ntj7/agentscope.db] 2026-03-12 09:32:24.309 | INFO | agentscope.models.model:__init__:256 - Initialize model [dummy_chat] 2026-03-12 09:32:24.309 | INFO | agentscope.utils.monitor:register:362 - Register metric [dummy_chat_model.call_counter] to SqliteMonitor with unit [times] and quota [None] 2026-03-12 09:32:24.311 | INFO | agentscope.utils.monitor:register:362 - Register metric [dummy_chat_model.prompt_tokens] to SqliteMonitor with unit [token] and quota [None] 2026-03-12 09:32:24.312 | INFO | agentscope.utils.monitor:register:362 - Register metric [dummy_chat_model.completion_tokens] to SqliteMonitor with unit [token] and quota [None] 2026-03-12 09:32:24.313 | INFO | agentscope.utils.monitor:register:362 - Register metric [dummy_chat_model.total_tokens] to SqliteMonitor with unit [token] and quota [None] /usr/local/lib/python3.12/site-packages/requests/__init__.py:113: RequestsDependencyWarning: urllib3 (2.6.3) or chardet (7.1.0)/charset_normalizer (3.4.5) doesn't match a supported version! warnings.warn( /workspace/src/agentscope/models/gemini_model.py:13: FutureWarning: All support for the `google.generativeai` package has ended. It will no longer be receiving updates or bug fixes. Please switch to the `google.genai` package as soon as possible. See README for more details: https://github.com/google-gemini/deprecated-generative-ai-python/blob/main/data/README.md import google.generativeai as genai Traceback (most recent call last): File "/workspace/tests/test91.py", line 95, in <module> test_dialog_and_text_to_image_agent() File "/workspace/tests/test91.py", line 57, in test_dialog_and_text_to_image_agent agent_image = TextToImageAgent( ^^^^^^^^^^^^^^^^^ File "/workspace/src/agentscope/agents/agent.py", line 21, in __call__ instance = super().__call__(*args, **kwargs) ^^^^^^^^^^^^^^^^^^^^^^^^^^^^^^^^^ TypeError: TextToImageAgent.__init__() got an unexpected keyword argument 'sys_prompt' HEAD is now at 17676eaa Add AS studio usage into web README.md (#81) | J25: 865.2 | K25: 0.021083
A26: 20 | B26: modelscope/agentscope | C26: 441 | D26: Python | E26: Y | F26: N | G26: N | H26: Output: Could not test OllamaChatWrapper.format directly: OllamaChatWrapper.__init__() missing 2 required positional arguments: 'config_name' and 'model_name' | J26: 616.38 | K26: 0.010423
A27: 21 | B27: modelscope/agentscope | C27: 513 | D27: Python | E27: Y | F27: N | G27: N | H27: Fixed version test result: FAIL Output: 2026-03-12 13:20:06.514 | WARNING | agentscope.rpc.rpc_meta:__init__:71 - Class with name [AgentBase] already exists. 2026-03-12 13:20:06.515 | WARNING | agentscope.rpc.rpc_meta:__init__:71 - Class with name [DialogAgent] already exists. 2026-03-12 13:20:06.516 | WARNING | agentscope.rpc.rpc_meta:__init__:71 - Class with name [DictDialogAgent] already exists. 2026-03-12 13:20:06.516 | WARNING | agentscope.rpc.rpc_meta:__init__:71 - Class with name [UserAgent] already exists. 2026-03-12 13:20:06.517 | WARNING | agentscope.rpc.rpc_meta:__init__:71 - Class with name [ReActAgent] already exists. 2026-03-12 13:20:06.517 | WARNING | agentscope.rpc.rpc_meta:__init__:71 - Class with name [LlamaIndexAgent] already exists. 2026-03-12 13:20:06.526 | WARNING | agentscope.rpc.rpc_meta:__init__:71 - Class with name [_SystemPromptTestAgent] already exists. Traceback (most recent call last): File "/workspace/tests/test513.py", line 15, in <module> from src.agentscope.web.workstation.workflow_dag import format_python_code File "/workspace/src/agentscope/__init__.py", line 22, in <module> from ._init import init File "/workspace/src/agentscope/_init.py", line 20, in <module> ASManager() File "/workspace/src/agentscope/manager/_manager.py", line 64, in __init__ self.model = ModelManager() ^^^^^^^^^^^^^^ File "/workspace/src/agentscope/manager/_model.py", line 57, in __init__ self.register_model_wrapper_class(cls, exist_ok=False) File "/workspace/src/agentscope/manager/_model.py", line 208, in register_model_wrapper_class raise TypeError( TypeError: The model wrapper class should inherit from ModelWrapperBase, but got <class 'agentscope.models.post_model.PostAPIChatWrapper'>. | J27: 786.28 | K27: 0.020829
A28: 22 | B28: modelscope/agentscope | C28: 1129 | D28: Python | E28: Y | F28: N | G28: N | H28: Output: Traceback (most recent call last): File "/workspace/tests/test1129.py", line 125, in <module> result_bug = asyncio.run(run_mem0_long_term_memory_with_bug()) ^^^^^^^^^^^^^^^^^^^^^^^^^^^^^^^^^^^^^^^^^^^^^^^^^ File "/usr/local/lib/python3.12/asyncio/runners.py", line 195, in run return runner.run(main) ^^^^^^^^^^^^^^^^ File "/usr/local/lib/python3.12/asyncio/runners.py", line 118, in run return self._loop.run_until_complete(task) ^^^^^^^^^^^^^^^^^^^^^^^^^^^^^^^^^^^ File "/usr/local/lib/python3.12/asyncio/base_events.py", line 691, in run_until_complete return future.result() ^^^^^^^^^^^^^^^ File "/workspace/tests/test1129.py", line 59, in run_mem0_long_term_memory_with_bug long_term_memory = Mem0LongTermMemory( ^^^^^^^^^^^^^^^^^^^ File "/workspace/src/agentscope/memory/_long_term_memory/_mem0/_mem0_long_term_memory.py", line 255, in __init__ self.long_term_working_memory = mem0.AsyncMemory(mem0_config) ^^^^^^^^^^^^^^^^^^^^^^^^^^^^^ File "/usr/local/lib/python3.12/site-packages/mem0/memory/main.py", line 1245, in __init__ self.embedding_model = EmbedderFactory.create( ^^^^^^^^^^^^^^^^^^^^^^^ File "/usr/local/lib/python3.12/site-packages/mem0/utils/factory.py", line 159, in create return embedder_instance(base_config) ^^^^^^^^^^^^^^^^^^^^^^^^^^^^^^ File "/workspace/src/agentscope/memory/_long_term_memory/_mem0/_mem0_utils.py", line 258, in __init__ raise ValueError( ValueError: `model` must be an instance of EmbeddingModelBase | J28: 1037.08 | K28: 0.028044
A29: 23 | B29: modelscope/agentscope | C29: 768 | D29: Python | E29: Y | F29: N | G29: N | H29: [Invalid syntax] File "/workspace/tests/test768.py", line 187 assert version := usage.get("prompt_tokens", None) is not None, "Prompt token count should be present" ^^ SyntaxError: invalid syntax | J29: 871.22 | K29: 0.024735
A30: 24 | B30: crewAIInc/crewAI | C30: 1437 | D30: Python | E30: Y | F30: Y | G30: N | H30: Output: Dependency Error: No module named 'pkg_resources' | J30: 1952.49 | K30: 0.038684
A31: 25 | B31: crewAIInc/crewAI | C31: 1439 | D31: Python | E31: Y | F31: Y | G31: N | H31: [In docker image, the lib folder is at src/crewai/lib. In the original repo, lib is at the root directory] Output: Dependency Error: No module named 'lib' | J31: 1378.92 | K31: 0.007076
A32: 26 | B32: crewAIInc/crewAI | C32: 1445 | D32: Python | E32: Y | F32: Y | G32: N | H32: Output: Dependency Error: No module named 'pkg_resources' | J32: 1074.45 | K32: 0.018823
... A46: 40 | B46: mastra-ai/mastra | C46: 6321 | D46: TS | E46: N | F46: N | G46: N | H46: -------------------- 33 | # Install node dependencies using pnpm 34 | >>> RUN pnpm store prune || true && \ 35 | >>> pnpm install --reporter=append-only || pnpm install --reporter=append-only --verbose 36 | -------------------- ERROR: failed to solve: process "/bin/sh -c pnpm store prune || true && pnpm install --reporter=append-only || pnpm install --reporter=append-only --verbose" did not complete successfully: exit code: 1 HEAD is now at ca69847090 chore: regenerate providers and docs [skip ci] Your branch is up to date with 'origin/main'. | J46: 437.7 | K46: 0.005812
J48: =SUM(J2:J46) -> 36684.26 | K48: =SUM(K2:K46) -> 0.663851
B49: === SUMMARY === | J49: =J48/40 -> 917.1065 | K49: =K48/40 -> 0.016596275
B50: Repositories | C50: {=COUNTA(UNIQUE(B2:B46))-3} -> 10
B51: Total Issues | C51: =COUNTA(B2:B46)-5 -> 40 | J51: 12 min 29 s
B52: Dockerbuild | C52: =COUNTIF(E2:E46, "Y") -> 38
B53: Test Gen | C53: =COUNTIF(F2:F46, "Y") -> 15
B54: E2E | C54: =COUNTIF(G2:G41, "Y") -> 5
B64: Final benchmark: 200-300

Sheet claude-opus-4-6
A1: No | B1: Agent | C1: Issue No. | D1: Language | E1: Dockerbuild | F1: Test Script | G1: E2E | H1: Result | I1: Debug By | J1: Duration | K1: Token cost
A2: 1 | B2: MLSysOps/MLE-agent | C2: 273 | D2: Python | E2: Y | F2: Y | G2: Y | H2: Buggy version: FAIL ✓ Fixed version: PASS ✓ Overall: VALID ✓ ✓ SUCCESS: Test verification passed! → Buggy version FAILed (correct) → Fixed version PASSed (correct) | J2: 841.2 | K2: 2.15151
A3: 2 | B3: dapr/dapr-agents | C3: 209 | D3: Python | E3: Y | F3: N | G3: N | H3: Buggy version test result: FAIL Output: Bug reproduced: No callback fired in buggy orchestrator. test209.py PASSED: callback mechanism reproduced and verified fixed. | J3: 3723.62 | K3: 0.021985
A4: 3 | B4: MLSysOps/MLE-agent | C4: 56 | D4: Python | E4: Y | F4: N | G4: N | J4: 852.13 | K4: 0.00524
A5: 4 | B5: MLSysOps/MLE-agent | C5: 71 | D5: Python | E5: Y | F5: N | G5: N | H5: AttributeError: 'ManualMockProject' object has no attribute 'requirement' | J5: 92.51 | K5: 0.000277
A6: 5 | B6: dapr/dapr-agents | C6: 83 | D6: Python | E6: Y | F6: N | G6: N | H6: File "/workspace/tests/test83.py", line 4, in <module> from dapr_agents.tool.mcp.client import MCPClient, ToolError ModuleNotFoundError: No module named 'dapr_agents' | J6: 1161.74 | K6: 0.012144
A7: 6 | B7: MLSysOps/MLE-agent | C7: 121 | D7: Python | E7: Y | F7: Y | G7: Y | J7: 1332.6 | K7: 0.062477
A8: 7 | B8: dapr/dapr-agents | C8: 149 | D8: Python | E8: Y | F8: N | G8: N | H8: Output: Traceback (most recent call last): File "/workspace/tests/test149.py", line 7, in <module> from dapr_agents.utils import add_signal_handlers_cross_platform File "/app/dapr_agents/__init__.py", line 1, in <module> from dapr_agents.agents.agent import Agent File "/app/dapr_agents/agents/__init__.py", line 1, in <module> from .base import AgentBase File "/app/dapr_agents/agents/base.py", line 1, in <module> from dapr_agents.memory import ( File "/app/dapr_agents/memory/__init__.py", line 1, in <module> from .base import MemoryBase File "/app/dapr_agents/memory/base.py", line 1, in <module> from dapr_agents.types import BaseMessage File "/app/dapr_agents/types/__init__.py", line 1, in <module> from .tools import OAIFunctionDefinition, OAIToolDefinition, ClaudeToolDefinition File "/app/dapr_agents/types/tools.py", line 1, in <module> from pydantic import BaseModel, field_validator, ValidationInfo ModuleNotFoundError: No module named 'pydantic' | J8: 664.96 | K8: 0.01195
A9: 8 | B9: MLSysOps/MLE-agent | C9: 174 | D9: Python | E9: Y | F9: Y | G9: Y | J9: 834.87 | K9: 0.00098
A10: 9 | B10: crewAIInc/crewAI | C10: 793 | D10: Python | E10: Y | F10: N | G10: N | H10: Output: Traceback (most recent call last): File "/workspace/tests/test793.py", line 4, in <module> from crewai.src.crewai.crew import Crew ModuleNotFoundError: No module named 'crewai' | J10: 1501.01 | K10: 0.00677
A11: 10 | B11: modelscope/agentscope | C11: 411 | D11: Python | E11: Y | F11: N | G11: N | H11: /usr/local/lib/python3.12/site-packages/requests/__init__.py:113: RequestsDependencyWarning: urllib3 (2.6.3) or chardet (6.0.0.post1)/charset_normalizer (3.4.4) doesn't match a supported version! warnings.warn( /usr/local/lib/python3.12/site-packages/agentscope/models/gemini_model.py:15: FutureWarning: All support for the `google.generativeai` package has ended. It will no longer be receiving updates or bug fixes. Please switch to the `google.genai` package as soon as possible. See README for more details: https://github.com/google-gemini/deprecated-generative-ai-python/blob/main/data/README.md import google.generativeai as genai Traceback (most recent call last): File "/workspace/tests/test411.py", line 23, in <module> from agentscope.service.execute_code.exec_shell import execute_shell_command File "/usr/local/lib/python3.12/site-packages/agentscope/__init__.py", line 5, in <module> from . import manager File "/usr/local/lib/python3.12/site-packages/agentscope/manager/__init__.py", line 7, in <module> from ._manager import ASManager File "/usr/local/lib/python3.12/site-packages/agentscope/manager/_manager.py", line 11, in <module> from ..logging import LOG_LEVEL, setup_logger File "/usr/local/lib/python3.12/site-packages/agentscope/logging.py", line 12, in <module> from .studio._client import _studio_client File "/usr/local/lib/python3.12/site-packages/agentscope/studio/__init__.py", line 3, in <module> from ._app import init File "/usr/local/lib/python3.12/site-packages/agentscope/studio/_app.py", line 49, in <module> os.makedirs(str(_cache_dir), exist_ok=True) File "<frozen os>", line 215, in makedirs File "<frozen os>", line 225, in makedirs PermissionError: [Errno 13] Permission denied: '/.cache' | J11: 1278.94 | K11: 0.011253
A12: 11 | B12: RedDotRocket/AgentUp | C12: 313 | D12: Python | E12: Y | F12: Y | G12: Y | J12: 883.44 | K12: 0.002516
A13: 12 | B13: VoltAgent/voltagent | C13: 87 | D13: Typescript | E13: Y | F13: N | G13: N | H13: Output: Traceback (most recent call last): File "/workspace/tests/test87.py", line 15, in <module> from packages.core.src import Agent ModuleNotFoundError: No module named 'packages' During handling of the above exception, another exception occurred: Traceback (most recent call last): File "/workspace/tests/test87.py", line 22, in <module> from agent.agent import Agent ModuleNotFoundError: No module named 'agent.agent' | J13: 1181.14 | K13: 0.00586
A14: 13 | B14: iflytek/astron-agent | C14: 434 | D14: Java | E14: Y | F14: N | G14: N | H14: Output: Test failed: Old port should be 18669 but got 18668 | J14: 533.33 | K14: 0.002904
A15: 14 | B15: modelscope/agentscope | C15: 71 | D15: Python | E15: Y | F15: Y | G15: Y | J15: 409.77 | K15: 0.015462
A16: 15 | B16: RedDotRocket/AgentUp | C16: 256 | D16: Python | E16: Y | F16: Y | G16: Y | J16: 951.13 | K16: 0.012965
A17: 16 | B17: iflytek/astron-agent | C17: 538 | D17: Java | E17: N | F17: N | G17: N | H17: ERROR: Test case file was not generated successfully! The test script was stored in core/agent/tests | J17: 403.67 | K17: 0.003979
A18: 17 | B18: iflytek/astron-agent | C18: 585 | D18: Java | E18: N | F18: N | G18: N | H18: ERROR: Test case file was not generated successfully! The test script was stored in core/agent/tests | J18: 379.23 | K18: 0.000549
A19: 18 | B19: modelscope/agentscope | C19: 923 | D19: Python | E19: Y | F19: N | G19: N | H19: Fixed version test result: FAIL Output: Traceback (most recent call last): File "/workspace/tests/test923.py", line 2, in <module> from agentscope.memory._long_term_memory._mem0._mem0_utils import AgentScopeLLM ModuleNotFoundError: No module named 'agentscope.memory._long_term_memory' | J19: 1211.55 | K19: 0.006221
A20: 19 | B20: modelscope/agentscope | C20: 91 | D20: Python | E20: Y | F20: N | G20: N | H20: Fixed version test result: FAIL Output: /usr/local/lib/python3.11/site-packages/requests/__init__.py:113: RequestsDependencyWarning: urllib3 (2.6.3) or chardet (6.0.0.post1)/charset_normalizer (3.4.4) doesn't match a supported version! warnings.warn( /usr/local/lib/python3.11/site-packages/agentscope/models/gemini_model.py:13: FutureWarning: All support for the `google.generativeai` package has ended. It will no longer be receiving updates or bug fixes. Please switch to the `google.genai` package as soon as possible. See README for more details: https://github.com/google-gemini/deprecated-generative-ai-python/blob/main/data/README.md import google.generativeai as genai Traceback (most recent call last): File "/workspace/tests/test91.py", line 2, in <module> from agentscope.agents import TextToImageAgent File "/usr/local/lib/python3.11/site-packages/agentscope/__init__.py", line 5, in <module> from . import agents File "/usr/local/lib/python3.11/site-packages/agentscope/agents/__init__.py", line 7, in <module> from .user_agent import UserAgent File "/usr/local/lib/python3.11/site-packages/agentscope/agents/user_agent.py", line 9, in <module> from agentscope.web.studio.utils import user_input ImportError: cannot import name 'user_input' from 'agentscope.web.studio.utils' (/usr/local/lib/python3.11/site-packages/agentscope/web/studio/utils.py) | J20: 1583.62 | K20: 0.014983
A21: 20 | B21: modelscope/agentscope | C21: 441 | D21: Python | E21: Y | F21: N | G21: N | H21: Traceback (most recent call last): File "/workspace/tests/test441.py", line 76, in <module> asyncio.run(run_buggy_format()) File "/usr/local/lib/python3.12/asyncio/runners.py", line 195, in run return runner.run(main) ^^^^^^^^^^^^^^^^ File "/usr/local/lib/python3.12/asyncio/runners.py", line 118, in run return self._loop.run_until_complete(task) ^^^^^^^^^^^^^^^^^^^^^^^^^^^^^^^^^^^ File "/usr/local/lib/python3.12/asyncio/base_events.py", line 691, in run_until_complete return future.result() ^^^^^^^^^^^^^^^ File "/workspace/tests/test441.py", line 22, in run_buggy_format wrapper = OllamaChatWrapper(model_name="llama3.1") ^^^^^^^^^^^^^^^^^^^^^^^^^^^^^^^^^^^^^^^^ TypeError: OllamaChatWrapper.__init__() missing 1 required positional argument: 'config_name' | J21: 1498.26 | K21: 0.014628
A22: 21 | B22: modelscope/agentscope | C22: 513 | D22: Python | E22: Y | F22: Y | G22: N | H22: Test output: -------------------------------------------------------------------------------- assert code != 0, "Buggy script did not fail with SyntaxError" ^^^^^^^^^ AssertionError: Buggy script did not fail with SyntaxError | J22: 605.53 | K22: 0.011726
A23: 22 | B23: modelscope/agentscope | C23: 1129 | D23: Python | E23: N | F23: N | G23: N | H23: -------------------- 22 | # Copy pyproject.toml if it exists and install dependencies via pip 23 | >>> RUN if [ -f "pyproject.toml" ]; then \ 24 | >>> pip install --upgrade pip && pip install poetry && poetry config virtualenvs.create false && poetry install --no-root; \ 25 | >>> fi 26 | -------------------- ERROR: failed to solve: process "/bin/sh -c if [ -f \"pyproject.toml\" ]; then pip install --upgrade pip && pip install poetry && poetry config virtualenvs.create false && poetry install --no-root; fi" did not complete successfully: exit code: 1 HEAD is now at f6db165 chore(version): bump version from 1.0.16dev to 1.0.16 (#1241) Your branch is behind 'origin/main' by 1 commit, and can be fast-forwarded. (use "git pull" to update your local branch) | J23: 787.08 | K23: 0.011464
A24: 23 | B24: modelscope/agentscope | C24: 768 | D24: Python | E24: Y | F24: N | G24: N | H24: Traceback (most recent call last): File "/workspace/tests/test768.py", line 5, in <module> from agentscope.agent import ReActAgent, UserAgent ModuleNotFoundError: No module named 'agentscope' | J24: 1369.81 | K24: 0.008164
A25: 24 | B25: crewAIInc/crewAI | C25: 1437 | D25: Python | E25: Y | F25: N | G25: N | H25: Output: Traceback (most recent call last): File "/workspace/tests/test1437.py", line 4, in <module> from crewai.experimental.agent_executor import AgentExecutor ModuleNotFoundError: No module named 'crewai' | J25: 1526.31 | K25: 0.013118
A26: 25 | B26: crewAIInc/crewAI | C26: 1439 | D26: Python | E26: N | F26: N | G26: N | H26: -------------------- 31 | 32 | # Install crewai package in editable mode to ensure imports work 33 | >>> RUN pip install --break-system-packages -e . 34 | 35 | # Default command to start a bash shell at /app root -------------------- ERROR: failed to solve: process "/bin/sh -c pip install --break-system-packages -e ." did not complete successfully: exit code: 1 HEAD is now at 51754899 feat: migrate CLI http client from requests to httpx Your branch is behind 'origin/main' by 26 commits, and can be fast-forwarded. | J26: 1328.44 | K26: 0.0084
A27: 26 | B27: crewAIInc/crewAI | C27: 1445 | D27: Python | E27: N | F27: N | G27: N | H27: -------------------- 18 | # Install Python dependencies using pip (this will install dependencies from pyproject.toml) 19 | RUN pip install --upgrade pip setuptools wheel 20 | >>> RUN pip install . 21 | 22 | # Set environment variables for Forge API integration -------------------- ERROR: failed to solve: process "/bin/sh -c pip install ." did not complete successfully: exit code: 1 HEAD is now at 51754899 feat: migrate CLI http client from requests to httpx Your branch is behind 'origin/main' by 26 commits, and can be fast-forwarded. | J27: 853.95 | K27: 0.008984
A28: 27 | B28: modelscope/agentscope | C28: 974 | D28: Python | E28: N | F28: N | G28: N | H28: -------------------- 21 | # Install Python dependencies via poetry (lock file does NOT exist, use poetry install without lock file) 22 | >>> RUN if [ -f "/app/pyproject.toml" ]; then \ 23 | >>> poetry config virtualenvs.create false && poetry install --no-interaction --no-ansi; \ 24 | >>> else echo "No pyproject.toml found, skipping poetry install"; \ 25 | >>> fi 26 | -------------------- ERROR: failed to solve: process "/bin/sh -c if [ -f \"/app/pyproject.toml\" ]; then poetry config virtualenvs.create false && poetry install --no-interaction --no-ansi; else echo \"No pyproject.toml found, skipping poetry install\"; fi" did not complete successfully: exit code: 1 HEAD is now at f6db165 chore(version): bump version from 1.0.16dev to 1.0.16 (#1241) Your branch is behind 'origin/main' by 1 commit, and can be fast-forwarded. | J28: 1403.24 | K28: 0.006598
... A41: 40 | B41: mastra-ai/mastra | C41: 6321 | D41: TS | E41: N | F41: N | G41: N | H41: /bin/bash: python3.10: No such file or directory | J41: 863.89 | K41: 0.022545
J43: =SUM(J2:J41) -> 39947.73 | K43: =SUM(K2:K41) -> 2.560897
B44: === SUMMARY === | J44: =J43/40 -> 998.69325 | K44: =K43/40 -> 0.064022425
B45: Repositories | C45: {=COUNTA(UNIQUE(B2:B41))-3} -> 7
B46: Total Issues | C46: =COUNTA(B2:B41) -> 40 | J46: 17 min 57 s
B47: Dockerbuild | C47: =COUNTIF(E2:E41, "Y") -> 25
B48: Test Gen | C48: =COUNTIF(F2:F41, "Y") -> 9
B49: E2E | C49: =COUNTIF(G2:G36, "Y") -> 6
B59: Final benchmark: 200-300

Sheet deepsek-v3
A1: No | B1: Agent | C1: Issue No. | D1: Language | E1: Dockerbuild | F1: Test Script | G1: E2E | H1: Result | I1: Debug By | J1: Duration | K1: Token cost
A2: 1 | B2: MLSysOps/MLE-agent | C2: 273 | D2: Python | E2: Y | F2: Y | G2: N | H2: Buggy version test: ✗ Unexpectedly passed Fixed version test: ✓ Passed as expected ⚠ Test results do not match expectations | J2: 1922.88 | K2: 0.012128
A3: 2 | B3: dapr/dapr-agents | C3: 209 | D3: Python | E3: Y | F3: N | G3: N | H3: Buggy version test result: FAIL Output: Bug reproduced: No callback fired in buggy orchestrator. test209.py PASSED: callback mechanism reproduced and verified fixed. | J3: 3723.62 | K3: 0.021985
A4: 3 | B4: MLSysOps/MLE-agent | C4: 56 | D4: Python | E4: Y | F4: N | G4: N | J4: 852.13 | K4: 0.00524
A5: 4 | B5: MLSysOps/MLE-agent | C5: 71 | D5: Python | E5: Y | F5: N | G5: N | H5: AttributeError: 'ManualMockProject' object has no attribute 'requirement' | J5: 92.51 | K5: 0.000277
A6: 5 | B6: dapr/dapr-agents | C6: 83 | D6: Python | E6: Y | F6: N | G6: N | H6: File "/workspace/tests/test83.py", line 4, in <module> from dapr_agents.tool.mcp.client import MCPClient, ToolError ModuleNotFoundError: No module named 'dapr_agents' | J6: 1161.74 | K6: 0.012144
A7: 6 | B7: MLSysOps/MLE-agent | C7: 121 | D7: Python | E7: Y | F7: Y | G7: Y | J7: 1332.6 | K7: 0.062477
A8: 7 | B8: dapr/dapr-agents | C8: 149 | D8: Python | E8: Y | F8: N | G8: N | H8: Output: Traceback (most recent call last): File "/workspace/tests/test149.py", line 7, in <module> from dapr_agents.utils import add_signal_handlers_cross_platform File "/app/dapr_agents/__init__.py", line 1, in <module> from dapr_agents.agents.agent import Agent File "/app/dapr_agents/agents/__init__.py", line 1, in <module> from .base import AgentBase File "/app/dapr_agents/agents/base.py", line 1, in <module> from dapr_agents.memory import ( File "/app/dapr_agents/memory/__init__.py", line 1, in <module> from .base import MemoryBase File "/app/dapr_agents/memory/base.py", line 1, in <module> from dapr_agents.types import BaseMessage File "/app/dapr_agents/types/__init__.py", line 1, in <module> from .tools import OAIFunctionDefinition, OAIToolDefinition, ClaudeToolDefinition File "/app/dapr_agents/types/tools.py", line 1, in <module> from pydantic import BaseModel, field_validator, ValidationInfo ModuleNotFoundError: No module named 'pydantic' | J8: 664.96 | K8: 0.01195
A9: 8 | B9: MLSysOps/MLE-agent | C9: 174 | D9: Python | E9: Y | F9: Y | G9: Y | J9: 834.87 | K9: 0.00098
A10: 9 | B10: crewAIInc/crewAI | C10: 793 | D10: Python | E10: Y | F10: N | G10: N | H10: Output: Traceback (most recent call last): File "/workspace/tests/test793.py", line 4, in <module> from crewai.src.crewai.crew import Crew ModuleNotFoundError: No module named 'crewai' | J10: 1501.01 | K10: 0.00677
A11: 10 | B11: modelscope/agentscope | C11: 411 | D11: Python | E11: Y | F11: N | G11: N | H11: /usr/local/lib/python3.12/site-packages/requests/__init__.py:113: RequestsDependencyWarning: urllib3 (2.6.3) or chardet (6.0.0.post1)/charset_normalizer (3.4.4) doesn't match a supported version! warnings.warn( /usr/local/lib/python3.12/site-packages/agentscope/models/gemini_model.py:15: FutureWarning: All support for the `google.generativeai` package has ended. It will no longer be receiving updates or bug fixes. Please switch to the `google.genai` package as soon as possible. See README for more details: https://github.com/google-gemini/deprecated-generative-ai-python/blob/main/data/README.md import google.generativeai as genai Traceback (most recent call last): File "/workspace/tests/test411.py", line 23, in <module> from agentscope.service.execute_code.exec_shell import execute_shell_command File "/usr/local/lib/python3.12/site-packages/agentscope/__init__.py", line 5, in <module> from . import manager File "/usr/local/lib/python3.12/site-packages/agentscope/manager/__init__.py", line 7, in <module> from ._manager import ASManager File "/usr/local/lib/python3.12/site-packages/agentscope/manager/_manager.py", line 11, in <module> from ..logging import LOG_LEVEL, setup_logger File "/usr/local/lib/python3.12/site-packages/agentscope/logging.py", line 12, in <module> from .studio._client import _studio_client File "/usr/local/lib/python3.12/site-packages/agentscope/studio/__init__.py", line 3, in <module> from ._app import init File "/usr/local/lib/python3.12/site-packages/agentscope/studio/_app.py", line 49, in <module> os.makedirs(str(_cache_dir), exist_ok=True) File "<frozen os>", line 215, in makedirs File "<frozen os>", line 225, in makedirs PermissionError: [Errno 13] Permission denied: '/.cache' | J11: 1278.94 | K11: 0.011253
A12: 11 | B12: RedDotRocket/AgentUp | C12: 313 | D12: Python | E12: Y | F12: Y | G12: Y | J12: 883.44 | K12: 0.002516
A13: 12 | B13: VoltAgent/voltagent | C13: 87 | D13: Typescript | E13: Y | F13: N | G13: N | H13: Output: Traceback (most recent call last): File "/workspace/tests/test87.py", line 15, in <module> from packages.core.src import Agent ModuleNotFoundError: No module named 'packages' During handling of the above exception, another exception occurred: Traceback (most recent call last): File "/workspace/tests/test87.py", line 22, in <module> from agent.agent import Agent ModuleNotFoundError: No module named 'agent.agent' | J13: 1181.14 | K13: 0.00586
A14: 13 | B14: iflytek/astron-agent | C14: 434 | D14: Java | E14: Y | F14: N | G14: N | H14: Output: Test failed: Old port should be 18669 but got 18668 | J14: 533.33 | K14: 0.002904
A15: 14 | B15: modelscope/agentscope | C15: 71 | D15: Python | E15: Y | F15: Y | G15: Y | J15: 409.77 | K15: 0.015462
A16: 15 | B16: RedDotRocket/AgentUp | C16: 256 | D16: Python | E16: Y | F16: Y | G16: Y | J16: 951.13 | K16: 0.012965
A17: 16 | B17: iflytek/astron-agent | C17: 538 | D17: Java | E17: N | F17: N | G17: N | H17: ERROR: Test case file was not generated successfully! The test script was stored in core/agent/tests | J17: 403.67 | K17: 0.003979
A18: 17 | B18: iflytek/astron-agent | C18: 585 | D18: Java | E18: N | F18: N | G18: N | H18: ERROR: Test case file was not generated successfully! The test script was stored in core/agent/tests | J18: 379.23 | K18: 0.000549
A19: 18 | B19: modelscope/agentscope | C19: 923 | D19: Python | E19: Y | F19: N | G19: N | H19: Fixed version test result: FAIL Output: Traceback (most recent call last): File "/workspace/tests/test923.py", line 2, in <module> from agentscope.memory._long_term_memory._mem0._mem0_utils import AgentScopeLLM ModuleNotFoundError: No module named 'agentscope.memory._long_term_memory' | J19: 1211.55 | K19: 0.006221
